Workbook

Sheet TB-22
A1: Dynamic Air Engineering (India) Pvt Ltd
A2: No:4, Boopathy Nagar,Industrial Estate,
A3: Keelkattalai,Chennai - 600 117.
A4: CIN: U2912TN2008PTC066303 | E4: 1000
A6: Trial Balance for the period | B6: 01-04-2021 TO 31-03-2022
A8: Particulars | B8: Debit | C8: Credit | E8: Check
A10: Opening Stock | B10: 56896.007 | C10: 0 | E10: =VLOOKUP(A10,'Link Sheet'!A:A,1,0) -> Opening Stock
A11: Ace Metro Enterprises | B11: 234.421 | C11: 0 | E11: =VLOOKUP(A11,'Link Sheet'!A:A,1,0) -> Ace Metro Enterprises
A12: AC Zone Private Limited | B12: 4.543 | C12: 0 | E12: =VLOOKUP(A12,'Link Sheet'!A:A,1,0) -> AC Zone Private Limited
A13: Adithya Wire Mesh Solutions | B13: 167.54 | C13: 0 | E13: =VLOOKUP(A13,'Link Sheet'!A:A,1,0) -> Adithya Wire Mesh Solutions
A14: Advance Paints Pvt Ltd | B14: 0 | C14: 77.88 | E14: =VLOOKUP(A14,'Link Sheet'!A:A,1,0) -> Advance Paints Pvt Ltd
A15: Advance Tax | B15: 3000 | C15: 0 | E15: =VLOOKUP(A15,'Link Sheet'!A:A,1,0) -> Advance Tax
A16: Advertising Expenses | B16: 23.732 | C16: 0 | E16: =VLOOKUP(A16,'Link Sheet'!A:A,1,0) -> Advertising Expenses
A17: Air Clime Engineers | B17: 1.7 | C17: 0 | E17: =VLOOKUP(A17,'Link Sheet'!A:A,1,0) -> Air Clime Engineers
A18: Air Comfort | B18: 40.202 | C18: 0 | E18: =VLOOKUP(A18,'Link Sheet'!A:A,1,0) -> Air Comfort
A19: Airconditioners | B19: 199.784 | C19: 0 | E19: =VLOOKUP(A19,'Link Sheet'!A:A,1,0) -> Airconditioners
A20: Air Cool | B20: 29.058 | C20: 0 | E20: =VLOOKUP(A20,'Link Sheet'!A:A,1,0) -> Air Cool
A21: Airflow Equipments India Pvt Limited | B21: 1048.948 | C21: 0 | E21: =VLOOKUP(A21,'Link Sheet'!A:A,1,0) -> Airflow Equipments India Pvt Limited
... A454: Zita & Company | B454: 0 | C454: 15 | E454: =VLOOKUP(A454,'Link Sheet'!A:A,1,0) -> Zita & Company
A455: Grand Total | B455: =SUM(B10:B454) -> 1040082.1 | C455: =SUM(C10:C454) -> 1040082.1

Sheet Link Sheet
A2: Subschedules to Financial Statements | B2: DEBIT | C2: CREDIT | D2: NETT
A4: SHARE CAPITAL. | D4: =+B4-C4 -> 0
A5: Share Capital | B5: =IF(ISNA(VLOOKUP(A5,'TB-22'!A:C,2,0)),0,VLOOKUP(A5,'TB-22'!A:C,2,0)) -> 0 | C5: =IF(ISNA(VLOOKUP(A5,'TB-22'!A:C,3,0)),0,VLOOKUP(A5,'TB-22'!A:C,3,0)) -> 28500 | D5: =+B5-C5 -> -28500 | F5: =D5 -> -28500
D6: =+B6-C6 -> 0
A7: RESERVES AND SURPLUS | D7: =+B7-C7 -> 0
A8: Share Premium | B8: =IF(ISNA(VLOOKUP(A8,'TB-22'!A:C,2,0)),0,VLOOKUP(A8,'TB-22'!A:C,2,0)) -> 0 | C8: =IF(ISNA(VLOOKUP(A8,'TB-22'!A:C,3,0)),0,VLOOKUP(A8,'TB-22'!A:C,3,0)) -> 16200 | D8: =+B8-C8 -> -16200
D9: =+B9-C9 -> 0
A10: Reserve & Surplus | B10: =IF(ISNA(VLOOKUP(A10,'TB-22'!A:C,2,0)),0,VLOOKUP(A10,'TB-22'!A:C,2,0)) -> 0 | C10: =IF(ISNA(VLOOKUP(A10,'TB-22'!A:C,3,0)),0,VLOOKUP(A10,'TB-22'!A:C,3,0)) -> 39257.515 | D10: =+B10-C10 -> -39257.515 | F10: =SUM(D8:D10) -> -55457.515
D11: =+B11-C11 -> 0
A12: LONG-TERM BORROWINGS | D12: =+B12-C12 -> 0
A13: ( a) Vehicle HP Loans - Banks | D13: =+B13-C13 -> 0
A14: Kotak Bank Vehicle Loan | B14: =IF(ISNA(VLOOKUP(A14,'TB-22'!A:C,2,0)),0,VLOOKUP(A14,'TB-22'!A:C,2,0)) -> 0 | C14: =IF(ISNA(VLOOKUP(A14,'TB-22'!A:C,3,0)),0,VLOOKUP(A14,'TB-22'!A:C,3,0)) -> 209.6 | D14: =+B14-C14 -> -209.6
A15: Indian Bank Vehicle Loan 7145753131 | B15: =IF(ISNA(VLOOKUP(A15,'TB-22'!A:C,2,0)),0,VLOOKUP(A15,'TB-22'!A:C,2,0)) -> 0 | C15: =IF(ISNA(VLOOKUP(A15,'TB-22'!A:C,3,0)),0,VLOOKUP(A15,'TB-22'!A:C,3,0)) -> 683.063 | D15: =+B15-C15 -> -683.063
D16: =+B16-C16 -> 0
A17: (c) Loan from Banks (secured by the immovable proerty and Machineries of the company) | D17: =+B17-C17 -> 0
A18: Indian Bank TL1 A/c No: 6613793057 | B18: =IF(ISNA(VLOOKUP(A18,'TB-22'!A:C,2,0)),0,VLOOKUP(A18,'TB-22'!A:C,2,0)) -> 0 | C18: =IF(ISNA(VLOOKUP(A18,'TB-22'!A:C,3,0)),0,VLOOKUP(A18,'TB-22'!A:C,3,0)) -> 27194.129 | D18: =+B18-C18 -> -27194.129
A19: Indian Bank TL2 A/c No: 6613796127 | B19: =IF(ISNA(VLOOKUP(A19,'TB-22'!A:C,2,0)),0,VLOOKUP(A19,'TB-22'!A:C,2,0)) -> 0 | C19: =IF(ISNA(VLOOKUP(A19,'TB-22'!A:C,3,0)),0,VLOOKUP(A19,'TB-22'!A:C,3,0)) -> 97806.491 | D19: =+B19-C19 -> -97806.491
A20: Indian Bank TL3 GECL A/c No: 6887518087 | B20: =IF(ISNA(VLOOKUP(A20,'TB-22'!A:C,2,0)),0,VLOOKUP(A20,'TB-22'!A:C,2,0)) -> 0 | C20: =IF(ISNA(VLOOKUP(A20,'TB-22'!A:C,3,0)),0,VLOOKUP(A20,'TB-22'!A:C,3,0)) -> 32498.903 | D20: =+B20-C20 -> -32498.903
A21: Inidan Bank TL4 GECL A/c No. 7124472429 | B21: =IF(ISNA(VLOOKUP(A21,'TB-22'!A:C,2,0)),0,VLOOKUP(A21,'TB-22'!A:C,2,0)) -> 0 | C21: =IF(ISNA(VLOOKUP(A21,'TB-22'!A:C,3,0)),0,VLOOKUP(A21,'TB-22'!A:C,3,0)) -> 18516.842 | D21: =+B21-C21 -> -18516.842
D22: =+B22-C22 -> 0
A23: Unsecured Loans | D23: =+B23-C23 -> 0
B24: =IF(ISNA(VLOOKUP(A24,'TB-22'!A:C,2,0)),0,VLOOKUP(A24,'TB-22'!A:C,2,0)) -> 0 | C24: =IF(ISNA(VLOOKUP(A24,'TB-22'!A:C,3,0)),0,VLOOKUP(A24,'TB-22'!A:C,3,0)) -> 0 | D24: =+B24-C24 -> 0
D25: =+B25-C25 -> 0 | F25: =SUM(D14:D25) -> -176909.03
A26: DEFERRED TAX ASSETS/(LIABILITIES) (NET) | D26: =+B26-C26 -> 0
A27: Deferrd Tax Liability | B27: =IF(ISNA(VLOOKUP(A27,'TB-22'!A:C,2,0)),0,VLOOKUP(A27,'TB-22'!A:C,2,0)) -> 0 | C27: =IF(ISNA(VLOOKUP(A27,'TB-22'!A:C,3,0)),0,VLOOKUP(A27,'TB-22'!A:C,3,0)) -> 4666.3068 | D27: =+B27-C27 -> -4666.3068 | F27: =D27 -> -4666.3068
D28: =+B28-C28 -> 0
A29: LONG-TERM PROVISIONS | D29: =+B29-C29 -> 0
A30: Provision for Gratuity | B30: =IF(ISNA(VLOOKUP(A30,'TB-22'!A:C,2,0)),0,VLOOKUP(A30,'TB-22'!A:C,2,0)) -> 0 | C30: =IF(ISNA(VLOOKUP(A30,'TB-22'!A:C,3,0)),0,VLOOKUP(A30,'TB-22'!A:C,3,0)) -> 742.962 | D30: =+B30-C30 -> -742.962 | F30: =D30 -> -742.962
D31: =+B31-C31 -> 0
A32: SHORT-TERM BORROWINGS | D32: =+B32-C32 -> 0
A33: Indian Bank OCC A/c No:6613788934 | B33: =IF(ISNA(VLOOKUP(A33,'TB-22'!A:C,2,0)),0,VLOOKUP(A33,'TB-22'!A:C,2,0)) -> 0 | C33: =IF(ISNA(VLOOKUP(A33,'TB-22'!A:C,3,0)),0,VLOOKUP(A33,'TB-22'!A:C,3,0)) -> 37687.912 | D33: =+B33-C33 -> -37687.912 | F33: =D33 -> -37687.912
A34: NSIC - Bill Discounting Account | B34: =IF(ISNA(VLOOKUP(A34,'TB-22'!A:C,2,0)),0,VLOOKUP(A34,'TB-22'!A:C,2,0)) -> 0 | C34: =IF(ISNA(VLOOKUP(A34,'TB-22'!A:C,3,0)),0,VLOOKUP(A34,'TB-22'!A:C,3,0)) -> 29505.835 | D34: =+B34-C34 -> -29505.835
D35: =+B35-C35 -> 0
A36: TRADE PAYABLES | D36: =+B36-C36 -> 0
A37: (i) Trade payables - Related Party | D37: =+B37-C37 -> 0
A38: Karthik Industries | B38: =IF(ISNA(VLOOKUP(A38,'TB-22'!A:C,2,0)),0,VLOOKUP(A38,'TB-22'!A:C,2,0)) -> 0 | C38: =IF(ISNA(VLOOKUP(A38,'TB-22'!A:C,3,0)),0,VLOOKUP(A38,'TB-22'!A:C,3,0)) -> 7419.6566 | D38: =+B38-C38 -> -7419.6566
A39: (ii) Payables - For Capital expenses | D39: =+B39-C39 -> 0
A40: Naga Welders | B40: =IF(ISNA(VLOOKUP(A40,'TB-22'!A:C,2,0)),0,VLOOKUP(A40,'TB-22'!A:C,2,0)) -> 0 | C40: =IF(ISNA(VLOOKUP(A40,'TB-22'!A:C,3,0)),0,VLOOKUP(A40,'TB-22'!A:C,3,0)) -> 1500.622 | D40: =+B40-C40 -> -1500.622
A41: K2 Cranes & Components P Ltd | B41: =IF(ISNA(VLOOKUP(A41,'TB-22'!A:C,2,0)),0,VLOOKUP(A41,'TB-22'!A:C,2,0)) -> 0 | C41: =IF(ISNA(VLOOKUP(A41,'TB-22'!A:C,3,0)),0,VLOOKUP(A41,'TB-22'!A:C,3,0)) -> 220.524 | D41: =+B41-C41 -> -220.524
A42: Pacific Weld Systems Pvt Ltd | B42: =IF(ISNA(VLOOKUP(A42,'TB-22'!A:C,2,0)),0,VLOOKUP(A42,'TB-22'!A:C,2,0)) -> 0 | C42: =IF(ISNA(VLOOKUP(A42,'TB-22'!A:C,3,0)),0,VLOOKUP(A42,'TB-22'!A:C,3,0)) -> 4.814 | D42: =+B42-C42 -> -4.814
A43: (iii) Raw Material Creditors
A44: Advance Paints Pvt Ltd | B44: =IF(ISNA(VLOOKUP(A44,'TB-22'!A:C,2,0)),0,VLOOKUP(A44,'TB-22'!A:C,2,0)) -> 0 | C44: =IF(ISNA(VLOOKUP(A44,'TB-22'!A:C,3,0)),0,VLOOKUP(A44,'TB-22'!A:C,3,0)) -> 77.88 | D44: =+B44-C44 -> -77.88
A45: Air Water India Private Limited | B45: =IF(ISNA(VLOOKUP(A45,'TB-22'!A:C,2,0)),0,VLOOKUP(A45,'TB-22'!A:C,2,0)) -> 0 | C45: =IF(ISNA(VLOOKUP(A45,'TB-22'!A:C,3,0)),0,VLOOKUP(A45,'TB-22'!A:C,3,0)) -> 27.73 | D45: =+B45-C45 -> -27.73
A46: A.K.Steel & Traders | B46: =IF(ISNA(VLOOKUP(A46,'TB-22'!A:C,2,0)),0,VLOOKUP(A46,'TB-22'!A:C,2,0)) -> 0 | C46: =IF(ISNA(VLOOKUP(A46,'TB-22'!A:C,3,0)),0,VLOOKUP(A46,'TB-22'!A:C,3,0)) -> 74.316 | D46: =+B46-C46 -> -74.316
A47: Alomex Profiles Pvt Ltd | B47: =IF(ISNA(VLOOKUP(A47,'TB-22'!A:C,2,0)),0,VLOOKUP(A47,'TB-22'!A:C,2,0)) -> 0 | C47: =IF(ISNA(VLOOKUP(A47,'TB-22'!A:C,3,0)),0,VLOOKUP(A47,'TB-22'!A:C,3,0)) -> 3379.656 | D47: =+B47-C47 -> -3379.656
A48: Aluminium Sales Corporation | B48: =IF(ISNA(VLOOKUP(A48,'TB-22'!A:C,2,0)),0,VLOOKUP(A48,'TB-22'!A:C,2,0)) -> 0 | C48: =IF(ISNA(VLOOKUP(A48,'TB-22'!A:C,3,0)),0,VLOOKUP(A48,'TB-22'!A:C,3,0)) -> 613.523 | D48: =+B48-C48 -> -613.523
A49: Anu Industries | B49: =IF(ISNA(VLOOKUP(A49,'TB-22'!A:C,2,0)),0,VLOOKUP(A49,'TB-22'!A:C,2,0)) -> 0 | C49: =IF(ISNA(VLOOKUP(A49,'TB-22'!A:C,3,0)),0,VLOOKUP(A49,'TB-22'!A:C,3,0)) -> 16.697 | D49: =+B49-C49 -> -16.697
A50: Aston Packaging Solutions | B50: =IF(ISNA(VLOOKUP(A50,'TB-22'!A:C,2,0)),0,VLOOKUP(A50,'TB-22'!A:C,2,0)) -> 0 | C50: =IF(ISNA(VLOOKUP(A50,'TB-22'!A:C,3,0)),0,VLOOKUP(A50,'TB-22'!A:C,3,0)) -> 43.75 | D50: =+B50-C50 -> -43.75
A51: Atlas Tools Suppliers | B51: =IF(ISNA(VLOOKUP(A51,'TB-22'!A:C,2,0)),0,VLOOKUP(A51,'TB-22'!A:C,2,0)) -> 0 | C51: =IF(ISNA(VLOOKUP(A51,'TB-22'!A:C,3,0)),0,VLOOKUP(A51,'TB-22'!A:C,3,0)) -> 165.238 | D51: =+B51-C51 -> -165.238
A52: Austopearl Foundry Technologies | B52: =IF(ISNA(VLOOKUP(A52,'TB-22'!A:C,2,0)),0,VLOOKUP(A52,'TB-22'!A:C,2,0)) -> 0 | C52: =IF(ISNA(VLOOKUP(A52,'TB-22'!A:C,3,0)),0,VLOOKUP(A52,'TB-22'!A:C,3,0)) -> 24.155 | D52: =+B52-C52 -> -24.155
A53: Automotive Rubber Sealings & Coatings | B53: =IF(ISNA(VLOOKUP(A53,'TB-22'!A:C,2,0)),0,VLOOKUP(A53,'TB-22'!A:C,2,0)) -> 0 | C53: =IF(ISNA(VLOOKUP(A53,'TB-22'!A:C,3,0)),0,VLOOKUP(A53,'TB-22'!A:C,3,0)) -> 943.908 | D53: =+B53-C53 -> -943.908
A54: Chennai Bearing Centre | B54: =IF(ISNA(VLOOKUP(A54,'TB-22'!A:C,2,0)),0,VLOOKUP(A54,'TB-22'!A:C,2,0)) -> 0 | C54: =IF(ISNA(VLOOKUP(A54,'TB-22'!A:C,3,0)),0,VLOOKUP(A54,'TB-22'!A:C,3,0)) -> 62.67 | D54: =+B54-C54 -> -62.67
A55: Chennai Steel Tubes | B55: =IF(ISNA(VLOOKUP(A55,'TB-22'!A:C,2,0)),0,VLOOKUP(A55,'TB-22'!A:C,2,0)) -> 0 | C55: =IF(ISNA(VLOOKUP(A55,'TB-22'!A:C,3,0)),0,VLOOKUP(A55,'TB-22'!A:C,3,0)) -> 0.685 | D55: =+B55-C55 -> -0.685
... A101: Virwadia Metal and Alloys | B101: =IF(ISNA(VLOOKUP(A101,'TB-22'!A:C,2,0)),0,VLOOKUP(A101,'TB-22'!A:C,2,0)) -> 0 | C101: =IF(ISNA(VLOOKUP(A101,'TB-22'!A:C,3,0)),0,VLOOKUP(A101,'TB-22'!A:C,3,0)) -> 2.969 | D101: =+B101-C101 -> -2.969
A102: Other Payables | D102: =+B102-C102 -> 0
A103: A.P.R Engineering | B103: =IF(ISNA(VLOOKUP(A103,'TB-22'!A:C,2,0)),0,VLOOKUP(A103,'TB-22'!A:C,2,0)) -> 0 | C103: =IF(ISNA(VLOOKUP(A103,'TB-22'!A:C,3,0)),0,VLOOKUP(A103,'TB-22'!A:C,3,0)) -> 75.514 | D103: =+B103-C103 -> -75.514
A104: Airmech Engineers | B104: =IF(ISNA(VLOOKUP(A104,'TB-22'!A:C,2,0)),0,VLOOKUP(A104,'TB-22'!A:C,2,0)) -> 0 | C104: =IF(ISNA(VLOOKUP(A104,'TB-22'!A:C,3,0)),0,VLOOKUP(A104,'TB-22'!A:C,3,0)) -> 4.524 | D104: =+B104-C104 -> -4.524
A105: Annai Water Supply | B105: =IF(ISNA(VLOOKUP(A105,'TB-22'!A:C,2,0)),0,VLOOKUP(A105,'TB-22'!A:C,2,0)) -> 0 | C105: =IF(ISNA(VLOOKUP(A105,'TB-22'!A:C,3,0)),0,VLOOKUP(A105,'TB-22'!A:C,3,0)) -> 5 | D105: =+B105-C105 -> -5
A106: Aravind Engineering Works | B106: =IF(ISNA(VLOOKUP(A106,'TB-22'!A:C,2,0)),0,VLOOKUP(A106,'TB-22'!A:C,2,0)) -> 0 | C106: =IF(ISNA(VLOOKUP(A106,'TB-22'!A:C,3,0)),0,VLOOKUP(A106,'TB-22'!A:C,3,0)) -> 44.571 | D106: =+B106-C106 -> -44.571
A107: Bharathi Power Tools & Service Centre | B107: =IF(ISNA(VLOOKUP(A107,'TB-22'!A:C,2,0)),0,VLOOKUP(A107,'TB-22'!A:C,2,0)) -> 0 | C107: =IF(ISNA(VLOOKUP(A107,'TB-22'!A:C,3,0)),0,VLOOKUP(A107,'TB-22'!A:C,3,0)) -> 3.1 | D107: =+B107-C107 -> -3.1
A108: Bright Aluminium | B108: =IF(ISNA(VLOOKUP(A108,'TB-22'!A:C,2,0)),0,VLOOKUP(A108,'TB-22'!A:C,2,0)) -> 0 | C108: =IF(ISNA(VLOOKUP(A108,'TB-22'!A:C,3,0)),0,VLOOKUP(A108,'TB-22'!A:C,3,0)) -> 30.659 | D108: =+B108-C108 -> -30.659
A109: BSNL Telephones | B109: =IF(ISNA(VLOOKUP(A109,'TB-22'!A:C,2,0)),0,VLOOKUP(A109,'TB-22'!A:C,2,0)) -> 0 | C109: =IF(ISNA(VLOOKUP(A109,'TB-22'!A:C,3,0)),0,VLOOKUP(A109,'TB-22'!A:C,3,0)) -> 0.691 | D109: =+B109-C109 -> -0.691
A110: Burhani Industrial Supplies | B110: =IF(ISNA(VLOOKUP(A110,'TB-22'!A:C,2,0)),0,VLOOKUP(A110,'TB-22'!A:C,2,0)) -> 0 | C110: =IF(ISNA(VLOOKUP(A110,'TB-22'!A:C,3,0)),0,VLOOKUP(A110,'TB-22'!A:C,3,0)) -> 16.205 | D110: =+B110-C110 -> -16.205
A111: Chandru Press Tools | B111: =IF(ISNA(VLOOKUP(A111,'TB-22'!A:C,2,0)),0,VLOOKUP(A111,'TB-22'!A:C,2,0)) -> 0 | C111: =IF(ISNA(VLOOKUP(A111,'TB-22'!A:C,3,0)),0,VLOOKUP(A111,'TB-22'!A:C,3,0)) -> 14.718 | D111: =+B111-C111 -> -14.718
A112: Chennai Mettex Lab Private Limited | B112: =IF(ISNA(VLOOKUP(A112,'TB-22'!A:C,2,0)),0,VLOOKUP(A112,'TB-22'!A:C,2,0)) -> 0 | C112: =IF(ISNA(VLOOKUP(A112,'TB-22'!A:C,3,0)),0,VLOOKUP(A112,'TB-22'!A:C,3,0)) -> 14.75 | D112: =+B112-C112 -> -14.75
A113: D.S. Engineering | B113: =IF(ISNA(VLOOKUP(A113,'TB-22'!A:C,2,0)),0,VLOOKUP(A113,'TB-22'!A:C,2,0)) -> 0 | C113: =IF(ISNA(VLOOKUP(A113,'TB-22'!A:C,3,0)),0,VLOOKUP(A113,'TB-22'!A:C,3,0)) -> 108.379 | D113: =+B113-C113 -> -108.379
A114: Dynamic Calibration Systems | B114: =IF(ISNA(VLOOKUP(A114,'TB-22'!A:C,2,0)),0,VLOOKUP(A114,'TB-22'!A:C,2,0)) -> 0 | C114: =IF(ISNA(VLOOKUP(A114,'TB-22'!A:C,3,0)),0,VLOOKUP(A114,'TB-22'!A:C,3,0)) -> 7.936 | D114: =+B114-C114 -> -7.936
... A166: VKN Industries | B166: =IF(ISNA(VLOOKUP(A166,'TB-22'!A:C,2,0)),0,VLOOKUP(A166,'TB-22'!A:C,2,0)) -> 0 | C166: =IF(ISNA(VLOOKUP(A166,'TB-22'!A:C,3,0)),0,VLOOKUP(A166,'TB-22'!A:C,3,0)) -> 134.376 | D166: =+B166-C166 -> -134.376
A167: WMS Consultancy | B167: =IF(ISNA(VLOOKUP(A167,'TB-22'!A:C,2,0)),0,VLOOKUP(A167,'TB-22'!A:C,2,0)) -> 0 | C167: =IF(ISNA(VLOOKUP(A167,'TB-22'!A:C,3,0)),0,VLOOKUP(A167,'TB-22'!A:C,3,0)) -> 56.91 | D167: =+B167-C167 -> -56.91 | F167: =SUM(D37:D167) -> -81756.068
A169: OTHER CURRENT LIABILITIES | D169: =+B169-C169 -> 0
A170: (i) Salary and wages Payable | D170: =+B170-C170 -> 0
A171: Salary Payable | B171: =IF(ISNA(VLOOKUP(A171,'TB-22'!A:C,2,0)),0,VLOOKUP(A171,'TB-22'!A:C,2,0)) -> 0 | C171: =IF(ISNA(VLOOKUP(A171,'TB-22'!A:C,3,0)),0,VLOOKUP(A171,'TB-22'!A:C,3,0)) -> 151.49 | D171: =+B171-C171 -> -151.49
A172: Wages Payable | B172: =IF(ISNA(VLOOKUP(A172,'TB-22'!A:C,2,0)),0,VLOOKUP(A172,'TB-22'!A:C,2,0)) -> 0 | C172: =IF(ISNA(VLOOKUP(A172,'TB-22'!A:C,3,0)),0,VLOOKUP(A172,'TB-22'!A:C,3,0)) -> 1700.983 | D172: =+B172-C172 -> -1700.983
A173: (ii) Dues to Directors | D173: =+B173-C173 -> 0
A174: Mr Karthikeyan Remuneration Payable | B174: =IF(ISNA(VLOOKUP(A174,'TB-22'!A:C,2,0)),0,VLOOKUP(A174,'TB-22'!A:C,2,0)) -> 0 | C174: =IF(ISNA(VLOOKUP(A174,'TB-22'!A:C,3,0)),0,VLOOKUP(A174,'TB-22'!A:C,3,0)) -> 0 | D174: =+B174-C174 -> 0
A175: Mr Karthikeyan - Director | B175: =IF(ISNA(VLOOKUP(A175,'TB-22'!A:C,2,0)),0,VLOOKUP(A175,'TB-22'!A:C,2,0)) -> 0 | C175: =IF(ISNA(VLOOKUP(A175,'TB-22'!A:C,3,0)),0,VLOOKUP(A175,'TB-22'!A:C,3,0)) -> 520.374 | D175: =+B175-C175 -> -520.374
A176: Mrs Girija K - Director | B176: =IF(ISNA(VLOOKUP(A176,'TB-22'!A:C,2,0)),0,VLOOKUP(A176,'TB-22'!A:C,2,0)) -> 0 | C176: =IF(ISNA(VLOOKUP(A176,'TB-22'!A:C,3,0)),0,VLOOKUP(A176,'TB-22'!A:C,3,0)) -> 612.32 | D176: =+B176-C176 -> -612.32
A177: Ms Girija K Remuneration Payable | B177: =IF(ISNA(VLOOKUP(A177,'TB-22'!A:C,2,0)),0,VLOOKUP(A177,'TB-22'!A:C,2,0)) -> 0 | C177: =IF(ISNA(VLOOKUP(A177,'TB-22'!A:C,3,0)),0,VLOOKUP(A177,'TB-22'!A:C,3,0)) -> 0 | D177: =+B177-C177 -> 0
A178: (iii) Other Expenses Payable | D178: =+B178-C178 -> 0
A179: Electricity Charges Payable | B179: =IF(ISNA(VLOOKUP(A179,'TB-22'!A:C,2,0)),0,VLOOKUP(A179,'TB-22'!A:C,2,0)) -> 0 | C179: =IF(ISNA(VLOOKUP(A179,'TB-22'!A:C,3,0)),0,VLOOKUP(A179,'TB-22'!A:C,3,0)) -> 530.8 | D179: =+B179-C179 -> -530.8
A180: Illayaraja Rent Payable - Unit II Staff Accom. | B180: =IF(ISNA(VLOOKUP(A180,'TB-22'!A:C,2,0)),0,VLOOKUP(A180,'TB-22'!A:C,2,0)) -> 0 | C180: =IF(ISNA(VLOOKUP(A180,'TB-22'!A:C,3,0)),0,VLOOKUP(A180,'TB-22'!A:C,3,0)) -> 8 | D180: =+B180-C180 -> -8
A181: Subramanian V - Rent Payable Ramaniyam Flats | B181: =IF(ISNA(VLOOKUP(A181,'TB-22'!A:C,2,0)),0,VLOOKUP(A181,'TB-22'!A:C,2,0)) -> 0 | C181: =IF(ISNA(VLOOKUP(A181,'TB-22'!A:C,3,0)),0,VLOOKUP(A181,'TB-22'!A:C,3,0)) -> 27 | D181: =+B181-C181 -> -27
A182: Mr Kothandam R Rent Payable | B182: =IF(ISNA(VLOOKUP(A182,'TB-22'!A:C,2,0)),0,VLOOKUP(A182,'TB-22'!A:C,2,0)) -> 0 | C182: =IF(ISNA(VLOOKUP(A182,'TB-22'!A:C,3,0)),0,VLOOKUP(A182,'TB-22'!A:C,3,0)) -> 1001.283 | D182: =+B182-C182 -> -1001.283
A183: Bharathi Airtel Limited | B183: =IF(ISNA(VLOOKUP(A183,'TB-22'!A:C,2,0)),0,VLOOKUP(A183,'TB-22'!A:C,2,0)) -> 0 | C183: =IF(ISNA(VLOOKUP(A183,'TB-22'!A:C,3,0)),0,VLOOKUP(A183,'TB-22'!A:C,3,0)) -> 8.58686 | D183: =+B183-C183 -> -8.58686
D184: =+B184-C184 -> 0
A185: (i) TDS Payable | D185: =+B185-C185 -> 0
A186: TDS on Contract 21-22 | B186: =IF(ISNA(VLOOKUP(A186,'TB-22'!A:C,2,0)),0,VLOOKUP(A186,'TB-22'!A:C,2,0)) -> 0 | C186: =IF(ISNA(VLOOKUP(A186,'TB-22'!A:C,3,0)),0,VLOOKUP(A186,'TB-22'!A:C,3,0)) -> 133.875 | D186: =+B186-C186 -> -133.875
A187: TDS on Professional Sevice 21-22 | B187: =IF(ISNA(VLOOKUP(A187,'TB-22'!A:C,2,0)),0,VLOOKUP(A187,'TB-22'!A:C,2,0)) -> 0 | C187: =IF(ISNA(VLOOKUP(A187,'TB-22'!A:C,3,0)),0,VLOOKUP(A187,'TB-22'!A:C,3,0)) -> 35.45 | D187: =+B187-C187 -> -35.45
A188: TDS on Purchase of Goods 21-22 | B188: =IF(ISNA(VLOOKUP(A188,'TB-22'!A:C,2,0)),0,VLOOKUP(A188,'TB-22'!A:C,2,0)) -> 0 | C188: =IF(ISNA(VLOOKUP(A188,'TB-22'!A:C,3,0)),0,VLOOKUP(A188,'TB-22'!A:C,3,0)) -> 94.066 | D188: =+B188-C188 -> -94.066
A189: TDS on Rent 21-22 | B189: =IF(ISNA(VLOOKUP(A189,'TB-22'!A:C,2,0)),0,VLOOKUP(A189,'TB-22'!A:C,2,0)) -> 0 | C189: =IF(ISNA(VLOOKUP(A189,'TB-22'!A:C,3,0)),0,VLOOKUP(A189,'TB-22'!A:C,3,0)) -> 27 | D189: =+B189-C189 -> -27
A190: TDS on Salary 21-22 | B190: =IF(ISNA(VLOOKUP(A190,'TB-22'!A:C,2,0)),0,VLOOKUP(A190,'TB-22'!A:C,2,0)) -> 0 | C190: =IF(ISNA(VLOOKUP(A190,'TB-22'!A:C,3,0)),0,VLOOKUP(A190,'TB-22'!A:C,3,0)) -> 4826.98 | D190: =+B190-C190 -> -4826.98
A191: TDS on Interest 21-22 | B191: =IF(ISNA(VLOOKUP(A191,'TB-22'!A:C,2,0)),0,VLOOKUP(A191,'TB-22'!A:C,2,0)) -> 0 | C191: =IF(ISNA(VLOOKUP(A191,'TB-22'!A:C,3,0)),0,VLOOKUP(A191,'TB-22'!A:C,3,0)) -> 349 | D191: =+B191-C191 -> -349
A192: TDS on Technical Service 21-22 | B192: =IF(ISNA(VLOOKUP(A192,'TB-22'!A:C,2,0)),0,VLOOKUP(A192,'TB-22'!A:C,2,0)) -> 0 | C192: =IF(ISNA(VLOOKUP(A192,'TB-22'!A:C,3,0)),0,VLOOKUP(A192,'TB-22'!A:C,3,0)) -> 16.402 | D192: =+B192-C192 -> -16.402
D193: =+B193-C193 -> 0
A194: (ii) GST Payable | D194: =+B194-C194 -> 0
A195: Output CGST @ 6% | B195: =IF(ISNA(VLOOKUP(A195,'TB-22'!A:C,2,0)),0,VLOOKUP(A195,'TB-22'!A:C,2,0)) -> 0 | C195: =IF(ISNA(VLOOKUP(A195,'TB-22'!A:C,3,0)),0,VLOOKUP(A195,'TB-22'!A:C,3,0)) -> 0 | D195: =+B195-C195 -> 0
A196: Output CGST @ 9% | B196: =IF(ISNA(VLOOKUP(A196,'TB-22'!A:C,2,0)),0,VLOOKUP(A196,'TB-22'!A:C,2,0)) -> 0 | C196: =IF(ISNA(VLOOKUP(A196,'TB-22'!A:C,3,0)),0,VLOOKUP(A196,'TB-22'!A:C,3,0)) -> 0 | D196: =+B196-C196 -> 0
A197: Output IGST @ 18% | B197: =IF(ISNA(VLOOKUP(A197,'TB-22'!A:C,2,0)),0,VLOOKUP(A197,'TB-22'!A:C,2,0)) -> 0 | C197: =IF(ISNA(VLOOKUP(A197,'TB-22'!A:C,3,0)),0,VLOOKUP(A197,'TB-22'!A:C,3,0)) -> 0 | D197: =+B197-C197 -> 0
A198: Output SGST @ 6% | B198: =IF(ISNA(VLOOKUP(A198,'TB-22'!A:C,2,0)),0,VLOOKUP(A198,'TB-22'!A:C,2,0)) -> 0 | C198: =IF(ISNA(VLOOKUP(A198,'TB-22'!A:C,3,0)),0,VLOOKUP(A198,'TB-22'!A:C,3,0)) -> 0 | D198: =+B198-C198 -> 0
A199: Output SGST @ 9% | B199: =IF(ISNA(VLOOKUP(A199,'TB-22'!A:C,2,0)),0,VLOOKUP(A199,'TB-22'!A:C,2,0)) -> 0 | C199: =IF(ISNA(VLOOKUP(A199,'TB-22'!A:C,3,0)),0,VLOOKUP(A199,'TB-22'!A:C,3,0)) -> 0 | D199: =+B199-C199 -> 0
...

Sheet STI 
A1: Index
C3: STATEMENT OF TOTAL INCOME FOR THE YEAR ENDED 31-3-2022
C5: Name of the Assessee | D5: =+BS!A1 -> DYNAMIC AIR ENGINEERING INDIA PRIVATE LIMITED
D6: CIN : U29192TN2008PTC066303
C8: Permanent Account Number | D8: AACCD 9024 A
C10: CIN No. | D10: U29192TN2008PTC066303
C12: Status | D12: Company (Domestic company in which public are not substantially interested)
H13: DISALLOWANCE FROM FORM 3CD
C14: Assessment Year | D14: 2022 - 2023 | H14: 36(1)(va) | I14: 3212
C16: Previous Year | D16: 2021 - 2022 | H16: 40A(3)
H17: 40(a)(ia) | I17: 762506.92
C18: Particulars
C19: INCOME FROM BUSINESS
C21: Profit before Tax as per Profit and Loss Account | F21: =+PL!E22*1000 -> 11220478
C23: Add : Depreciation as per books | E23: =+PL!E15*1000 -> 32221600
C24: Disallowance u/s 40A(3) | D24: Cash payments exceeding Rs.10,000 | E24: =+I16 -> 0 | J24: =I24-H24 -> 0
C25: Disallowance u/s 36(1)(va) | D25: EPF & ESI Employee Contribution | E25: =I14 -> 3212 | J25: =I25-H25 -> 0
C26: Disallowance u/s 40(a)(ia) | D26: Non deduction of TDS | E26: =I17*30/100 -> 228752.08
C27: Disallowance u/s 40(a)(ii) | D27: Interest on income tax | E27: =+'Link Sheet'!D601*1000 -> 234228
C28: Disallowance u/s 37 | D28: Interest on TDS & Penalty | E28: =SUM('Link Sheet'!D602:D603)*1000 -> 266229 | F28: =SUM(E23:E28) -> 32954021
C30: Less: Depreciation allowable u/s 32 | E30: =+'Dep IT'!I39+'Dep IT'!J39 -> 25806010
C31: Less: Income taxable under other heads | E31: =+'PL Notes'!C21*1000 -> 391314 | F31: =SUM(E30:E31) -> 26197324
F32: =+F21+F28-F31 -> 17977175
C33: INCOME FROM OTHER SOURCES
C34: Interest on Deposits | E34: =+'PL Notes'!C21*1000 -> 391314
F35: =+SUM(E34:E35) -> 391314
C37: Gross Total Income | F37: =SUM(F32:F36) -> 18368489
C39: Less: Deduction U/ch VIA | F39: 0
C40: Total Taxable Income | F40: =+F37-F39 -> 18368489
D41: Income Rounded off to Rs. | F41: =ROUNDUP(F40,-1) -> 18368490
C43: COMPUTATION OF TAX LIABILITY
C44: Tax on Total Taxable Income @ 25% | E44: A | F44: =+IF(F41*25%>0,F41*25%,0) -> 4592122.5
C45: Tax Under Minimum Alternate Tax (MAT) | E45: B | F45: ='115JB '!E50 -> 1872922.5
C46: Tax | E46: (Higher of A & B) | F46: =+MAX(F44,F45) -> 4592122.5
C47: Add: Surcharge @ 7% | F47: =IF(F41>10000000,'STI '!F46*0.07,0) -> 321448.58
C48: Tax Before Education Cess | F48: =+F46+F47 -> 4913571.1
C49: Add: Education Cess @ 4% | F49: =+F48*4% -> 196542.84
C50: TOTAL TAX LIABILITY | F50: =+ROUND(F48+F49,-1) -> 5110110
C51: Less: MAT Credit Utilised
C52: Less: Tax Deducted at Source | F52: =557733-866 -> 556867 | G52: 866 Rs to be c/f
C53: Less: Tax Collected at Source | F53: =71628.14 -> 71628.14 | G53: 10 Rs to be c/f
F54: =F50-F51-F52-F53 -> 4481614.9
C55: Less : Advance tax paid on | D55: 14/12/2021 | E55: 1000000
D56: 15/3/2022 | E56: 2000000 | F56: =SUM(E55:E56) -> 3000000
F57: =+F54-F56 -> 1481614.9 | H57: 234C
D58: Add: Interest U/s 234A
D59: Interest U/s 234B | E59: =IF(F56<F54*90%,ROUNDDOWN(F57,-2)*1%*7,0) -> 103712 | G59: 43997 | H59: =+ROUND($F$54*15%,-1) -> 672240 | I59: 0 | J59: =+H59-I59 -> 672240 | K59: =IF(J59>0,J59*1%*3,0) -> 20167.2
D60: Interest U/s 234C | E60: =K63 -> 166321.48 | F60: =SUM(E58:E60) -> 270033.48 | G60: 44089 | H60: =+$F$54*45% -> 2016726.7 | I60: 0 | J60: =+H60-I60 -> 2016726.7 | K60: =IF(J60>0,J60*1%*3,0) -> 60501.801
F61: =+F57+F60 -> 1751648.3 | G61: 44180 | H61: =+$F$54*75% -> 3361211.1 | I61: =E55 -> 1000000 | J61: =+H61-I61 -> 2361211.1 | K61: =IF(J61>0,J61*1%*3,0) -> 70836.334
D62: Less: Self Assessment Tax paid u/s 140 -A | F62: 1774460 | G62: 44270 | H62: =+$F$54*100% -> 4481614.9 | I62: =I61+E56 -> 3000000 | J62: =+H62-I62 -> 1481614.9 | K62: =IF(J62>0,J62*1%*1,0) -> 14816.149
E63: BALANCE TAX PAYABLE | F63: =+ROUND(F61-F62,0) -> -22812 | K63: =SUM(K59:K62) -> 166321.48
E64: 140A Tax Paid | F64: =ROUND(F63,-1) -> -22810
D69: Party | E69: TDS credit b/f | F69: TDS as per 26AS | G69: TDS as per Books | H69: Excess TDS in books | I69: Claimed in ITR | J69: TDS credit c/f
D70: Model Infra corporation | E70: 0 | F70: 15024.27 | G70: 15024 | H70: =+G70-F70 -> -0.27 | I70: =F70 -> 15024.27 | J70: =+E70+F70-I70 -> 0
D71: Bhoopathy Dhanakumar | E71: 562 | F71: 0 | G71: 0 | H71: =+G71-F71 -> 0 | I71: 0 | J71: =+E71+F71-I71 -> 562 | K71: credit in FY19-20 from unknown party hence tds not claimed & c/f
D72: Chennai Radha Engg | E72: 0 | F72: 29121 | G72: 29121 | H72: =+G72-F72 -> 0 | I72: =F72 -> 29121 | J72: =+E72+F72-I72 -> 0
D73: Kocon India Pvt Ltd | E73: 0 | F73: 5504 | G73: 5504 | H73: =+G73-F73 -> 0 | I73: =F73 -> 5504 | J73: =+E73+F73-I73 -> 0
D74: TN generation and distribution | E74: 0 | F74: 2345 | G74: 2345 | H74: =+G74-F74 -> 0 | I74: =F74 -> 2345 | J74: =+E74+F74-I74 -> 0
D75: Universal Engineers chennai Pvt Ltd | E75: 0 | F75: 1800 | G75: 1800 | H75: =+G75-F75 -> 0 | I75: =F75 -> 1800 | J75: =+E75+F75-I75 -> 0
D76: PRECISION EQUIPMENTS ( CHENNAI ) PVT LTD | E76: 0 | F76: 11370 | G76: 15495 | H76: =+G76-F76 -> 4125 | I76: =F76 -> 11370 | J76: =+E76+F76-I76 -> 0 | K76: tds short reported in 26as form. Hence the excess tds credit receivable will be claimed in the year of receipt
D77: JSL lifestyle limited | E77: 0 | F77: 1833 | G77: 1833 | H77: =+G77-F77 -> 0 | I77: =F77 -> 1833 | J77: =+E77+F77-I77 -> 0
D78: Pennar Industries Ltd | E78: 0 | F78: 5325 | G78: 5325 | H78: =+G78-F78 -> 0 | I78: =F78 -> 5325 | J78: =+E78+F78-I78 -> 0
D79: Indian bank circle office | E79: 0 | F79: 8515 | G79: 8515 | H79: =+G79-F79 -> 0 | I79: =F79 -> 8515 | J79: =+E79+F79-I79 -> 0
D80: Jin sung engineering pvt ltd | E80: 0 | F80: 0 | G80: 746 | H80: =+G80-F80 -> 746 | J80: =+E80+F80-I80 -> 0 | K80: tds short reported in 26as form. Hence the excess tds credit receivable will be claimed in the year of receipt
J81: =+E81+F81-I81 -> 0
E82: =SUM(E70:E81) -> 562 | F82: =SUM(F70:F81) -> 80837.27 | G82: =SUM(G70:G81) -> 85708 | H82: =SUM(H70:H81) -> 4870.73 | I82: =SUM(I70:I81) -> 80837.27 | J82: =SUM(J70:J81) -> 562
D88: Party | E88: TCS credit b/f | F88: TCS credit as per 26AS | G88: TCS credit as per books | H88: Excess TCS in books | I88: TCS claimed in ITR | J88: TCS credit c/f
D89: Alomex Profiles Private Limited | E89: 0 | F89: 2032 | G89: 2032 | H89: =+G89-F89 -> 0 | I89: =+E89+F89 -> 2032 | J89: =+E89+F89-I89 -> 0
D90: Metal Scope (India) Private Limited | E90: 0 | F90: 3751 | G90: 3751.85 | H90: =+G90-F90 -> 0.85 | I90: =+E90+F90 -> 3751 | J90: =+E90+F90-I90 -> 0
D91: Mitesh Bhandari | E91: 0 | F91: 4187.37 | G91: 4187.18 | H91: =+G91-F91 -> -0.19 | I91: =+E91+F91 -> 4187.37 | J91: =+E91+F91-I91 -> 0
D92: Salem Stainless Steel Suppliers Private Limited | E92: 0 | F92: 15694 | G92: 15696 | H92: =+G92-F92 -> 2 | I92: =+E92+F92 -> 15694 | J92: =+E92+F92-I92 -> 0
D93: Bansal Wire Industries Limited | E93: 0 | F93: 422 | G93: 422 | H93: =+G93-F93 -> 0 | I93: =+E93+F93 -> 422 | J93: =+E93+F93-I93 -> 0
D94: Pennar Industries Limited | E94: 0 | F94: 1416.23 | G94: 1416.23 | H94: =+G94-F94 -> 0 | I94: =+E94+F94 -> 1416.23 | J94: =+E94+F94-I94 -> 0
D95: Metallica Metals | E95: 0 | F95: 4519 | G95: 4518.64 | H95: =+G95-F95 -> -0.36 | I95: =+E95+F95 -> 4519 | J95: =+E95+F95-I95 -> 0 | K95: tcs short reported in 26as form. Hence the excess tds credit receivable will be claimed in the year of receipt
D96: Madras Metals | E96: 0 | F96: 0 | G96: 354.7 | H96: =+G96-F96 -> 354.7 | I96: =+E96+F96 -> 0 | J96: =+E96+F96-I96 -> 0 | K96: tcs short reported in 26as form. Hence the excess tds credit receivable will be claimed in the year of receipt
E97: =SUM(E89:E96) -> 0 | F97: =SUM(F89:F96) -> 32021.6 | G97: =SUM(G89:G96) -> 32378.6 | H97: =SUM(H89:H96) -> 357 | I97: =SUM(I89:I96) -> 32021.6 | J97: =SUM(J89:J96) -> 0

Sheet 115JB 
A1: Index
B2: STATEMENT OF TOTAL INCOME
B4: Name of the Assessee : DYNAMIC AIR ENGINEERING (INDIA) PRIVATE LIMITED
B6: Permanent Account Number : AACCD 9024 A
B8: Status : Company (Domestic company in which public are not substantially interested)
B10: Assessment Year : 2022-2023
B12: Previous Year : 2021-2022
B14: Particulars | D14: Amount | E14: Amount
B16: Profit as per Profit and Loss Account | E16: ='STI '!F21 -> 11220478
B17: Add: If the following are debited to the P&L Account
B18: Income tax Payable (includes interst on belated payments) | D18: 0
B19: Amount carried to Reserves | D19: 0
B20: Unascertained liabilities | D20: 0
B21: Provision for subsidiary losses | D21: 0
B22: Dividends Payable | D22: 0
B23: Expenses relating to amounts exempted u/s 10/11/12 | D23: 0
B24: Amount of Depreciation | D24: =+PL!E15*1000 -> 32221600
B25: Amount of Deferred Tax & provision thereof | D25: 0
B26: Amounts set aside as provision for diminution in the value of any asset | D26: 0
E27: =+SUM(D18:D27) -> 32221600
E28: =+E16+E27 -> 43442078
B29: Less: If the following are Credited to the P&L Account
B30: Amounts withdrawn from Reserves | D30: 0
B31: Income exempted u/s 10/11/12 other than 10(38) | D31: 0
B32: Amounts debited as depreciation (except depreciation on revaluation of assets) | D32: =+PL!E15*1000 -> 32221600
B33: Amount withdrawn from revaluation reserve and credited to the profit and loss account, | D33: 0
B34: (to the extent it does not exceed the amount of depreciation on account of revaluation of assets)
B35: Amount of loss brought forward or unabsorbed depreciation | D35: 0
B36: Amounts allowable as deduction u/s 80HHC/HHE/HHF | D36: 0
B37: Amount of deferred tax if credited to P&L | D37: 0
D38: 0 | E38: =SUM(D30:D38) -> 32221600
B40: Book Profit U/S 115JB | E40: =E28-E38 -> 11220478
B42: TAX PARTICULARS
B44: 15% of Book Profit | E44: =MAX(ROUND((ROUND(E40,-1)*15%),0),0) -> 1683072
B46: Tax Before Surcharge | E46: =+E44 -> 1683072
B47: Add : Surcharge@7% | E47: =IF(E40>10000000,E46*7%,0) -> 117815.04
B48: Tax Before Education Cess | E48: =+E46+E47 -> 1800887
B49: Add : Education Cess @ 4 % | E49: =+E48*4% -> 72035.482
B50: Tax Liability | E50: =+E48+E49 -> 1872922.5

Sheet Dep IT
A2: M/S DYNAMIC AIR ENGINEERING INDIA PRIVATE LIMITED
A3: CIN No. : U29192TN2008PTC066303
A4: REGISTERED OFFICE
A5: NO. 4, BOOPATHY NAGAR, INDUSTRIAL ESTATE
A6: KEEZHKATTALAI, CHENNAI - 600 117.
A8: DEPRECIATION STATEMENT AS PER INCOME TAX ACT 1961 FOR THE YEAR ENDED 31-03-2022
D9: GROSS BLOCK | K9: NET BLOCK
A10: SLNO | B10: PARTICULARS | C10: % | D10: AS ON 31-03-2021 | E10: ADDITIONS | G10: DELETIONS | H10: AS ON 31-03-2022 | I10: DEPRECIATION | J10: ADDITIONAL DEPRECIATION | K10: WDV AS ON 31-03-2022
E11: Before Sep | F11: After Sep
B12: BLOCK - I
A13: 1 | B13: Land | C13: 0 | D13: 24942539 | E13: 0 | F13: 0 | G13: 0 | H13: =+D13+E13+F13-G13 -> 24942539 | I13: =+((D13+E13-G13)*C13)+(F13*C13/2) -> 0 | K13: =+H13-I13-J13 -> 24942539
D14: 24942539 | E14: =SUM(E13) -> 0 | F14: =SUM(F13) -> 0 | G14: =SUM(G13) -> 0 | H14: =SUM(H13) -> 24942539 | I14: 0 | J14: =SUM(J13) -> 0 | K14: =SUM(K13) -> 24942539
B15: BLOCK - II 10%
A16: 2 | B16: Buildings | C16: 0.1 | D16: 58924903 | E16: 0 | F16: 0 | G16: 0 | H16: =+D16+E16+F16-G16 -> 58924903 | I16: =+((D16+E16-G16)*C16)+(F16*C16/2) -> 5892490.3 | K16: =+H16-I16-J16 -> 53032412
A17: =+A16+1 -> 3 | B17: Furniture & Fittings | C17: 0.1 | D17: 1241453.7 | E17: ='FA Additions'!G30 -> 0 | F17: ='FA Additions'!H30 -> 41450 | G17: 0 | H17: =+D17+E17+F17-G17 -> 1282903.7 | I17: =+((D17+E17-G17)*C17)+(F17*C17/2) -> 126217.87 | K17: =+H17-I17-J17 -> 1156685.8
D18: 60166356 | E18: =SUM(E16:E17) -> 0 | F18: =SUM(F16:F17) -> 41450 | G18: =SUM(G16:G17) -> 0 | H18: =SUM(H16:H17) -> 60207806 | I18: =SUM(I16:I17) -> 6018708.1 | J18: =SUM(J16:J17) -> 0 | K18: =SUM(K16:K17) -> 54189098
B19: BLOCK - III 15%
A20: =+A17+1 -> 4 | B20: Airconditioners | C20: 0.15 | D20: 87917.2 | E20: 0 | F20: 0 | G20: 0 | H20: =+D20+E20+F20-G20 -> 87917.2 | I20: =+((D20+E20)*C20)+(F20*C20/2) -> 13187.58 | K20: =+H20-I20-J20 -> 74729.62
A21: =A20+1 -> 5 | B21: Inventor | C21: 0.15 | D21: 3354.95 | E21: 0 | F21: 0 | G21: 0 | H21: =+D21+E21+F21-G21 -> 3354.95 | I21: =+((D21+E21)*C21)+(F21*C21/2) -> 503.2425 | K21: =+H21-I21-J21 -> 2851.7075
A22: =A21+1 -> 6 | B22: Plant & Machineries | C22: 0.15 | D22: 1.0450414e+08 | E22: ='FA Additions'!G20 -> 528000 | F22: ='FA Additions'!H28 -> 6774500 | G22: ='FA Additions'!F45 -> 1500000 | H22: =+D22+E22+F22-G22 -> 1.1030664e+08 | I22: =+((D22+E22-G22)*C22)+F22*C22/2 -> 16037909 | J22: =(E22*0.2)+F22*0.1 -> 783050 | K22: =+H22-I22-J22 -> 93485685
A23: =A22+1 -> 7 | B23: Telephone | C23: 0.15 | D23: 3269.1 | E23: 0 | F23: 0 | G23: 0 | H23: =+D23+E23+F23-G23 -> 3269.1 | I23: =+((D23+E23)*C23)+(F23*C23/2) -> 490.365 | K23: =+H23-I23-J23 -> 2778.735
A24: =A23+1 -> 8 | B24: Office Equipments | C24: 0.15 | D24: 474775.58 | E24: ='FA Additions'!G35 -> 74067.8 | F24: ='FA Additions'!H35 -> 8515.63 | G24: 0 | H24: =+D24+E24+F24-G24 -> 557359.01 | I24: =+((D24+E24)*C24)+(F24*C24/2) -> 82965.179 | K24: =+H24-I24-J24 -> 474393.83
A25: =A24+1 -> 9 | B25: 2 wheelers | C25: 0.15 | D25: 194786.85 | E25: 0 | F25: 0 | G25: 0 | H25: =+D25+E25+F25-G25 -> 194786.85 | I25: =+((D25+E25)*C25)+(F25*C25/2) -> 29218.028 | K25: =+H25-I25-J25 -> 165568.82
A26: =A25+1 -> 10 | B26: Car | C26: 0.15 | D26: 1224076.5 | F26: ='FA Additions'!H39 -> 785210 | G26: 0 | H26: =+D26+E26+F26-G26 -> 2009286.5 | I26: =+((D26+E26)*C26)+(F26*C26/2) -> 242502.23 | K26: =+H26-I26-J26 -> 1766784.3
A27: =A26+1 -> 11 | B27: Electrical Equipments | C27: 0.15 | D27: 13155912 | E27: 0 | F27: 0 | H27: =+D27+E27+F27-G27 -> 13155912 | I27: =+((D27+E27)*C27)+(F27*C27/2) -> 1973386.9 | K27: =+H27-I27-J27 -> 11182526
A28: =A27+1 -> 12 | B28: Trucks and trailers | C28: 0.15 | D28: 1587519.5 | F28: =SUM('FA Additions'!H37:H38) -> 1350000 | G28: 0 | H28: =+D28+E28+F28-G28 -> 2937519.5 | I28: =+((D28+E28)*C28)+(F28*C28/2) -> 339377.92 | K28: =+H28-I28-J28 -> 2598141.6
D29: =SUM(D20:D28) -> 1.2123576e+08 | E29: =SUM(E20:E28) -> 602067.8 | F29: =SUM(F20:F28) -> 8918225.6 | G29: =SUM(G20:G28) -> 1500000 | H29: =SUM(H20:H28) -> 1.2925605e+08 | I29: =SUM(I20:I28) -> 18719540 | J29: =SUM(J20:J28) -> 783050 | K29: =SUM(K20:K28) -> 1.0975346e+08 | L29: 129256050 | M29: =H29-L29 -> -0.7915
B31: BLOCK - IV 25%
A32: =A28+1 -> 13 | B32: Software | C32: 0.25 | F32: ='FA Additions'!H12 -> 480000 | H32: =+D32+E32+F32-G32 -> 480000 | I32: =+((D32+E32)*C32)+F32*C32/2 -> 60000 | K32: =+H32-I32-J32 -> 420000
D33: =SUM(D32) -> 0 | E33: =SUM(E32) -> 0 | F33: =SUM(F32) -> 480000 | G33: =SUM(G32) -> 0 | H33: =SUM(H32) -> 480000 | I33: =SUM(I32) -> 60000 | J33: =SUM(J32) -> 0 | K33: =SUM(K32) -> 420000
B35: BLOCK - V 40%
A36: =A32+1 -> 14 | B36: Computer & Peripherals | C36: 0.4 | D36: 425358.47 | E36: ='FA Additions'!G18 -> 0 | F36: ='FA Additions'!H18 -> 272838.93 | G36: 0 | H36: =+D36+E36+F36-G36 -> 698197.4 | I36: =+((D36+E36)*C36)+F36*C36/2 -> 224711.17 | K36: =+H36-I36-J36 -> 473486.22
D37: =SUM(D36) -> 425358.47 | E37: =SUM(E36) -> 0 | F37: =SUM(F36) -> 272838.93 | G37: =SUM(G36) -> 0 | H37: =SUM(H36) -> 698197.4 | I37: =SUM(I36) -> 224711.17 | K37: =SUM(K36) -> 473486.22
B39: GRAND TOTAL | D39: =D14+D18+D29+D33+D37 -> 2.0677001e+08 | E39: =E14+E18+E29+E33+E37 -> 602067.8 | F39: =F14+F18+F29+F33+F37 -> 9712514.6 | G39: =G14+G18+G29+G33+G37 -> 1500000 | H39: =H14+H18+H29+H33+H37 -> 2.1558459e+08 | I39: =I14+I18+I29+I33+I37 -> 25022960 | J39: =J14+J18+J29+J33+J37 -> 783050 | K39: =K14+K18+K29+K33+K37 -> 1.8977858e+08
A43: For and on behalf of the Board of Directors of | H43: As per our report of even date
A44: DYNAMIC AIR ENGINEERING INDIA PRIVATE LIMITED | H44: For S.Ravi & Associates
H45: Chartered Accountants
H46: Firm Reg No: 009261S
A49: K. KARTHIKEYAN | D49: GIRIJA KARTHIKEYAN | H49: S.RAVI
A50: DIRECTOR | D50: DIRECTOR | H50: Proprietor
A51: DIN : 0192405 | D51: DIN : 03329379 | H51: M No: 204618
A53: Place: Chennai
A54: Date: 02-09-2022

Sheet Key Ratios
A1: Ratio | B1: Year ended 31 March, 2022 | C1: Year ended 31 March, 2021 | D1: Variance % | E1: Reasons for Variance (Mandatory if variance is more than 25%)
A2: (a) Current Ratio (in times) | B2: =B3/B4 -> 1.1000644 | C2: =C3/C4 -> 1.1898263 | D2: =(B2-C2)/C2 -> -0.075441188 | F2: Current assets/ current liabilities
A3: - Current Assets | B3: =SUM(BS!G39:G42) -> 225478.21 | C3: =SUM(BS!H39:H42) -> 166046.63
A4: - Current Liabilities | B4: =SUM(BS!G20:G25) -> 204968.2 | C4: =SUM(BS!H20:H25) -> 139555.35
A6: (b) Debt-Equity Ratio (in times) | B6: =(B7-B8)/(B9-B10) -> 2.5632018 | C6: =(C7-C8)/(C9-C10) -> 2.6569655 | D6: =(B6-C6)/C6 -> -0.035289766 | F6: (Total Debt - Cash and cash equivalents)/ (Total equity - Investments in subsidiaries)
A7: - Total Debt | B7: =BS!G15+BS!G20 -> 244102.77 | C7: =BS!H15+BS!H20 -> 225276.52
A8: - Cash & Cash Equivalents | B8: =BS!G41 -> 8673.6364 | C8: =BS!H41 -> 2204.3002
A9: - Shareholders Equity | B9: =SUM(BS!G9:G10) -> 91849.63 | C9: =SUM(BS!H9:H10) -> 83957.515
A10: - Investments in subsidiaries | B10: 0 | C10: 0
A12: (c) Debt Service Coverage Ratio (in times) | B12: =SUM(B13:B14)/SUM(B14:B15) -> 0.60289275 | C12: =SUM(C13:C14)/(C14+C15) -> 0.71850881 | D12: =(B12-C12)/C12 -> -0.16091112 | F12: (Profit before tax + Interest expenses) / (Interest expenses + Repayment of long-term loans during the year)
A13: - Profit before tax | B13: =PL!E18 -> 11220.478 | C13: =PL!F18 -> 3195.779
A14: - Interest expense | B14: =PL!E14 -> 25251.749 | C14: =PL!F14 -> 24227.589
A15: - Repayments made during the year | B15: 35243.633 | C15: 13939.47
A17: (d) Return on Equity Ratio (in %) | B17: =B18/((B19+B20)/2-B21) -> 0.089781509 | C17: =C18/((C19+C20)/2-C21) -> 0.024886143 | D17: =(B17-C17)/C17 -> 2.6076907 | E17: Increase in turnover & Profit | F17: Profit after tax / (Average equity – Investments in subsidiaries)
A18: - Net Profits after taxes – Preference Dividend (if any) | B18: =PL!E31 -> 7892.1153 | C18: =PL!F31 -> 2063.6999
A19: - Opening Shareholder’s Equity | B19: =C20 -> 83957.515 | C19: 81893.81
A20: - Closing Shareholder’s Equity | B20: =SUM(BS!G9:G10) -> 91849.63 | C20: =SUM(BS!H9:H10) -> 83957.515
A21: - Investment in subsidiaries | B21: 0 | C21: 0
A23: (e) Inventory turnover ratio (in times) | B23: =B24/(B25+B26)/2 -> 1.5218004 | C23: =C24/(C25+C26)/2 -> 0.8540187 | D23: =(B23-C23)/C23 -> 0.78192865 | E23: Increase in turnover & Profit | F23: Revenue from operations / Average inventories
A24: - Revenue from operations | B24: =PL!E7 -> 460793.21 | C24: =PL!F7 -> 175821.62
A25: - Closing Inventory | B25: =BS!G39 -> 94501.381 | C25: =BS!H39 -> 56896.007
A26: - Opening Inventory | B26: =C25 -> 56896.007 | C26: 46041.8
A28: (f) Trade Receivables turnover ratio (in times) | B28: =B29/(B30+B31)/2 -> 1.405615 | C28: =C29/(C30+C31)/2 -> 0.70312864 | D28: =(B28-C28)/C28 -> 0.99908649 | E28: Collections made before timeline | F28: Revenue from operations / Average trade receivables
A29: - Revenue from operations | B29: =B24 -> 460793.21 | C29: =C24 -> 175821.62
A30: - Opening Trade Debtors / Accounts receivable | B30: =C31 -> 69214.863 | C30: 55813.2
A31: - Closing Trade Debtors / Accounts receivable | B31: =BS!G40 -> 94696.741 | C31: =BS!H40 -> 69214.863
A33: (g) Trade payables turnover ratio (in times) | B33: =B34/(B35+B36)/2 -> 1.2188625 | C33: =C34/(C35+C36)/2 -> 0.27937795 | D33: =(B33-C33)/C33 -> 3.3627726 | E33: Creditors paid before timeline | F33: Credit Purchases / Average trade payables
A34: - Purchases | B34: =PL!E11+PL!E16 -> 363247.34 | C34: =PL!F11+PL!F16 -> 115110.2
A35: - Opening Trade Payables | B35: =C36 -> 67254.73 | C35: 138756.88
A36: - Closing Trade Payables | B36: =BS!G23 -> 81756.068 | C36: 67254.73
A38: (h) Net capital turnover ratio | B38: =B39/B40 -> 22.466744 | C38: =C39/C40 -> 6.636964 | D38: =(B38-C38)/C38 -> 2.3850935 | E38: Increase in turnover & Profit | F38: Revenue from operations / Average Working Capital
A39: - Revenue from operations | B39: =B29 -> 460793.21 | C39: =C29 -> 175821.62
A40: - Average Working Capital | B40: =B3-B4 -> 20510.013 | C40: =C3-C4 -> 26491.273
A42: (i) Net profit ratio (in %) | B42: =B43/B44 -> 0.024350355 | C42: =C43/C44 -> 0.018176257 | D42: =(B42-C42)/C42 -> 0.33967929 | E42: Increase in turnover & Profit | F42: Net profit / Revenue from operations
A43: - Net profit | B43: =PL!E22 -> 11220.478 | C43: =PL!F22 -> 3195.779
A44: - Revenue from operations | B44: =B39 -> 460793.21 | C44: =C39 -> 175821.62
A46: (j) Return on Capital employed (in %) | B46: =B47/B48 -> 0.53258035 | C46: =C47/C48 -> 0.44155879 | D46: =(B46-C46)/C46 -> 0.20613691 | F46: (Profit before tax + Interest expenses)/( Average capital employed- Cash and Cash Equivalents)
A47: - Earnings Before Interest and tax | B47: =PL!E18+PL!E14 -> 36472.228 | C47: =PL!F18+PL!F14 -> 27423.368
A48: - Average Capital employed | B48: 68482.112 | C48: 62105.814
A50: (k) Return on investment (in %) | B50: NA | C50: NA | D50: 0 | F50: Other Income / Average Cash and Cash Equivalents and Other Marketable Securities)
A51: - Other Income
A52: - Opening Cash and Cash Equivalents
A53: - Closing Cash and Cash Equivalents
A54: - Other marketable securities at the beginning of the year | B54: 0 | C54: 0
A55: - Other marketable securities at the end of the year | B55: 0 | C55: 0
A59: Return on capital employed (Gross) % | B59: =(B60+B61)/((B62+B63)-B64) -> 0.11618335 | C59: =(C60+C61)/((C62+C63)-C64) -> 0.097217507 | D59: =(B59-C59)/C59 -> 0.19508667
A60: Profit before tax | B60: =PL!E22 -> 11220.478 | C60: =PL!F22 -> 3195.779
A61: Interest expenses | B61: =PL!E14 -> 25251.749 | C61: =PL!F14 -> 24227.589
A62: Average Equity | B62: =(SUM(BS!G9:G10)+SUM(BS!H9:H10))/2 -> 87903.572 | C62: =(SUM(BS!H9:H10)+SUM(BS!I9:I10))/2 -> 82925.665
A63: Average Borrowing | B63: =(SUM(BS!G15+BS!G20)+(BS!H15+BS!H20))/2 -> 234689.65 | C63: =(SUM(BS!H15+BS!H20)+(BS!I15+BS!I20))/2 -> 201361.25
A64: Cash and Cash equivalent | B64: =BS!G41 -> 8673.6364 | C64: =BS!H41 -> 2204.3002

Sheet FA Additions
B1: =+BS!A1 -> DYNAMIC AIR ENGINEERING INDIA PRIVATE LIMITED
B2: =+BS!A2 -> CIN No. : U29192TN2008PTC066303
B3: ='Dep IT'!A4 -> REGISTERED OFFICE
B4: ='Dep IT'!A5 -> NO. 4, BOOPATHY NAGAR, INDUSTRIAL ESTATE
B5: ='Dep IT'!A6 -> KEEZHKATTALAI, CHENNAI - 600 117.
B7: Details of Additions | I7: 44651
B8: SL NO | C8: DESCRIPTION | D8: DATE OF ADDITION | E8: DATE OF PUT TO USE | F8: Amount | G8: BEFORE SEP | H8: AFTER SEP | I8: Check
C10: Software
C11: Solidworks Premium Software | D11: 44501 | E11: 44501 | F11: 480000 | H11: =F11 -> 480000 | I11: =+$I$7-E11+1 -> 151
F12: =SUM(F11) -> 480000 | G12: =SUM(G11) -> 0 | H12: =SUM(H11) -> 480000
C13: Computer & Peripherals
C14: Computer | D14: 44525 | E14: 44525 | F14: 124576.27 | H14: =F14 -> 124576.27 | I14: =+$I$7-E14+1 -> 127
C15: Printer | D15: 44585 | E15: 44585 | F15: 17796.61 | G15: 0 | H15: =F15 -> 17796.61 | I15: =+$I$7-E15+1 -> 67
C16: Computer | D16: 44622 | E16: 44622 | F16: 88983.05 | G16: 0 | H16: =F16 -> 88983.05 | I16: =+$I$7-E16+1 -> 30
C17: Computer | D17: 44628 | E17: 44628 | F17: 41483 | G17: 0 | H17: =F17 -> 41483 | I17: =+$I$7-E17+1 -> 24
F18: =SUM(F14:F17) -> 272838.93 | G18: =SUM(G14:G17) -> 0 | H18: =SUM(H14:H17) -> 272838.93
C19: Plant & Machinery
C20: Welding Machine | D20: 44469 | E20: 44469 | F20: 528000 | G20: =F20 -> 528000
C21: Welding Machine | D21: 44573 | E21: 44573 | F21: 64500 | G21: 0 | H21: =F21 -> 64500 | I21: =+$I$7-E21+1 -> 79
C22: Paint Booth | D22: 44608 | E22: 44608 | F22: 900000 | G22: 0 | H22: =F22 -> 900000 | I22: =+$I$7-E22+1 -> 44
C23: Shot Blast Equipment | D23: 44635 | E23: 44635 | F23: 1700000 | H23: =F23 -> 1700000
C24: Paint Booth Equipment | D24: 44635 | E24: 44635 | F24: 900000 | H24: =F24 -> 900000 | L24: Subsidy-Rs.15,00,000
C25: Industrial Crane | D25: 44646 | E25: 44646 | F25: 2600000 | H25: =F25 -> 2600000
C26: Industrial Crane | D26: 44651 | E26: 44651 | F26: 125000 | H26: =F26 -> 125000
C27: Power Unit | D27: 44651 | E27: 44651 | F27: 485000 | H27: =F27 -> 485000
F28: =SUM(F20:F27) -> 7302500 | G28: =SUM(G20:G27) -> 528000 | H28: =SUM(H20:H27) -> 6774500
C29: Furniture & Fittings
C30: Steel Almirah | D30: 44585 | E30: 44585 | F30: 41450 | G30: 0 | H30: =F30 -> 41450 | I30: =+$I$7-E30+1 -> 67
C32: Office Equipments
C33: Camera & Installation | D33: 44468 | E33: 44468 | F33: 74067.8 | G33: =IF(I33>180,F33,0) -> 74067.8 | H33: =IF(I33>180,0,F33) -> 0 | I33: =+$I$7-E33+1 -> 184
C34: Projector | D34: 44592 | E34: 44592 | F34: 8515.63 | G34: 0 | H34: =F34 -> 8515.63 | I34: =+$I$7-E34+1 -> 60
F35: =SUM(F33:F34) -> 82583.43 | G35: =SUM(G33:G34) -> 74067.8 | H35: =SUM(H33:H34) -> 8515.63
C36: Vehicle
C37: 75 Feet Trailor | D37: 44537 | E37: 44537 | F37: 625000 | G37: =IF(I37>180,F37,0) -> 0 | H37: =IF(I37>180,0,F37) -> 625000 | I37: =+$I$7-E37+1 -> 115
C38: Trailor Jeep | D38: 44537 | E38: 44537 | F38: 725000 | G38: =IF(I38>180,F38,0) -> 0 | H38: =IF(I38>180,0,F38) -> 725000 | I38: =+$I$7-E38+1 -> 115
C39: Maruti Dezire Car | D39: 44562 | E39: 44562 | F39: 785210 | G39: =IF(I39>180,F39,0) -> 0 | H39: =IF(I39>180,0,F39) -> 785210 | I39: =+$I$7-E39+1 -> 90
F40: =SUM(F37:F39) -> 2135210 | G40: =SUM(G37:G39) -> 0 | H40: =SUM(H37:H39) -> 2135210
E43: GROSS TOTAL | F43: =F40+F35+F30+F28+F18+F12 -> 10314582 | G43: =G40+G35+G30+G28+G18+G12 -> 602067.8 | H43: =H40+H35+H30+H28+H18+H12 -> 9712514.6
C45: Subsidy Received | F45: 1500000 | G45: =F45 -> 1500000 | I45: 44355

Sheet BS
A1: DYNAMIC AIR ENGINEERING INDIA PRIVATE LIMITED
A2: CIN No. : U29192TN2008PTC066303
A3: Balance Sheet as at 31st March 2022
A4: (All amounts are in Indian Rupees in thousands, except share data and as stated)
B5: Particulars | F5: Note No. | G5: As at 31st March, 2022 (Current reporting period) | H5: As at 31st March, 2021 (Previous reporting period)
A6: I. | B6: EQUITY AND LIABILITIES
A8: 1 | B8: Shareholders’ funds
B9: (a) | C9: Share capital | F9: 2 | G9: =ROUND('BS Notes'!E18,0)/1000 -> 28500 | H9: =+'BS Notes'!F18/1000 -> 28500 | I9: 28500 | J9: =G9-H9 -> 0
B10: (b) | C10: Reserves and surplus | F10: 3 | G10: ='BS Notes'!E56 -> 63349.63 | H10: ='BS Notes'!F56 -> 55457.515 | I10: =53393814.65/1000 -> 53393.815 | J10: =G10-H10 -> 7892.1153
A12: 2 | B12: Share application money pending allotment | G12: 0 | H12: 0
A14: 3 | B14: Non-current liabilities
B15: (a) | C15: Long-term borrowings | F15: 4 | G15: ='BS Notes'!E70 -> 136398.97 | H15: ='BS Notes'!F70 -> 163379.73 | I15: =147890891.9/1000 -> 147890.89 | J15: =G15-H15 -> -26980.76
B16: (b) | C16: Deferred tax liabilities(net) | F16: 5 | G16: =IF('BS Notes'!E86>0,'BS Notes'!E86,0) -> 2881.4896 | H16: =+'BS Notes'!F86 -> 4666.3069 | J16: =G16-H16 -> -1784.8172
B17: (c) | C17: Long-term provisions | F17: 6 | G17: ='BS Notes'!E92 -> 742.962 | H17: ='BS Notes'!F92 -> 742.962 | J17: =G17-H17 -> 0
A19: 4 | B19: Current liabilities
B20: (a) | C20: Short-term borrowings | F20: 7 | G20: =+'BS Notes'!E111 -> 107703.8 | H20: =+'BS Notes'!F111 -> 61896.787 | I20: =29555080.5/1000 -> 29555.081 | J20: =G20-H20 -> 45807.014 | K20: =G15+G20 -> 244102.77 | L20: =H15+H20 -> 225276.52 | M20: =(I15+I20) -> 177445.97 | N20: =M20-L20 -> -47830.548
B21: (b) | C21: Trade payables | F21: 8
C22: (A) Total outstanding dues of micro enterprises and small enterprises
C23: (B) Total outstanding dues of creditors other than Micro enterprises and small enterprises | G23: ='BS Notes'!E123 -> 81756.068 | H23: ='BS Notes'!F123 -> 67254.733 | J23: =G23-H23 -> 14501.335
B24: (c) | C24: Other current liabilities | F24: 9 | G24: ='BS Notes'!E158 -> 10398.22 | H24: ='BS Notes'!F158 -> 7183.0632 | J24: =G24-H24 -> 3215.1568
B25: (d) | C25: Short-term provisions | F25: 10 | G25: ='BS Notes'!E179 -> 5110.11 | H25: =3220770/1000 -> 3220.77 | J25: =G25-H25 -> 1889.34
D26: TOTAL | G26: =SUM(G8:G25) -> 436841.25 | H26: =SUM(H8:H25) -> 392301.87
A27: II. | B27: ASSETS
B28: Non-current assets
A29: 1 | B29: (a) | C29: Property, Plant and Equipment and Intangible Assets | F29: 11
C30: (i) | D30: Property, Plant and Equipment | G30: ='Dep - co'!M26-G31 -> 200524.58 | H30: =+'Dep - co'!L26 -> 224286.18 | J30: =G30-H30 -> -23761.598
C31: (ii) | D31: Intangible assets | G31: ='Dep - co'!M24 -> 354.58044 | H31: 0 | J31: =G31-H31 -> 354.58044
C32: (iii) | D32: Capital work-in-progress | G32: =+'Dep - co'!G36 -> 0 | H32: =+'Dep - co'!L36 -> 0
C33: (iv) | D33: Intangible assets under development | G33: 0 | H33: 0
B34: (b) | C34: Non-current investments | G34: 0 | H34: 0
B35: (c) | C35: Deferred tax Assets (net) | G35: 0 | H35: 0
B36: (d) | C36: Other non-current assets | F36: 12 | G36: ='BS Notes'!E189 -> 10483.879 | H36: ='BS Notes'!F189 -> 1969.063 | J36: =G36-H36 -> 8514.816
A38: 2 | B38: Current assets
B39: (a) | C39: Inventories | F39: 13 | G39: ='BS Notes'!E199 -> 94501.381 | H39: ='BS Notes'!F199 -> 56896.007 | J39: =G39-H39 -> 37605.374
B40: (b) | C40: Trade receivables | F40: 14 | G40: =+'BS Notes'!E207 -> 94696.741 | H40: =+'BS Notes'!F207 -> 69214.863 | J40: =G40-H40 -> 25481.879
B41: (c) | C41: Cash and cash equivalents | F41: 15 | G41: ='BS Notes'!E238 -> 8673.6364 | H41: ='BS Notes'!F238 -> 2204.3002 | J41: =G41-H41 -> 6469.3362
B42: (d) | C42: Other current assets | F42: 16 | G42: ='BS Notes'!E260 -> 27606.452 | H42: ='BS Notes'!F260 -> 37731.456 | J42: =G42-H42 -> -10125.004
K43: =J43+G43 -> 0
D44: TOTAL | G44: =SUM(G29:G43) -> 436841.25 | H44: =SUM(H29:H43) -> 392301.87 | J44: =G44-G26 -> 1.617067e-06 | K44: =H44-H26 -> 1.617067e-06
A45: Summary of Significant Accounting Policies | F45: 1
A46: The accompanying notes are an integral part of the financial statements
G47: As per our report of even date
A48: For and on behalf of the Board of Directors of | G48: For S. Ravi & Associates
A49: For DYNAMIC AIR ENGINEERING INDIA PRIVATE LIMITED | G49: Chartered Accountants
G50: Firm Reg No: 009261S
A54: K. KARTHIKEYAN | E54: GIRIJA KARTHIKEYAN | G54: S.RAVI
A55: Director | E55: Director | G55: Proprietor
A56: DIN : 01924065 | E56: DIN : 03329379 | G56: M No: 204618
A58: PLACE: CHENNAI
A59: DATE: 02-09-2022

Sheet PL
A1: DYNAMIC AIR ENGINEERING INDIA PRIVATE LIMITED
A2: CIN No. : U29192TN2008PTC066303
A3: Statement of Profit And Loss for the Year Ended 31st March 2022
A4: =BS!A4 -> (All amounts are in Indian Rupees in thousands, except share data and as stated)
B5: Particulars | D5: Note No. | E5: For the year ended 31st March, 2022 | F5: For the year ended 31st March, 2021 | I5: 2021-2022 | J5: 2020-2021
H6: Sales | I6: =E7 -> 460793.21 | J6: =F7 -> 175821.62
A7: I. | B7: Revenue from operations | D7: 17 | E7: ='PL Notes'!C15 -> 460793.21 | F7: ='PL Notes'!D15 -> 175821.62 | G7: ='Link Sheet'!F443 -> -460793.21 | H7: Cost of Sales | I7: =SUM(E11:E12) -> 352325.79 | J7: =SUM(F11:F12) -> 97566.643
A8: II. | B8: Other income | D8: 18 | E8: ='PL Notes'!C24 -> 728.57951 | F8: ='PL Notes'!D24 -> 176.674 | G8: ='Link Sheet'!F452 -> -728.57951 | H8: GP | I8: =I6-I7 -> 108467.41 | J8: =J6-J7 -> 78254.981
A9: III. | B9: Total Income (I + II) | E9: =+E7+E8 -> 461521.79 | F9: =+F7+F8 -> 175998.3 | I9: =I8/I6*100 -> 23.539282 | J9: =J8/J6*100 -> 44.508166
A10: IV. | B10: Expenses: | H10: NP | I10: =E18/E7*100 -> 2.4350355 | J10: =F18/F7*100 -> 1.8176257
B11: Raw Materials Consumed & Direct Costs | D11: 19 | E11: ='PL Notes'!C36 -> 343545.92 | F11: ='PL Notes'!D36 -> 106233.88 | G11: ='Link Sheet'!F490 -> 342817.34
B12: Changes in inventories of WIP, Finished goods and Stock-in-Trade | D12: 20 | E12: ='PL Notes'!C50 -> 8779.873 | F12: ='PL Notes'!D50 -> -8667.233 | G12: ='Link Sheet'!F500 -> -36282.081
B13: Employee benefits expense | D13: 21 | E13: ='PL Notes'!C63 -> 20800.743 | F13: ='PL Notes'!D63 -> 3061.2609 | G13: ='Link Sheet'!F516 -> 20800.743
B14: Finance costs | D14: 22 | E14: =+'PL Notes'!C74 -> 25251.749 | F14: =+'PL Notes'!D74 -> 24227.589 | G14: ='Link Sheet'!F539 -> 25251.749
B15: Depreciation and amortization expense | D15: 11 | E15: ='Dep - co'!I26 -> 32221.6 | F15: =39070696.8332249/1000 -> 39070.697
B16: Other expenses | D16: 23 | E16: =+'PL Notes'!C103 -> 19701.422 | F16: =+'PL Notes'!D103 -> 8876.3289 | G16: ='Link Sheet'!F619 -> 19701.422 | K16: Deferred Tax Reco
B17: Total expenses | E17: =SUM(E11:E16) -> 450301.31 | F17: =SUM(F11:F16) -> 172802.52 | K17: Tax rate | L17: =+'Def Tax'!C11 -> 0.2782
A18: V. | B18: Profit before exceptional and extraordinary items and tax (III-IV) | E18: =E9-E17 -> 11220.478 | F18: =F9-F17 -> 3195.779 | G18: 11220478 | K18: NP | L18: =+E22 -> 11220.478
A19: VI. | B19: Exceptional items | E19: 0 | F19: 0 | G19: =G18-E18 -> 11209258 | K19: Tax on NP | N19: =+L17*L18 -> 3121.537
A20: VII. | B20: Profit before extraordinary items and tax (V - VI) | E20: =E18-E19 -> 11220.478 | F20: =F18-F19 -> 3195.779 | K20: Provision for tax + deferred tax | N20: =E24+E25+E26 -> 3328.3628
A21: VIII. | B21: Extraordinary Items | E21: 0 | F21: 0 | K21: Increase in Depreciation as per IT Act | N21: =-('STI '!E30-'STI '!E23)*L17 -> 1784817.2
A22: IX. | B22: Profit before tax (VII- VIII) | E22: =+E20-E21 -> 11220.478 | F22: =+F20-F21 -> 3195.779 | N22: =+N19-N20+N21 -> 1784610.4
A23: X | B23: Tax expense: | K23: Permanent Diff
B24: (1) Current tax | E24: =('STI '!F50+3070)/1000 -> 5113.18 | F24: =3220770/1000 -> 3220.77 | K24: Interest on Delayed Pmt of taxes | L24: =+'STI '!E26 -> 228752.08 | M24: =+L24*$L$17 -> 63638.828
B25: (2) Less: MAT Credit Entitlement | E25: =0 -> 0 | F25: 0 | L25: 279914 | M25: =+L25*$L$17 -> 77872.075
B26: (3) Deferred tax Liability / (Asset) | E26: =-'Def Tax'!C35/1000 -> -1784.8172 | F26: =-2088690.91855138/1000 -> -2088.6909 | K26: =+'STI '!C25 -> Disallowance u/s 36(1)(va) | L26: =+'STI '!E25 -> 3212 | M26: =+L26*$L$17 -> 893.5784
A27: XI | B27: Profit (Loss) for the period from continuing operations (VII-VIII) | E27: =+E22-SUM(E24:E26) -> 7892.1153 | F27: =+F22-SUM(F24:F26) -> 2063.6999 | K27: Term Loan Interest | L27: =SUM('STI '!E28:E28) -> 266229 | M27: =L27*L17 -> 74064.908
A28: XII | B28: Profit/(loss) from discontinuing operations | E28: 0 | F28: 0
A29: XIII | B29: Tax expense of discontinuing operations | E29: 0 | F29: 0 | K29: Disallowance 40(a)(ia) | L29: =+'STI '!E24 -> 0 | M29: =+L29*L17 -> 0 | N29: =SUM(M23:M29) -> 216469.39
A30: XIV | B30: Profit/(loss) from Discontinuing operations (after tax) (XII-XIII) | E30: =E28-E29 -> 0 | F30: 0 | M30: Diff | N30: =+N22+N29 -> 2001079.8
A31: XV | B31: Profit (Loss) for the period (XI + XIV) | E31: =+E27+E30 -> 7892.1153 | F31: =+F27+F30 -> 2063.6999 | H31: =E31*1000 -> 7892115.3
A32: XVI | B32: Earnings per equity share: | K32: CHECK
B33: (1) Basic | E33: =E31/'BS Notes'!C29 -> 2.7691633 | F33: =F31/'BS Notes'!C29 -> 0.72410523 | K33: Profit as per Tally | L33: 14621823
B34: (2) Diluted | E34: =E33 -> 2.7691633 | F34: =F33 -> 0.72410523 | K34: Profit as per Financials | L34: =+E22 -> 11220.478
A35: Summary of Significant Accouting Policies | D35: 1 | K35: Diff | L35: =+L33-L34 -> 14610603
A36: The accompanying notes are an integral part of the finacial statements | E36: As per our report of even date | L36: 0
E37: For S.Ravi & Associates
A38: For and on behalf of the Board of Directors of | E38: Chartered Accountants
A39: DYNAMIC AIR ENGINEERING INDIA PRIVATE LIMITED | E39: Firm Reg No: 009261S
A43: K. KARTHIKEYAN | C43: GIRIJA KARTHIKEYAN | E43: S.RAVI
A44: Director | C44: Director | E44: Proprietor
A45: DIN : 01924065 | C45: DIN : 03329379 | E45: M No: 204618
A47: PLACE: CHENNAI
A48: =BS!A59 -> DATE: 02-09-2022

Sheet BS Notes
A1: DYNAMIC AIR ENGINEERING INDIA PRIVATE LIMITED
A2: CIN No. : U29192TN2008PTC066303
A3: NOTES TO THE FINANCIAL STATEMENTS FOR THE YEAR ENDED 31 MARCH 2022
A4: =CFS!A5 -> (All amounts are in Indian Rupees in thousands, except share data and as stated)
A6: Note 2
A7: Share capital
A8: Particulars | E8: As at | F8: As at
E9: 44651 | F9: 44286
A11: Authorised
A12: 65,00,000 Equity Shares of Rs 10 each | E12: =(6500000*10) -> 65000000 | F12: =(6500000*10) -> 65000000
A13: Issued
A14: 28,50,000 Equity Shares of Rs 10 each | E14: =D29 -> 28500000 | F14: =28500*1000 -> 28500000
A15: Subscribed & Paid up
A16: 28,50,000 Equity Shares of Rs. 10 each fully paid | E16: =D29 -> 28500000 | F16: =F14 -> 28500000
A18: Total | E18: =SUM(E16:E17) -> 28500000 | F18: =SUM(F16:F17) -> 28500000
A20: Rights, preferences and restrictions attached to shares
A21: Equity shares: The Company has one class of equity shares having a par value of Rs 10 per share. Each shareholder is eligible for one vote per share held. In the event of liquidation, the equity shareholders are eligible to receive the remaining assets of the Company after distribution of all preferential amounts, in proportion to their shareholding. The dividend proposed by the Board of Directors is subject to the approval of the shareholders in the ensuing Annual General Meeting, except in case of interim dividend
A23: Reconciliation of the number of shares outstanding at the beginning and at the end of the reporting period
A24: Particulars | C24: As at March 31, 2022 | E24: As at March 31, 2021
C25: Number | D25: Amount | E25: Number | F25: Amount
A26: Shares outstanding at the beginning of the year | C26: =+E29 -> 2850 | D26: =+C26*10000 -> 28500000 | E26: 2850 | F26: =28500*1000 -> 28500000
A27: Shares Issued during the year | E27: 0 | F27: 0
A28: Shares bought back during the year | C28: 0 | D28: =+C28*10 -> 0 | E28: 0 | F28: 0
A29: Shares outstanding at the end of the year | C29: =C26+C27-C28 -> 2850 | D29: =D26+D27-D28 -> 28500000 | E29: 2850 | F29: =SUM(F26:F28) -> 28500000
A31: Shares in the company held by each shareholder holding more than 5 percent shares
A32: Name of Shareholder | C32: =C24 -> As at March 31, 2022 | E32: =E24 -> As at March 31, 2021
C33: No. of Shares held | D33: % of Holding | E33: No. of Shares held | F33: % of Holding
A34: K . KARTHIKEYAN | C34: =(145000+145000*6+1746000)/1000 -> 2761 | D34: =+C34/C29 -> 0.96877193 | E34: 2761 | F34: =+E34/E29 -> 0.96877193
A35: GIRIJA KARTHIKEYAN | C35: =(5000+5000*6+54000)/1000 -> 89 | D35: =+C35/C29 -> 0.03122807 | E35: 89 | F35: =+E35/E29 -> 0.03122807
A36: Total | C36: =SUM(C34:C35) -> 2850 | D36: =SUM(D34:D35) -> 1 | E36: =SUM(E34:E35) -> 2850 | F36: =SUM(F34:F35) -> 1
A38: Shares held by promoters at the end of the year
A39: Promoter name | B39: No of Shares | C39: % of Total shares | D39: No of Shares | E39: % of Total shares | F39: % change during the year
A40: K . KARTHIKEYAN | B40: =C34 -> 2761 | C40: =B40/B42 -> 0.96877193 | D40: =(145000+145000*6+1746000)/1000 -> 2761 | E40: =D40/D42 -> 0.96877193 | F40: -
A41: GIRIJA KARTHIKEYAN | B41: =C35 -> 89 | C41: =B41/B42 -> 0.03122807 | D41: =(5000+5000*6+54000)/1000 -> 89 | E41: =D41/D42 -> 0.03122807 | F41: -
A42: TOTAL | B42: =SUM(B40:B41) -> 2850 | C42: =SUM(C40:C41) -> 1 | D42: =SUM(D40:D41) -> 2850 | E42: =SUM(E40:E41) -> 1 | F42: =SUM(F40:F41) -> 0
A44: Note 3
A45: Reserves and surplus
A46: Particulars | E46: =C32 -> As at March 31, 2022 | F46: =E32 -> As at March 31, 2021
A48: Share Premium | D48: a | E48: ='Link Sheet'!C8 -> 16200 | F48: 16200
A50: Surplus
A51: Opening balance | E51: =F54 -> 39257.515 | F51: 37193.815
A52: (-) Bonus shares issued | E52: 0 | F52: 0
A53: (+) Net Profit/(Net Loss) For the current year | E53: =PL!E27 -> 7892.1153 | F53: 2063.6999
D54: b | E54: =SUM(E51:E53) -> 47149.63 | F54: =(SUM(F51:F53)) -> 39257.515
A56: Closing Balance | D56: a+b | E56: =E54+E48 -> 63349.63 | F56: =F54+F48 -> 55457.515
A59: Note 4
A60: Long Term Borrowings
A61: Particulars | E61: =+$E$46 -> As at March 31, 2022 | F61: =+$F$46 -> As at March 31, 2021
A63: Secured Loans
A64: (a) Vehicle HP Loans - Banks (Secured against Hypothecation of vehicles) | E64: =-SUM('Link Sheet'!D14:D15)-E105 -> 486.60841 | F64: 209.6
A65: (b) Loan from Banks (Secured against factory plot & building, machineries & equipments and Properties of relative of director and personal guarantee of the Directors) | E65: =-SUM('Link Sheet'!D18:D21)-E106 -> 135912.37 | F65: 163060.98
A66: Unsecured Loans
A67: HDFC Bank | E67: 0 | F67: 96.86551
A68: Deutsche Bank | E68: 0 | F68: 12.28592
A70: Total | E70: =SUM(E64:E69) -> 136398.97 | F70: =SUM(F62:F69) -> 163379.73
A72: Note 5
A73: Deferred Tax liability / (Asset) (Net)
A74: Particulars | E74: =+$E$46 -> As at March 31, 2022 | F74: =+$F$46 -> As at March 31, 2021
A76: Deferred Tax Liability arising on account of
A77: i. Block of assets | E77: =-'Def Tax'!D18/1000 -> 3088.1817 | F77: 4666.3069
A78: ii. Others
A79: Gross deferred tax liability | E79: =SUM(E77:E78) -> 3088.1817 | F79: =SUM(F77:F78) -> 4666.3069
A81: Deferred Tax Asset arising on account of
A82: i. Block of assets | E82: 0 | F82: 0
A83: ii. Others | E83: ='Def Tax'!D21/1000 -> 206.69203 | F83: 0
A84: Gross deferred tax asset | E84: =SUM(E82:E83) -> 206.69203 | F84: =SUM(F82:F83) -> 0
A86: Closing Deferred Tax Liabilty / (Asset) - Net | E86: =E79-E84 -> 2881.4896 | F86: =F79-F84 -> 4666.3069
A88: Note 6
A89: Long Term Provisions
A90: Particulars | E90: =+$E$46 -> As at March 31, 2022 | F90: =+$F$46 -> As at March 31, 2021
A92: Provision for employee benefits | E92: ='Link Sheet'!C30 -> 742.962 | F92: 742.962
A94: Total | E94: =SUM(E91:E93) -> 742.962 | F94: =SUM(F91:F93) -> 742.962
A96: Note 7
A97: Short Term Borrowings
A98: Particulars | E98: =+$E$46 -> As at March 31, 2022 | F98: =+$F$46 -> As at March 31, 2021
A100: (a) Indian Bank - CC Account | E100: =-SUM('Link Sheet'!D33) -> 37687.912 | F100: 32361.687
A101: (Secured against receivables, stock & book debts)
A102: (b) NSIC- Loan against guarantee | E102: ='Link Sheet'!C34 -> 29505.835
A104: Secured Loans
A105: (a) Vehicle HP Loans - Banks (Secured against Hypothecation of vehicles) | E105: =406054.593306396/1000 -> 406.05459 | F105: 331.338
A106: (c) Loan from Banks (Secured against factory plot & building, machineries & equipments, property of relative of director and personal guarantee of the directors) | E106: =40104000/1000 -> 40104 | F106: 27600
A107: Unsecured Loans
A108: HDFC Bank | E108: 0 | F108: =1155762/1000 -> 1155.762
A109: Deutsche Bank | E109: 0 | F109: 448
A111: Total | E111: =SUM(E100:E109) -> 107703.8 | F111: =SUM(F100:F109) -> 61896.787
A114: Note 8
A115: Trade Payable
A116: Particulars | E116: =+$E$46 -> As at March 31, 2022 | F116: =+$F$46 -> As at March 31, 2021
A118: (i) Trade payables - Related Party | E118: ='Link Sheet'!C38 -> 7419.6566 | F118: 3018.0776
A119: (ii) Payables - for Capital Goods | E119: =-SUM('Link Sheet'!D40:D42) -> 1725.96 | F119: 3558.816
A120: (iii) Payables - for Raw Materials | E120: =ABS(SUM('Link Sheet'!D44:D101)) -> 67715.609 | F120: 0
A121: (ii) Payables - Others | E121: =-SUM('Link Sheet'!D103:D168) -> 4894.842 | F121: 60677.839
A123: Total | E123: =SUM(E118:E121) -> 81756.068 | F123: =SUM(F118:F121) -> 67254.733
A125: Trade payable ageing schedule as on 31st Mar 2022
A126: Particulars | C126: Outstanding for following periods from due date of payment
C127: Less than 1 year | D127: 1-2 years | E127: 2-3 years | F127: More than 3 years
A128: (i) MSME | C128: 0 | D128: 0 | E128: 0 | F128: 0
A129: (ii) Others | C129: =79153319/1000 -> 79153.319 | D129: =337761/1000 -> 337.761 | E129: =1044249/1000 -> 1044.249 | F129: =1220738.56/1000 -> 1220.7386
A130: (iii) Disputed dues- MSME | C130: 0 | D130: 0 | E130: 0 | F130: 0
A131: (iv) Disputed dues-Others | C131: 0 | D131: 0 | E131: 0 | F131: 0
...

Sheet PL Notes
B1: DYNAMIC AIR ENGINEERING INDIA PRIVATE LIMITED
B2: CIN No. : U29192TN2008PTC066303
B3: NOTES TO THE FINANCIAL STATEMENTS FOR THE YEAR ENDED 31 MARCH 2022
B4: =CFS!A5 -> (All amounts are in Indian Rupees in thousands, except share data and as stated)
B6: Note 17
B7: Revenue from operations
B8: Particulars | C8: For the year ended 31 March, 2022 | D8: For the year ended 31 March, 2021
B10: Sales | C10: =-SUM('Link Sheet'!D432:D435) -> 452531.78 | D10: =171696.54122 -> 171696.54 | E10: Excise Duty | G10: 4539462 | I10: =C10-#REF!+C12 -> #REF!
B11: Freight Charges | C11: =-SUM('Link Sheet'!D437:D438) -> 2570.4995 | D11: 914.80468
B12: Packing and Installation | C12: =-SUM('Link Sheet'!D440:D441) -> 40.56741 | D12: 71.60997 | E12: =3145486+62909+31454 -> 3239849
B13: Job Work Income | C13: ='Link Sheet'!C443 -> 5650.3579 | D13: 3138.6674
B15: Total | C15: =SUM(C10:C13) -> 460793.21 | D15: =SUM(D10:D13) -> 175821.62 | E15: 3464166
E16: 42028.68
B17: Note 18 | E17: =SUM(E13:E16) -> 3506194.7
B18: Other income
B19: Particulars | C19: =+$C$8 -> For the year ended 31 March, 2022 | D19: =+$D$8 -> For the year ended 31 March, 2021
B21: Interest on deposits | C21: =SUM('Link Sheet'!C447:C448) -> 391.314 | D21: 144.786
B22: Other income | C22: =-SUM('Link Sheet'!D450:D452) -> 337.26551 | D22: 31.888 | F22: =16577078.86-#REF! -> #REF!
B24: Total | C24: =SUM(C21:C22) -> 728.57951 | D24: =SUM(D21:D22) -> 176.674
B26: Note 19
B27: Cost of materials consumed & Direct expenses
B28: Particulars | C28: =+$C$8 -> For the year ended 31 March, 2022 | D28: =+$D$8 -> For the year ended 31 March, 2021
B30: Raw Materials Consumed & Direct expenses | C30: =SUM('Link Sheet'!D456:D468) -> 298996.88 | D30: 78332.979 | E30: =C30+C31 -> 300805.81
B31: Carriage Inwards | C31: =SUM('Link Sheet'!D471:D474) -> 1808.927 | D31: 732.88698
B32: Rent - Factory | C32: =SUM('Link Sheet'!D476:D477) -> 1498.5 | D32: 1868.25
B33: Electricity & Power | C33: =SUM('Link Sheet'!D479:D480) -> 6722.766 | D33: 4763.079
B34: Wages & Other Direct Expenses | C34: =SUM('Link Sheet'!D482:D490) -> 34518.849 | D34: 20536.681
B36: Total | C36: =SUM(C30:C34) -> 343545.92 | D36: =SUM(D30:D34) -> 106233.88
B38: Note 20
B39: Changes in inventories of finished goods, work-in-progress and stock in Trade
B40: Particulars | C40: =+$C$8 -> For the year ended 31 March, 2022 | D40: =+$D$8 -> For the year ended 31 March, 2021
B42: Opening Stock :
B43: Work-in-Process | C43: =+D47 -> 9882.053 | D43: 13369.828
B44: Finished Goods | C44: =D48 -> 35225.008 | D44: 23070
B46: Closing Stock :
B47: Work-in-Progress | C47: ='BS Notes'!E196 -> 25014.138 | D47: 9882.053
B48: Finished Goods | C48: ='BS Notes'!E197 -> 11313.05 | D48: 35225.008
B50: Decrease / (Increase) in Inventories | C50: =SUM(C43:C44)-SUM(C47:C49) -> 8779.873 | D50: =SUM(D43:D44)-SUM(D47:D49) -> -8667.233
B53: Note 21
B54: Employee Benefits Expense
B55: Particulars | C55: =+$C$8 -> For the year ended 31 March, 2022 | D55: =+$D$8 -> For the year ended 31 March, 2021
B57: (a) Salaries and incentives | C57: =SUM('Link Sheet'!D504:D506) -> 1889.897 | D57: 1865.404
B58: (b) Director Remuneration | C58: =SUM('Link Sheet'!D510) -> 18000 | D58: 600
B59: (c) Staff Welfare | C59: =SUM('Link Sheet'!D508) -> 724.7876 | D59: 415.52785
B60: (d) Contribution to EPF and ESI | C60: =SUM('Link Sheet'!D512:D514) -> 186.058 | D60: 180.329
B61: (e) Gratuity | C61: ='Link Sheet'!D516 -> 0 | D61: 0
B63: Total | C63: =SUM(C57:C61) -> 20800.743 | D63: =SUM(D57:D61) -> 3061.2609 | F63: =C63-2002100.5 -> -1981299.8
B65: Note 22
B66: Finance Costs
B67: Particulars | C67: =+$C$8 -> For the year ended 31 March, 2022 | D67: =+$D$8 -> For the year ended 31 March, 2021
B69: (a) Loan/Overdraft Processing Fee | C69: =SUM('Link Sheet'!D520:D521) -> 196.116 | D69: 0
B70: (b) Interest on Bill discounting & charges | C70: =SUM('Link Sheet'!D525:D525) -> 2461.577 | D70: 731.814
B71: (c) Interest on loan | C71: =SUM('Link Sheet'!D527:D536) -> 22542.971 | D71: 23430.231
B72: (d) Interest on Vehicle loan | C72: =SUM('Link Sheet'!D538:D539) -> 51.085 | D72: 65.544
B74: Total | C74: =SUM(C69:C72) -> 25251.749 | D74: =SUM(D69:D72) -> 24227.589
B76: Note 23
B77: Other expenses
B78: Particulars | C78: =+$C$8 -> For the year ended 31 March, 2022 | D78: =+$D$8 -> For the year ended 31 March, 2021
B79: A. Administrative Expenses
B80: Advertisement | C80: =SUM('Link Sheet'!D548:D548) -> 23.732 | D80: 13.5975
B81: Printing & Stationery | C81: =SUM('Link Sheet'!D550) -> 181.23028 | D81: 118.457
B82: Communication | C82: =SUM('Link Sheet'!D552:D554) -> 183.55504 | D82: 216.08491
B83: Travelling Expenses | C83: =SUM('Link Sheet'!D556:D557) -> 349.994 | D83: 196.991 | G83: FY 14-15
B84: Insurance | C84: =SUM('Link Sheet'!D559:D560) -> 458.369 | D84: 390.674 | E84: Worker's Insurance | G84: =#REF! -> #REF!
B85: Repairs and Maintenance | E85: Other iNsurance | G85: =#REF!+#REF!+#REF! -> #REF!
B86: Building | C86: =SUM('Link Sheet'!B562:B563) -> 672.19345 | D86: 335.49158
B87: Others | C87: =SUM('Link Sheet'!B565:B570) -> 4193.9667 | D87: 2356.816
B88: Brokerage & Commission | C88: =SUM('Link Sheet'!D572) -> 109.61 | D88: 19.144
B89: Professional charges & consultancy charges | C89: =SUM('Link Sheet'!D574:D575) -> 811.878 | D89: 839.01 | G89: =SUM(G84:G85) -> #REF!
B90: Rates and taxes | C90: =SUM('Link Sheet'!D577:D578) -> 62.5 | D90: 29.5515
B91: Office Expenses | C91: =SUM('Link Sheet'!D581:D598) -> 3284.6642 | D91: 1584.4764
B92: Interest on Delay in payment of taxes | C92: =SUM('Link Sheet'!D601:D603) -> 500.457 | D92: 708.24
B93: Liquidty Damages | C93: =SUM('Link Sheet'!B605:B605) -> 217.76 | D93: 49.223
B94: Bank Charges | C94: =SUM('Link Sheet'!D610) -> 3014.9695 | D94: 671.98201
B95: Payments to the auditor as
B96: a. auditor | C96: =SUM('Link Sheet'!D613) -> 175 | D96: 175
B97: b. Other services
B98: Total (A) | C98: =SUM(C80:C97) -> 14239.879 | D98: =SUM(D80:D97) -> 7704.7389
B99: B. Selling expenses
B100: Carriage Outward | C100: =SUM('Link Sheet'!D617) -> 5461.5428 | D100: 1171.59
B101: Total (B) | C101: =SUM(C100:C100) -> 5461.5428 | D101: =SUM(D100:D100) -> 1171.59
B103: Total (A) + (B) | C103: =+C101+C98 -> 19701.422 | D103: =+D101+D98 -> 8876.3289

Sheet CFS
A2: =BS!A1 -> DYNAMIC AIR ENGINEERING INDIA PRIVATE LIMITED
A3: =BS!A2 -> CIN No. : U29192TN2008PTC066303
A4: STATEMENT OF CASH FLOW FOR THE YEAR ENDED 31ST MARCH 2022 | G4: BALANCE SHEET AS AT 31ST MARCH 2022
A5: =BS!A4 -> (All amounts are in Indian Rupees in thousands, except share data and as stated)
B6: Particulars | D6: For the year ended 31st March, 2022 | E6: For the year ended 31st March, 2021
A7: A | B7: CASH FLOW FROM OPERATING ACTIVITIES
B8: Profit before tax from continuing operations | D8: =PL!E18 -> 11220.478 | E8: 3195.779
B9: Profit before tax from discontinuing operations | E9: 0
B10: Profit before tax | D10: =SUM(D8:D9) -> 11220.478 | E10: =SUM(E8:E9) -> 3195.779
B11: Non-cash adjustment to reconcile profit before tax to net cash flows | D11: 0 | E11: 0
B12: Share of (profit)/loss from investment in partnership firm | D12: 0 | E12: 0 | F12: 1000
B13: Depreciation/amortization on continuing operation | D13: =PL!E15 -> 32221.6 | E13: 39070.697
B14: Depreciation/amortization on discontinuing operation | D14: 0 | E14: 0
B15: Impairment/other write off on tangible/intangible assets pertaining to continuing operation | D15: 0 | E15: 0
B16: Impairment/other write off on tangible/intangible assets pertaining to discontinued operation | D16: 0 | E16: 0
B17: Loss/(profit) on sale of fixed assets | D17: 0 | E17: 0
B18: Provision for diminution in value of investments in subsidiary company | D18: 0 | E18: 0
B19: Provision for diminution in value of investments (current plus other long term) | D19: 0 | E19: 0
B20: Employee stock compensation expense | D20: 0 | E20: 0
B21: Unrealized foreign exchange loss | D21: 0 | E21: 0
B22: Premium on forward exchange contract amortized | D22: 0 | E22: 0
B23: Amortization of ancillary cost | D23: 0 | E23: 0
B24: Net gain on sale of current investments | D24: 0 | E24: 0
B25: Interest expense | D25: =PL!E14 -> 25251.749 | E25: 24227.589
B26: Preliminary expenses written off | D26: 0 | E26: 0
B27: Interest income | D27: =-'PL Notes'!C21 -> -391.314 | E27: -144.786
B28: Dividend income | D28: 0 | E28: 0
B29: Operating profit before working capital changes | D29: =SUM(D10:D28) -> 68302.514 | E29: =SUM(E10:E28) -> 66349.279
B31: Movements in working capital :
B32: Increase/(decrease) in trade payables | D32: =BS!G23-BS!H23 -> 14501.335 | E32: -71502.144
B33: Increase / (decrease) in long-term provisions | D33: =BS!G17-BS!H17 -> 0 | E33: 0
B34: Increase / (decrease) in short-term provisions | D34: 0 | E34: 0
B35: Increase/(decrease) in other current liabilities | D35: =BS!G24-BS!H24 -> 3215.1568 | E35: -1020.6692
B36: Increase/ (decrease) in other long-term liabilities | D36: 0 | E36: 0
B37: Increase/ (decrease) in short term provision | D37: =-PL!E25 -> 0 | E37: 0
B38: Decrease/(increase) in trade receivables | D38: =BS!H40-BS!G40 -> -25481.879 | E38: -13401.662
B39: Decrease/(increase) in inventories | D39: =BS!H39-BS!G39 -> -37605.374 | E39: -10854.209
B40: Decrease / (increase) in long-term loans and advances | D40: =BS!H36-BS!G36 -> -8514.816 | E40: 0
B41: Decrease / (increase) in short-term loans and advances | D41: =BS!H42-BS!G42 -> 10125.004 | E41: 37004.588
B42: Decrease/(increase) in other current assets | D42: 0 | E42: 0
B43: Decrease / (increase) in other non-current assets | D43: 0 | E43: 0
B44: Cash generated from /(used in) operations | D44: =SUM(D29:D43) -> 24541.94 | E44: =SUM(E29:E43) -> 6575.1825
B45: Direct taxes paid (net of refunds) | D45: ='BS Notes'!E175 -> 3223.84 | E45: 5259.87
B46: Extraordinary Items | D46: 0 | E46: 0
B47: Net cash flow from/ (used in) operating activities (A) | D47: =D44-D45 -> 21318.1 | E47: =E44-E45 -> 1315.3125
A49: B | B49: CASH FLOW FROM INVESTING ACTIVITIES
B51: Purchase of fixed assets, including intangible assets, CWIP and capital advances | D51: =-'Dep - co'!E26 -> -10314.582 | E51: -163.152
B52: Subsidy Received | D52: ='Dep - co'!F15 -> 1500 | E52: 4500
B53: Proceeds from sale of fixed assets | D53: 0 | E53: 0
B54: Proceeds of non-current investments | D54: 0 | E54: 0
B55: Purchase of non-current investments | D55: 0 | E55: 0
B56: Purchase of current investments | D56: 0 | E56: 0
B57: Proceeds from sale/maturity of current investments | D57: 0 | E57: 0
B58: Investments in bank deposits (having original maturity of more than three months) | D58: 0 | E58: 0
B59: Redemption/maturity of bank deposits (having original maturity of more than three months) | D59: 0 | E59: 0
B60: Purchase consideration for amalgamation | D60: 0 | E60: 0
B61: Interest received | D61: ='PL Notes'!C21 -> 391.314 | E61: 144.786
B62: Dividends received from subsidiary company | D62: 0 | E62: 0
B63: Dividends received | D63: 0 | E63: 0
B64: Net cash flow from/(used in) investing activities (B) | D64: =SUM(D51:D63) -> -8423.2684 | E64: =SUM(E51:E63) -> 4481.634
A66: C | B66: CASH FLOW FROM FINANCING ACTIVITIES
B67: Proceeds from issuance of share capital | D67: =BS!G9-BS!H9 -> 0 | E67: 0
B68: Share application money pending allotment | D68: 0 | E68: 0
B69: Share Premium | D69: 0 | E69: 0
B70: Proceeds from issuance of preference share capital | D70: 0 | E70: 0
B71: Proceeds from long-term borrowings | D71: =BS!G15-BS!H15 -> -26980.76 | E71: 15488.842
B72: Repayment of long-term borrowings | D72: 0 | E72: 0
B73: Proceeds from short-term borrowings | D73: =BS!G20-BS!H20 -> 45807.014 | E73: 2806.6065
B74: Repayment of short-term borrowings | D74: 0 | E74: 0
B75: Interest paid | D75: =-PL!E14 -> -25251.749 | E75: -24227.589
B76: Dividends paid on equity shares | D76: 0 | E76: 0
B77: Dividends paid on preference shares | D77: 0 | E77: 0
B78: Tax on equity dividend paid | D78: 0 | E78: 0
B79: Tax on preference dividend paid | D79: 0 | E79: 0
B80: Net cash flow from/(used in) in financing activities (C) | D80: =SUM(D67:D79) -> -6425.4954 | E80: =SUM(E67:E79) -> -5932.1411
B82: Net increase/(decrease) in cash and cash equivalents (A + B + C) | D82: =D80+D64+D47 -> 6469.3362 | E82: =E80+E64+E47 -> -135.19458
B83: Effect of exchange differences on cash & cash equivalents held in foreign currency | D83: 0 | E83: 0
B84: Cash and cash equivalents at the beginning of the year | D84: =BS!H41 -> 2204.3002 | E84: 2339.4947
B85: Cash and cash equivalents at the end of the year | D85: =SUM(D82:D84) -> 8673.6364 | E85: =SUM(E82:E84) -> 2204.3002
B87: Components of cash and cash equivalents
B88: Cash on hand | D88: ='BS Notes'!E236 -> 19.252 | E88: 18.157
B89: Cheques/ drafts on hand | D89: 0 | E89: 0
B90: With banks- on current account | D90: 0 | E90: 0
B91: − on Current account | D91: =SUM('BS Notes'!E232:E233) -> 509.41935 | E91: 120.62616
B92: − on deposit account | D92: ='BS Notes'!E235 -> 8144.965 | E92: 2065.517
B93: − unpaid dividend accounts* | D93: 0 | E93: 0
B94: − unpaid matured deposits* | D94: 0 | E94: 0
B95: − unpaid matured debentures* | D95: 0 | E95: 0
B96: Total cash and cash equivalents (note 12) | D96: =SUM(D88:D95) -> 8673.6364 | E96: =SUM(E88:E95) -> 2204.3002 | F96: =D85-D96 -> 6.5483619e-11 | G96: =E85-E96 -> -5.2750693e-11
A98: For and on behalf of the Board of Directors of | D98: As per our report of even date
A99: DYNAMIC AIR ENGINEERING INDIA PRIVATE LIMITED | D99: For S.Ravi & Associates | F99: Reason for difference:
D100: Chartered Accountants | F100: ADDITION TO FA | G100: As per Tally | H100: =10314582.36 -> 10314582
D101: Firm Reg No: 009261S | G101: As per Financials | H101: ='Dep - co'!E26 -> 10314.582
G102: Diff | H102: =H100-H101 -> 10304268
A104: K. KARTHIKEYAN | C104: GIRIJA KARTHIKEYAN | D104: S.RAVI
A105: Director | C105: Director | D105: Proprietor
A106: DIN : 01924065 | C106: DIN : 03329379 | D106: M No: 204618
A108: PLACE: CHENNAI
A109: =PL!A48 -> DATE: 02-09-2022

Sheet Dep - co
A1: DYNAMIC AIR ENGINEERING INDIA PRIVATE LIMITED
A2: CIN No. : U29192TN2008PTC066303
A3: ='PL Notes'!B3 -> NOTES TO THE FINANCIAL STATEMENTS FOR THE YEAR ENDED 31 MARCH 2022
A5: Note 11 - Property, Plant & Equipment and Intangible Assets
A6: =CFS!A5 -> (All amounts are in Indian Rupees in thousands, except share data and as stated)
B7: Fixed Assets | D7: Gross Block | H7: Accumulated Depreciation | L7: Net Block
D8: Balance as at 31 March 2021 | E8: Additions/ (Disposals) | F8: Subsidy received | G8: Balance as at 31 March 2022 | H8: =D8 -> Balance as at 31 March 2021 | I8: Depreciation for the year | J8: Subsidy received | K8: =G8 -> Balance as at 31 March 2022 | L8: =H8 -> Balance as at 31 March 2021 | M8: =K8 -> Balance as at 31 March 2022
A9: I | B9: Property, Plant & Equipment
A11: a | B11: Land | C11: 0 | D11: 24942.539 | E11: 0 | F11: 0 | G11: =SUM(D11:F11) -> 24942.539 | H11: 0 | I11: 0 | J11: 0 | K11: =SUM(H11:J11) -> 0 | L11: 24942.539 | M11: =+G11-K11 -> 24942.539
A12: b | B12: Factory Building | C12: 0.1 | D12: 82773.607 | E12: 0 | F12: 0 | G12: =SUM(D12:F12) -> 82773.607 | H12: 22264.801 | I12: =('FA Register'!BS59)/1000 -> 5747.5527 | J12: 0 | K12: =SUM(H12:J12) -> 28012.353 | L12: =+D12-H12 -> 60508.807 | M12: =+G12-K12 -> 54761.254 | N12: ='FA Register'!BT59 -> 54761255 | O12: =M12-N12 -> -54706494
A13: c | B13: Computers & Peripherals | C13: 0.4 | D13: =(1400345.65)/1000 -> 1400.3456 | E13: =('FA Additions'!F18)/1000 -> 272.83893 | F13: 0 | G13: =SUM(D13:F13) -> 1673.1846 | H13: 1129.4034 | I13: =('FA Register'!BS95/1000-I24) -> 190.29025 | J13: 0 | K13: =SUM(H13:J13) -> 1319.6936 | L13: =+D13-H13 -> 270.94227 | M13: =+G13-K13 -> 353.49095 | N13: ='FA Register'!BT95-'FA Register'!BT93 -> 353490.26 | O13: =M13-N13 -> -353136.77
A14: d | B14: Air Conditioners | C14: 0.1391 | D14: 199.784 | E14: 0 | F14: 0 | G14: =SUM(D14:F14) -> 199.784 | H14: 131.83882 | I14: =(SUM('FA Register'!BS97:BS102))/1000 -> 52.946854 | J14: 0 | K14: =SUM(H14:J14) -> 184.78567 | L14: =+D14-H14 -> 67.945181 | M14: =+G14-K14 -> 14.998326 | N14: =SUM('FA Register'!BT97:BT102) -> 14998.05 | O14: =M14-N14 -> -14983.052
A15: e | B15: Plant & Machineries | C15: 0.1391 | D15: 206210.07 | E15: =('FA Additions'!F28)/1000 -> 7302.5 | F15: =('FA Additions'!F45)/1000 -> 1500 | G15: =SUM(D15:E15)-F15 -> 212012.57 | H15: 79634.74 | I15: =('FA Register'!BS301)/1000 -> 22748.461 | J15: 0 | K15: =SUM(H15:J15)+13767 -> 116150.2 | L15: =+D15-H15 -> 126575.33 | M15: =+G15-K15 -> 95862.365 | N15: ='FA Register'!BT301 -> 1.0961479e+08 | O15: =M15-N15 -> -1.0951893e+08
A16: f | B16: Invertor | C16: 0.1391 | D16: 25.5 | E16: 0 | F16: 0 | G16: =SUM(D16:F16) -> 25.5 | H16: 23.709111 | I16: =('FA Register'!BS104)/1000 -> 0.51515904 | J16: 0 | K16: =SUM(H16:J16) -> 24.22427 | L16: =+D16-H16 -> 1.790889 | M16: =+G16-K16 -> 1.27573 | N16: ='FA Register'!BT104 -> 1275 | O16: =M16-N16 -> -1273.7243
A17: g | B17: Telephone Instruments | C17: 0.1391 | D17: 20.948 | E17: 0 | F17: 0 | G17: =SUM(D17:F17) -> 20.948 | H17: 20.546226 | I17: =(SUM('FA Register'!BS106:BS110))/1000 -> 0 | J17: 0 | K17: =SUM(H17:J17) -> 20.546226 | L17: =+D17-H17 -> 0.4017736 | M17: =+G17-K17 -> 0.4017736 | N17: ='FA Register'!BT106+'FA Register'!BT107+'FA Register'!BT108+'FA Register'!BT109+'FA Register'!BT110 -> 401.77219 | O17: =M17-N17 -> -401.37042
A18: h | B18: Office Equipments | C18: 0.1391 | D18: 768.84622 | E18: =('FA Additions'!F35)/1000 -> 82.58343 | F18: 0 | G18: =SUM(D18:F18) -> 851.42965 | H18: 480.04158 | I18: =(SUM('FA Register'!BS112:BS131))/1000 -> 175.97503 | J18: 0 | K18: =SUM(H18:J18)-13767 -> -13110.983 | L18: =+D18-H18 -> 288.80464 | M18: =+G18-K18 -> 13962.413 | N18: =SUM('FA Register'!BT112:BT132) -> 209180.11 | O18: =M18-N18 -> -195217.7
A19: i | B19: Vehicles | C19: 0.2589 | D19: 7298.3147 | E19: =('FA Additions'!F40)/1000 -> 2135.21 | F19: 0 | G19: =SUM(D19:F19) -> 9433.5247 | H19: 5872.3232 | I19: =('FA Register'!BS158)/1000 -> 537.10015 | J19: 0 | K19: =SUM(H19:J19) -> 6409.4234 | L19: =+D19-H19 -> 1425.9915 | M19: =+G19-K19 -> 3024.1013 | N19: ='FA Register'!BT158 -> 3024099.5 | O19: =M19-N19 -> -3021075.4
A20: j | B20: Electrical Installations | D20: 19682.887 | E20: 0 | F20: 0 | G20: =SUM(D20:F20) -> 19682.887 | H20: 10263.618 | I20: =('FA Register'!BS138)/1000 -> 2438.324 | J20: 0 | K20: =SUM(H20:J20) -> 12701.942 | L20: =+D20-H20 -> 9419.269 | M20: =+G20-K20 -> 6980.945 | N20: ='FA Register'!BT138 -> 6980945 | O20: =M20-N20 -> -6973964
A21: k | B21: Furniture & Fixtures | D21: 1677.3565 | E21: =('FA Additions'!F30)/1000 -> 41.45 | F21: 0 | G21: =SUM(D21:F21) -> 1718.8065 | H21: 892.9922 | I21: =('FA Register'!BS330)/1000 -> 205.0155 | J21: 0 | K21: =SUM(H21:J21) -> 1098.0077 | L21: =+D21-H21 -> 784.36427 | M21: =+G21-K21 -> 620.79877 | N21: ='FA Register'!BT330 -> 620798.77 | O21: =M21-N21 -> -620177.98
O22: =M22-N22 -> 0
A23: II | B23: Intangible Assets | O23: =M23-N23 -> 0
A24: a | B24: Software | E24: =('FA Additions'!F12)/1000 -> 480 | G24: =SUM(D24:F24) -> 480 | H24: 0 | I24: =('FA Register'!BS93)/1000 -> 125.41956 | K24: =SUM(H24:J24) -> 125.41956 | L24: =+D24-H24 -> 0 | M24: =+G24-K24 -> 354.58044 | N24: ='FA Register'!BT93 -> 354580.44 | O24: =M24-N24 -> -354225.86
O25: =SUM(O12:O24) -> -1.7575988e+08
B26: Total | D26: =SUM(D11:D24) -> 345000.2 | E26: =SUM(E11:E24) -> 10314.582 | F26: =SUM(F11:F24) -> 1500 | G26: =SUM(G11:G24) -> 353814.78 | H26: =SUM(H11:H24) -> 120714.01 | I26: =SUM(I11:I24) -> 32221.6 | J26: =SUM(J11:J24) -> 0 | K26: =SUM(K11:K24) -> 152935.61 | ... M26: =SUM(M11:M24) -> 200879.16
A28: II | B28: Intangible Assets
B30: Total | D30: 0 | E30: 0 | F30: 0 | G30: 0 | H30: 0 | I30: 0 | J30: 0 | K30: 0 | L30: 0 | M30: 0
A31: III | B31: Capital Work In Progress
A32: a | B32: Land | F32: 0 | G32: =SUM(D32:F32) -> 0 | H32: 0 | I32: 0 | J32: 0 | K32: 0 | L32: =+D32-H32 -> 0 | M32: =+G32-K32 -> 0
A33: b | B33: Building | F33: 0 | G33: =SUM(D33:F33) -> 0 | H33: 0 | I33: 0 | J33: 0 | K33: 0 | L33: =+D33-H33 -> 0 | M33: =+G33-K33 -> 0
A34: c | B34: Plant and Machinery | F34: 0 | G34: =SUM(D34:F34) -> 0 | H34: 0 | I34: 0 | J34: 0 | K34: 0 | L34: =+D34-H34 -> 0 | M34: =+G34-K34 -> 0
B36: Total | D36: =SUM(D30:D35) -> 0 | E36: =SUM(E30:E35) -> 0 | F36: =SUM(F30:F35) -> 0 | G36: =SUM(G30:G35) -> 0 | H36: =SUM(H30:H35) -> 0 | I36: =SUM(I30:I35) -> 0 | J36: =SUM(J30:J35) -> 0 | K36: =SUM(K30:K35) -> 0 | L36: =SUM(L30:L35) -> 0 | M36: =SUM(M31:M35) -> 0
L39: As per our report of even date
A40: For and on behalf of the Board ofDirectors of | L40: For S.Ravi & Associates
A41: DYNAMIC AIR ENGINEERING INDIA PRIVATE LIMITED | L41: Chartered Accountants
L42: Firm Reg No: 009261S
A46: K . KARTHIKEYAN | D46: GIRIJA KARTHIKEYAN | L46: S.RAVI
A47: Director | D47: Director | L47: Proprietor
A48: DIN : 01924065 | D48: DIN : 03329379 | L48: M No: 204618
A50: PLACE: CHENNAI
A51: =+PL!A48 -> DATE: 02-09-2022

Sheet Def Tax
A1: ='Dep - co'!A1 -> DYNAMIC AIR ENGINEERING INDIA PRIVATE LIMITED
A2: ='Dep - co'!A2 -> CIN No. : U29192TN2008PTC066303
A3: DEFERRED TAX CALCULATION
B4: Schedule for Deferred Tax for the year ended 31.03.22
C5: 31st Mar 22 | D5: 31st Mar 21
B7: Income Tax Rate | C7: 0.25 | D7: 0.25
B8: Surcharge | C8: =+IF('STI '!F41>10000000,C7*7%,0) -> 0.0175 | D8: 0
B9: Education cess @ 4% | C9: 0 | D9: 0
B10: Health and education cess @ 4% | C10: =+(C7+C8)*4% -> 0.0107 | D10: 0.01
B11: TOTAL | C11: =SUM(C7:C10) -> 0.2782 | D11: =SUM(D7:D10) -> 0.26
B13: Deferred tax Asset / Liability arising on account of
A15: 1 | B15: Block of Assets | F15: 16644174 | G15: =F15*D11 -> 4327485.2
B16: Closing WDV of Assets as at yearend - as per Income Tax Act | C16: ='Dep IT'!K39 -> 1.8977858e+08
B17: Closing WDV of Assets as at yearend - as per Books | C17: ='Dep - co'!M26*1000 -> 2.0087916e+08
B18: Timing Difference on account of Closing WDV | C18: =+C16-C17 -> -11100581 | D18: =+C18*C11 -> -3088181.7 | E18: DTA / (DTL)
A20: 2 | B20: Others
B21: On account of Gratuity provision | C21: =BS!G17*1000 -> 742962 | D21: =C21*C11 -> 206692.03 | E21: DTA / (DTL)
B24: Net Deferred Tax ( liability) / Asset | D24: =SUM(D18:D21) -> -2881489.6
B26: Closing Balance of Deferred Tax Asset/(Liability)
C27: Asset | D27: Liability
B28: Opening Balance B/F - (DTL)/DTA | D28: =-+BS!H16*1000 -> -4666306.9 | E28: 6754.99
B29: Provision during the year (DTL)/ DTA | D29: =D24-D28 -> 1784817.2 | E29: -2088.68
B30: Closing Balance of Deferred Tax (Liability ) Asset | D30: =D24 -> -2881489.6 | E30: =SUM(E28:E29) -> 4666.31
B32: Net Def Tax (Liability)/ Asset at the end of the year - 31-3-2022 | D32: =D24 -> -2881489.6
B34: Entries to be passed for the year 2021-2022
B35: Deferred Tax asset/Liability | C35: =D29 -> 1784817.2
B36: To Profit & Loss account | D36: =+C35 -> 1784817.2
C38: =SUM(C35:C36) -> 1784817.2 | D38: =SUM(D35:D36) -> 1784817.2

Sheet FA  Register
A1: Depreciation Workings as per Companies Act 2013
A3: Example
A4: WDV Rate = 1 - ((salvage / cost) ^ (1 / life)) | AI4: Salvage Rate | AJ4: 0.05
A5: Sl No | B5: Asset Name | C5: Classification | D5: Rate of Dep | E5: Cost (Rs.) | F5: Addition during | G5: Date of Addition | H5: End Date | I5: Useful life | J5: No of days for which depn is charged in the year acquisition | K5: No of Days to be charged in the last year of useful life | L5: Dep to be calc in Last year on | M5: No. of Days | N5: Depn | O5: WDV as on 31.03.2009 | P5: No. of Days | Q5: Depn | R5: WDV as on 31.03.2010 | S5: No. of Days | T5: Depn | U5: WDV as on 31.03.2011 | V5: No. of Days | W5: Depn | X5: WDV as on 31.03.2012 | Y5: No. of Days | Z5: Depn | AA5: WDV as on 31.03.2013 | AB5: No. of Days | AC5: Depn | AD5: WDV as on 31.03.2014 | AE5: Total Depn | AF5: WDV | AG5: Check -Difference | AH5: Completed Life in Years | AI5: Usefule life as per Companies Act 2013 | AJ5: Balance Life | AK5: New Depreciation Rate | AL5: Adjust against Retained Earning | AM5: No. of Days | AN5: Depreciation already Charged at old Rate (books) | AO5: Depreciation at New Rate for FY 14-15 | AP5: Check - Written Down Value 31-3-15 | AQ5: New WDV as on 31/03/2015 | AR5: Check | AS5: Diff in Dep to be accounted in Mar 15 | AT5: WDV as per books (old Comp Act) | AU5: WDV to be shown as on 31/03/2015 | AW5: No of days | AX5: Dep-15-16 | AY5: WDV 15-16 | BA5: Dep-16-17 | BB5: WDV 16-17 | BC5: Use ful Life | BD5: Completed Life | BE5: Bal Life | BG5: Dep-17-18 | BH5: WDV 17-18 | BI5: Dep-18-19 | BJ5: WDV 18-19 | BK5: Dep- 19-20 | BL5: WDV -19-20 | BM5: Subsidy received | BN5: WDV as on 01-04-2020 | BO5: Dep--20-21 | BP5: WDV 20-21 | BQ5: Subsidy received | BR5: WDV as on 01-04-2021 | BS5: Dep-21-22 | BT5: WDV 21-22 | BU5: Dep-22-23 | BV5: WDV 22-23 | BW5: Dep-23-24 | BX5: WDV 23-24 | BY5: Dep-24-25 | BZ5: WDV 24-25 | CA5: Dep-25-26 | CB5: WDV 25-26 | CC5: Dep-26-27 | CD5: WDV 26-27 | CE5: Dep 27-28 | CF5: WDV 27-28 | CG5: Dep 28-29 | CH5: WDV 28-29 | CI5: Dep 29-30 | CJ5: WDV 29-30 | CK5: Dep 30-31 | CL5: WDV 30-31 | CM5: Dep -31-32 | CN5: WDV 31-32 | CO5: Dep 32-33 | CP5: WDV 32-33 | CQ5: Dep 33-34 | CR5: WDV 33-34 | CS5: Dep34-35 | CT5: WDV34-35 | CU5: Dep35-36 | CV5: WDV35-36 | CW5: Dep36-37 | CX5: WDV36-37 | CY5: Dep37-38 | CZ5: WDV37-38 | DA5: Dep38-39 | DB5: WDV38-39 | DC5: Dep39-40 | DD5: WDV39-40 | DE5: Dep40-41 | DF5: WDV40-41 | DG5: Dep41-42 | DH5: WDV41-42 | DI5: Dep42-43 | DJ5: WDV42-43 | DK5: Dep43-44 | DL5: WDV43-44 | DM5: Dep44-45 | DN5: WDV44-45 | DO5: Dep45-46 | DP5: WDV45-46 | DQ5: Dep46-47 | DR5: WDV46-47 | DS5: Dep47-48 | DT5: WDV47-48 | DU5: Dep48-49 | DV5: WDV48-49
M6: 39903 | N6: FY 08-09 | P6: 40268 | Q6: FY 09-10 | S6: 40633 | T6: FY 10-11 | V6: 40999 | W6: FY 11-12 | Y6: 41364 | Z6: FY 12-13 | AB6: 41729 | AC6: FY 13-14 | AE6: Till 31.03.14 | AF6: As on 31.03.14 | AH6: 41729 | AI6: (years) | AJ6: (years) | AM6: 42094 | AN6: FY14-15 | AT6: 42094 | AU6: Check | AW6: 42460 | AX6: 2015-16 | AZ6: 42825 | BD6: 42825 | BF6: 43190 | BI6: 43555 | BK6: 43921 | BO6: 44286 | BS6: 44651 | DW6: Salvage value | DX6: Check
A8: 1 | B8: Factory Shed | C8: Building | D8: 0.1 | E8: 845555 | F8: opening | G8: 39547 | M8: =$M$6-G8+1-6 -> 351 | N8: =ROUND(E8*M8/365*D8,0) -> 81312 | O8: =E8-N8 -> 764243 | P8: =IF(($P$6-G8+1)>365,365,($P$6-G8+1)) -> 365 | Q8: =ROUND(O8*13.91%/365*P8,0) -> 106306 | R8: =O8-Q8 -> 657937 | S8: =IF(($S$6-G8+1)>365,365,($Y$6-G8+1)) -> 365 | T8: =ROUND(R8*13.91%/365*S8,0) -> 91519 | U8: =R8-T8 -> 566418 | V8: =IF(($V$6-G8+1)>365,365,($V$6-G8+1)) -> 365 | W8: =186694/(U59+825639)*U8 -> 31018.673 | X8: =IF((U8-W8)>0,U8-W8,E8-W8) -> 535399.33 | Y8: =IF(($Y$6-G8+1)>365,365,($Y$6-G8+1)) -> 365 | Z8: =ROUND(IF(X8>0,X8*$D8/365*Y8,($E8*$D8*Y8/365)),0) -> 53540 | AA8: =IF((X8-Z8)>0,X8-Z8,$E8-Z8) -> 481859.33 | AB8: =IF(($AB$6-G8+1)>365,365,($AB$6-G8+1)) -> 365 | AC8: =ROUND(IF(AA8>0,AA8*$D8/365*AB8,($E8*$D8*AB8/365)),0) -> 48186 | AD8: =IF((AA8-AC8)>0,AA8-AC8,$E8-AC8) -> 433673.33 | AE8: =T8+W8+Z8+AC8+Q8+N8 -> 411881.67 | AF8: =E8-AE8 -> 433673.33 | AG8: =AD8-AF8 -> 0 | AH8: =($AH$6-G8+1)/365 -> 5.9808219 | AI8: 30 | AJ8: =AI8-AH8 -> 24.019178 | AK8: =IF(AJ8>0,1-(((E8*$AJ$4)/AF8)^(1/AJ8)),0) -> 0.092374858 | AL8: =IF(AJ8<0,AF8-(E8*5%),0) -> 0 | AM8: =IF(($AM$6-$G8+1)>365,365,($AM$6-$G8+1)) -> 365 | AN8: =ROUND(IF(AF8>0,AF8*$D8/365*AM8,($E8*$D8*AM8/365)),0) -> 43367 | AO8: =MIN(ROUND(IF(AL8>0,0,(AK8*AF8)*AM8/365),0),AF8-(E8*5%)) -> 40061 | AP8: =ROUND(+IF(AJ8<1,(E8*5%),IF(AF8>0,AF8-AO8,E8-AO8)),0) -> 393612 | AQ8: =AF8-AO8-AL8 -> 393612.33 | AR8: =$AF8-($AL8+$AO8+$AP8) -> 0.32749451 | AS8: =AO8-AN8 -> -3306 | AT8: =AF8-AN8 -> 390306.33 | AU8: =AT8-AS8-AL8 -> 393612.33 | AV8: =AU8-AQ8 -> 0 | AW8: =IF(($AW$6-$G8+1)>365,365,($AW$6-$G8+1)) -> 365 | AX8: =AU8*AK8 -> 36359.883 | AY8: =AU8-AX8 -> 357252.44 | AZ8: =IF(($AZ$6-$G8+1)>365,365,($AZ$6-$G8+1)) -> 365 | BA8: =AY8*AK8 -> 33001.144 | BB8: =AY8-BA8 -> 324251.3 | BC8: =60*365 -> 21900 | BD8: =+$BD$6-G8 -> 3278 | BE8: =+BC8-BD8 -> 18622 | BF8: =IF(($BF$6-$G8+1)>365,365,($BF$6-$G8+1)) -> 365 | BG8: =IF(BE8>365,IF(BF8=365,BB8*AK8,BB8*AK8*BF8/365),0) -> 29952.668 | BH8: =+BB8-BG8 -> 294298.63 | BI8: =+BH8*AK8 -> 27185.794 | BJ8: =+BH8-BI8 -> 267112.84 | BK8: =+ROUND(BJ8*AK8,2) -> 24674.51 | BL8: =+BJ8-BK8 -> 242438.33 | BN8: =BL8-BM8 -> 242438.33 | BO8: =+BL8*AK8 -> 22395.206 | BP8: =+BL8-BO8 -> 220043.12 | BR8: =BP8-BQ8 -> 220043.12 | BS8: =+BR8*AK8 -> 20326.452 | BT8: =+BP8-BS8 -> 199716.67 | BU8: =+BT8*AK8 -> 18448.799 | BV8: =+BT8-BU8 -> 181267.87 | BW8: =+BV8*AK8 -> 16744.594 | BX8: =+BV8-BW8 -> 164523.28 | BY8: =+BX8*AK8 -> 15197.814 | BZ8: =+BX8-BY8 -> 149325.46 | CA8: =+BZ8*AK8 -> 13793.918 | CB8: =+BZ8-CA8 -> 135531.54 | CC8: =+CB8*AK8 -> 12519.707 | CD8: =+CB8-CC8 -> 123011.84 | CE8: =+CD8*AK8 -> 11363.201 | CF8: =+CD8-CE8 -> 111648.64 | CG8: =+CF8*AK8 -> 10313.527 | CH8: =+CF8-CG8 -> 101335.11 | CI8: =+CH8*AK8 -> 9360.8163 | CJ8: =+CH8-CI8 -> 91974.293 | CK8: =+CJ8*AK8 -> 8496.1123 | CL8: =+CJ8-CK8 -> 83478.181 | CM8: =+CL8*AK8 -> 7711.2851 | CN8: =+CL8-CM8 -> 75766.896 | CO8: =+CN8*AK8 -> 6998.9562 | CP8: =+CN8-CO8 -> 68767.94 | CQ8: =+CP8*AK8 -> 6352.4286 | CR8: =+CP8-CQ8 -> 62415.511 | CS8: =+CR8*AK8 -> 5765.624 | CT8: =+CR8-CS8 -> 56649.887 | CU8: =+CT8*AK8 -> 5233.0253 | CV8: =+CT8-CU8 -> 51416.862 | CW8: =+CV8*AK8 -> 4749.6253 | CX8: =+CV8-CW8 -> 46667.236 | CY8: =+CX8*AK8 -> 4310.8793 | CZ8: =+CX8-CY8 -> 42356.357 | DA8: =+CZ8-E8*5% -> 78.607094 | DB8: =+CZ8-DA8 -> 42277.75 | DC8: 0 | DD8: =+DB8-DC8 -> 42277.75 | DE8: 0 | DF8: =+DD8-DE8 -> 42277.75 | DG8: 0 | DH8: =+DF8-DG8 -> 42277.75 | DJ8: =+DH8-DI8 -> 42277.75 | DL8: =+DJ8-DK8 -> 42277.75 | DN8: =+DL8-DM8 -> 42277.75 | DP8: =+DN8-DO8 -> 42277.75 | DR8: =+DP8-DQ8 -> 42277.75 | DT8: =+DR8-DS8 -> 42277.75 | DW8: =+E8*5% -> 42277.75 | DX8: =+DW8-DR8 -> 0
A9: =A8+1 -> 2 | B9: Factory Building Construction | C9: Building | D9: 0.1 | E9: 23500 | F9: opening | G9: 39969 | P9: =IF(($P$6-G9+1)>365,365,($P$6-G9+1)) -> 300 | Q9: =ROUND(E9*P9/365*D9,0) -> 1932 | R9: =E9-Q9 -> 21568 | S9: =IF(($S$6-G9+1)>365,365,($Y$6-G9+1)) -> 365 | T9: =ROUND(R9*13.91%/365*S9,0) -> 3000 | U9: =R9-T9 -> 18568 | V9: =IF(($V$6-G9+1)>365,365,($V$6-G9+1)) -> 365 | W9: =186694/(U59+825639)*U9 -> 1016.8369 | X9: =IF((U9-W9)>0,U9-W9,E9-W9) -> 17551.163 | Y9: =IF(($Y$6-G9+1)>365,365,($Y$6-G9+1)) -> 365 | Z9: =ROUND(IF(X9>0,X9*$D9/365*Y9,($E9*$D9*Y9/365)),0) -> 1755 | AA9: =IF((X9-Z9)>0,X9-Z9,$E9-Z9) -> 15796.163 | AB9: =IF(($AB$6-G9+1)>365,365,($AB$6-G9+1)) -> 365 | AC9: =ROUND(IF(AA9>0,AA9*$D9/365*AB9,($E9*$D9*AB9/365)),0) -> 1580 | AD9: =IF((AA9-AC9)>0,AA9-AC9,$E9-AC9) -> 14216.163 | AE9: =T9+W9+Z9+AC9+Q9+N9 -> 9283.8369 | AF9: =E9-AE9 -> 14216.163 | AG9: =AD9-AF9 -> 0 | AH9: =($AH$6-G9+1)/365 -> 4.8246575 | AI9: 30 | AJ9: =AI9-AH9 -> 25.175342 | AK9: =IF(AJ9>0,1-(((E9*$AJ$4)/AF9)^(1/AJ9)),0) -> 0.094284365 | AL9: =IF(AJ9<0,AF9-(E9*5%),0) -> 0 | AM9: =IF(($AM$6-$G9+1)>365,365,($AM$6-$G9+1)) -> 365 | AN9: =ROUND(IF(AF9>0,AF9*$D9/365*AM9,($E9*$D9*AM9/365)),0) -> 1422 | AO9: =MIN(ROUND(IF(AL9>0,0,(AK9*AF9)*AM9/365),0),AF9-(E9*5%)) -> 1340 | AP9: =ROUND(+IF(AJ9<1,(E9*5%),IF(AF9>0,AF9-AO9,E9-AO9)),0) -> 12876 | AQ9: =AF9-AO9-AL9 -> 12876.163 | AR9: =$AF9-($AL9+$AO9+$AP9) -> 0.16312144 | AS9: =AO9-AN9 -> -82 | AT9: =AF9-AN9 -> 12794.163 | AU9: =AT9-AS9-AL9 -> 12876.163 | AV9: =AU9-AQ9 -> 0 | AW9: =IF(($AW$6-$G9+1)>365,365,($AW$6-$G9+1)) -> 365 | AX9: =AU9*AK9 -> 1214.0209 | AY9: =AU9-AX9 -> 11662.142 | AZ9: =IF(($AZ$6-$G9+1)>365,365,($AZ$6-$G9+1)) -> 365 | BA9: =AY9*AK9 -> 1099.5577 | BB9: =AY9-BA9 -> 10562.585 | BC9: =60*365 -> 21900 | BD9: =+$BD$6-G9 -> 2856 | BE9: =+BC9-BD9 -> 19044 | BF9: =IF(($BF$6-$G9+1)>365,365,($BF$6-$G9+1)) -> 365 | BG9: =IF(BE9>365,IF(BF9=365,BB9*AK9,BB9*AK9*BF9/365),0) -> 995.88658 | BH9: =+BB9-BG9 -> 9566.698 | BI9: =+BH9*AK9 -> 901.99005 | BJ9: =+BH9-BI9 -> 8664.708 | BK9: =+ROUND(BJ9*AK9,2) -> 816.95 | BL9: =+BJ9-BK9 -> 7847.758 | BN9: =BL9-BM9 -> 7847.758 | BO9: =+BL9*AK9 -> 739.92088 | BP9: =+BL9-BO9 -> 7107.8371 | BR9: =BP9-BQ9 -> 7107.8371 | BS9: =+BR9*AK9 -> 670.15791 | BT9: =+BP9-BS9 -> 6437.6792 | BU9: =+BT9*AK9 -> 606.97249 | BV9: =+BT9-BU9 -> 5830.7067 | BW9: =+BV9*AK9 -> 549.74448 | BX9: =+BV9-BW9 -> 5280.9622 | BY9: =+BX9*AK9 -> 497.91217 | BZ9: =+BX9-BY9 -> 4783.05 | CA9: =+BZ9*AK9 -> 450.96684 | CB9: =+BZ9-CA9 -> 4332.0832 | CC9: =+CB9*AK9 -> 408.44771 | CD9: =+CB9-CC9 -> 3923.6355 | CE9: =+CD9*AK9 -> 369.93748 | CF9: =+CD9-CE9 -> 3553.698 | CG9: =+CF9*AK9 -> 335.05816 | CH9: =+CF9-CG9 -> 3218.6398 | CI9: =+CH9*AK9 -> 303.46741 | CJ9: =+CH9-CI9 -> 2915.1724 | CK9: =+CJ9*AK9 -> 274.85518 | CL9: =+CJ9-CK9 -> 2640.3172 | CM9: =+CL9*AK9 -> 248.94064 | CN9: =+CL9-CM9 -> 2391.3766 | CO9: =+CN9*AK9 -> 225.46943 | CP9: =+CN9-CO9 -> 2165.9072 | CQ9: =+CP9*AK9 -> 204.21118 | CR9: =+CP9-CQ9 -> 1961.696 | CS9: =+CR9*AK9 -> 184.95726 | CT9: =+CR9-CS9 -> 1776.7387 | CU9: =+CT9*AK9 -> 167.51868 | CV9: =+CT9-CU9 -> 1609.2201 | CW9: =+CV9*AK9 -> 151.72429 | CX9: =+CV9-CW9 -> 1457.4958 | CY9: =+CX9*AK9 -> 137.41906 | CZ9: =+CX9-CY9 -> 1320.0767 | DA9: =+CZ9*AK9 -> 124.46259 | DB9: =+CZ9-DA9 -> 1195.6141 | DC9: =+DB9-E9*5% -> 20.61411 | DD9: =+DB9-DC9 -> 1175 | DE9: 0 | DF9: =+DD9-DE9 -> 1175 | DG9: 0 | DH9: =+DF9-DG9 -> 1175 | DJ9: =+DH9-DI9 -> 1175 | DL9: =+DJ9-DK9 -> 1175 | DN9: =+DL9-DM9 -> 1175 | DP9: =+DN9-DO9 -> 1175 | DR9: =+DP9-DQ9 -> 1175 | DT9: =+DR9-DS9 -> 1175 | DW9: =+E9*5% -> 1175 | DX9: =+DW9-DR9 -> 0
A10: =A9+1 -> 3 | B10: Factory Building Construction | C10: Building | D10: 0.1 | E10: 5500 | F10: opening | G10: 40033 | P10: =IF(($P$6-G10+1)>365,365,($P$6-G10+1))+1 -> 237 | Q10: =ROUND(E10*P10/365*D10,0) -> 357 | R10: =E10-Q10 -> 5143 | S10: =IF(($S$6-G10+1)>365,365,($Y$6-G10+1)) -> 365 | T10: =ROUND(R10*13.91%/365*S10,0) -> 715 | U10: =R10-T10 -> 4428 | V10: =IF(($V$6-G10+1)>365,365,($V$6-G10+1)) -> 365 | W10: =186694/(U59+825639)*U10 -> 242.48997 | X10: =IF((U10-W10)>0,U10-W10,E10-W10) -> 4185.51 | Y10: =IF(($Y$6-G10+1)>365,365,($Y$6-G10+1)) -> 365 | Z10: =ROUND(IF(X10>0,X10*$D10/365*Y10,($E10*$D10*Y10/365)),0) -> 419 | AA10: =IF((X10-Z10)>0,X10-Z10,$E10-Z10) -> 3766.51 | AB10: =IF(($AB$6-G10+1)>365,365,($AB$6-G10+1)) -> 365 | AC10: =ROUND(IF(AA10>0,AA10*$D10/365*AB10,($E10*$D10*AB10/365)),0) -> 377 | AD10: =IF((AA10-AC10)>0,AA10-AC10,$E10-AC10) -> 3389.51 | AE10: =T10+W10+Z10+AC10+Q10+N10 -> 2110.49 | AF10: =E10-AE10 -> 3389.51 | AG10: =AD10-AF10 -> 0 | AH10: =($AH$6-G10+1)/365 -> 4.6493151 | AI10: 30 | AJ10: =AI10-AH10 -> 25.350685 | AK10: =IF(AJ10>0,1-(((E10*$AJ$4)/AF10)^(1/AJ10)),0) -> 0.094327022 | AL10: =IF(AJ10<0,AF10-(E10*5%),0) -> 0 | AM10: =IF(($AM$6-$G10+1)>365,365,($AM$6-$G10+1)) -> 365 | AN10: =ROUND(IF(AF10>0,AF10*$D10/365*AM10,($E10*$D10*AM10/365)),0) -> 339 | AO10: =MIN(ROUND(IF(AL10>0,0,(AK10*AF10)*AM10/365),0),AF10-(E10*5%)) -> 320 | AP10: =ROUND(+IF(AJ10<1,(E10*5%),IF(AF10>0,AF10-AO10,E10-AO10)),0) -> 3070 | AQ10: =AF10-AO10-AL10 -> 3069.51 | AR10: =$AF10-($AL10+$AO10+$AP10) -> -0.48996652 | AS10: =AO10-AN10 -> -19 | AT10: =AF10-AN10 -> 3050.51 | AU10: =AT10-AS10-AL10 -> 3069.51 | AV10: =AU10-AQ10 -> 0 | AW10: =IF(($AW$6-$G10+1)>365,365,($AW$6-$G10+1)) -> 365 | AX10: =AU10*AK10 -> 289.53774 | AY10: =AU10-AX10 -> 2779.9723 | AZ10: =IF(($AZ$6-$G10+1)>365,365,($AZ$6-$G10+1)) -> 365 | BA10: =AY10*AK10 -> 262.22651 | BB10: =AY10-BA10 -> 2517.7458 | BC10: =60*365 -> 21900 | BD10: =+$BD$6-G10 -> 2792 | BE10: =+BC10-BD10 -> 19108 | BF10: =IF(($BF$6-$G10+1)>365,365,($BF$6-$G10+1)) -> 365 | BG10: =IF(BE10>365,IF(BF10=365,BB10*AK10,BB10*AK10*BF10/365),0) -> 237.49146 | BH10: =+BB10-BG10 -> 2280.2543 | BI10: =+BH10*AK10 -> 215.0896 | BJ10: =+BH10-BI10 -> 2065.1647 | BK10: =+ROUND(BJ10*AK10,2) -> 194.8 | BL10: =+BJ10-BK10 -> 1870.3647 | BN10: =BL10-BM10 -> 1870.3647 | BO10: =+BL10*AK10 -> 176.42593 | BP10: =+BL10-BO10 -> 1693.9388 | BR10: =BP10-BQ10 -> 1693.9388 | BS10: =+BR10*AK10 -> 159.7842 | BT10: =+BP10-BS10 -> 1534.1546 | BU10: =+BT10*AK10 -> 144.71223 | BV10: =+BT10-BU10 -> 1389.4423 | BW10: =+BV10*AK10 -> 131.06196 | BX10: =+BV10-BW10 -> 1258.3804 | BY10: =+BX10*AK10 -> 118.69928 | BZ10: =+BX10-BY10 -> 1139.6811 | CA10: =+BZ10*AK10 -> 107.50273 | CB10: =+BZ10-CA10 -> 1032.1784 | CC10: =+CB10*AK10 -> 97.362314 | CD10: =+CB10-CC10 -> 934.81607 | CE10: =+CD10*AK10 -> 88.178417 | CF10: =+CD10-CE10 -> 846.63766 | CG10: =+CF10*AK10 -> 79.860809 | CH10: =+CF10-CG10 -> 766.77685 | CI10: =+CH10*AK10 -> 72.327777 | CJ10: =+CH10-CI10 -> 694.44907 | CK10: =+CJ10*AK10 -> 65.505313 | CL10: =+CJ10-CK10 -> 628.94376 | CM10: =+CL10*AK10 -> 59.326392 | CN10: =+CL10-CM10 -> 569.61737 | CO10: =+CN10*AK10 -> 53.73031 | CP10: =+CN10-CO10 -> 515.88706 | CQ10: =+CP10*AK10 -> 48.66209 | CR10: =+CP10-CQ10 -> 467.22497 | CS10: =+CR10*AK10 -> 44.07194 | CT10: =+CR10-CS10 -> 423.15303 | CU10: =+CT10*AK10 -> 39.914765 | CV10: =+CT10-CU10 -> 383.23826 | CW10: =+CV10*AK10 -> 36.149724 | CX10: =+CV10-CW10 -> 347.08854 | CY10: =+CX10*AK10 -> 32.739828 | CZ10: =+CX10-CY10 -> 314.34871 | DA10: =+CZ10*AK10 -> 29.651578 | DB10: =+CZ10-DA10 -> 284.69713 | DC10: =+DB10-E10*5% -> 9.6971308 | DD10: =+DB10-DC10 -> 275 | DE10: 0 | DF10: =+DD10-DE10 -> 275 | DG10: 0 | DH10: =+DF10-DG10 -> 275 | DJ10: =+DH10-DI10 -> 275 | DL10: =+DJ10-DK10 -> 275 | DN10: =+DL10-DM10 -> 275 | DP10: =+DN10-DO10 -> 275 | DR10: =+DP10-DQ10 -> 275 | DT10: =+DR10-DS10 -> 275 | DW10: =+E10*5% -> 275 | DX10: =+DW10-DR10 -> 0
A11: =A10+1 -> 4 | B11: Factory Building Construction | C11: Building | D11: 0.1 | E11: 37400 | F11: opening | G11: 40039 | P11: =IF(($P$6-G11+1)>365,365,($P$6-G11+1))+1 -> 231 | Q11: =ROUND(E11*P11/365*D11,0) -> 2367 | R11: =E11-Q11 -> 35033 | S11: =IF(($S$6-G11+1)>365,365,($Y$6-G11+1)) -> 365 | T11: =ROUND(R11*13.91%/365*S11,0) -> 4873 | U11: =R11-T11 -> 30160 | V11: =IF(($V$6-G11+1)>365,365,($V$6-G11+1)) -> 365 | W11: =186694/(U59+825639)*U11 -> 1651.648 | X11: =IF((U11-W11)>0,U11-W11,E11-W11) -> 28508.352 | Y11: =IF(($Y$6-G11+1)>365,365,($Y$6-G11+1)) -> 365 | Z11: =ROUND(IF(X11>0,X11*$D11/365*Y11,($E11*$D11*Y11/365)),0) -> 2851 | AA11: =IF((X11-Z11)>0,X11-Z11,$E11-Z11) -> 25657.352 | AB11: =IF(($AB$6-G11+1)>365,365,($AB$6-G11+1)) -> 365 | AC11: =ROUND(IF(AA11>0,AA11*$D11/365*AB11,($E11*$D11*AB11/365)),0) -> 2566 | AD11: =IF((AA11-AC11)>0,AA11-AC11,$E11-AC11) -> 23091.352 | AE11: =T11+W11+Z11+AC11+Q11+N11 -> 14308.648 | AF11: =E11-AE11 -> 23091.352 | AG11: =AD11-AF11 -> 0 | AH11: =($AH$6-G11+1)/365 -> 4.6328767 | AI11: 30 | AJ11: =AI11-AH11 -> 25.367123 | AK11: =IF(AJ11>0,1-(((E11*$AJ$4)/AF11)^(1/AJ11)),0) -> 0.094334931 | AL11: =IF(AJ11<0,AF11-(E11*5%),0) -> 0 | AM11: =IF(($AM$6-$G11+1)>365,365,($AM$6-$G11+1)) -> 365 | AN11: =ROUND(IF(AF11>0,AF11*$D11/365*AM11,($E11*$D11*AM11/365)),0) -> 2309 | AO11: =MIN(ROUND(IF(AL11>0,0,(AK11*AF11)*AM11/365),0),AF11-(E11*5%)) -> 2178 | AP11: =ROUND(+IF(AJ11<1,(E11*5%),IF(AF11>0,AF11-AO11,E11-AO11)),0) -> 20913 | AQ11: =AF11-AO11-AL11 -> 20913.352 | AR11: =$AF11-($AL11+$AO11+$AP11) -> 0.35198958 | AS11: =AO11-AN11 -> -131 | AT11: =AF11-AN11 -> 20782.352 | AU11: =AT11-AS11-AL11 -> 20913.352 | AV11: =AU11-AQ11 -> 0 | AW11: =IF(($AW$6-$G11+1)>365,365,($AW$6-$G11+1)) -> 365 | AX11: =AU11*AK11 -> 1972.8596 | AY11: =AU11-AX11 -> 18940.492 | AZ11: =IF(($AZ$6-$G11+1)>365,365,($AZ$6-$G11+1)) -> 365 | BA11: =AY11*AK11 -> 1786.75 | BB11: =AY11-BA11 -> 17153.742 | BC11: =60*365 -> 21900 | BD11: =+$BD$6-G11 -> 2786 | BE11: =+BC11-BD11 -> 19114 | BF11: =IF(($BF$6-$G11+1)>365,365,($BF$6-$G11+1)) -> 365 | BG11: =IF(BE11>365,IF(BF11=365,BB11*AK11,BB11*AK11*BF11/365),0) -> 1618.1971 | BH11: =+BB11-BG11 -> 15535.545 | BI11: =+BH11*AK11 -> 1465.5446 | BJ11: =+BH11-BI11 -> 14070.001 | BK11: =+ROUND(BJ11*AK11,2) -> 1327.29 | BL11: =+BJ11-BK11 -> 12742.711 | BN11: =BL11-BM11 -> 12742.711 | BO11: =+BL11*AK11 -> 1202.0827 | BP11: =+BL11-BO11 -> 11540.628 | BR11: =BP11-BQ11 -> 11540.628 | BS11: =+BR11*AK11 -> 1088.6843 | BT11: =+BP11-BS11 -> 10451.944 | BU11: =+BT11*AK11 -> 985.98338 | BV11: =+BT11-BU11 -> 9465.9602 | BW11: =+BV11*AK11 -> 892.9707 | BX11: =+BV11-BW11 -> 8572.9895 | BY11: =+BX11*AK11 -> 808.73237 | BZ11: =+BX11-BY11 -> 7764.2571 | CA11: =+BZ11*AK11 -> 732.44066 | CB11: =+BZ11-CA11 -> 7031.8164 | CC11: =+CB11*AK11 -> 663.34592 | CD11: =+CB11-CC11 -> 6368.4705 | CE11: =+CD11*AK11 -> 600.76923 | CF11: =+CD11-CE11 -> 5767.7013 | CG11: =+CF11*AK11 -> 544.0957 | CH11: =+CF11-CG11 -> 5223.6056 | CI11: =+CH11*AK11 -> 492.76847 | CJ11: =+CH11-CI11 -> 4730.8371 | CK11: =+CJ11*AK11 -> 446.28319 | CL11: =+CJ11-CK11 -> 4284.5539 | CM11: =+CL11*AK11 -> 404.1831 | CN11: =+CL11-CM11 -> 3880.3708 | CO11: =+CN11*AK11 -> 366.05451 | CP11: =+CN11-CO11 -> 3514.3163 | CQ11: =+CP11*AK11 -> 331.52279 | CR11: =+CP11-CQ11 -> 3182.7935 | CS11: =+CR11*AK11 -> 300.24861 | CT11: =+CR11-CS11 -> 2882.5449 | CU11: =+CT11*AK11 -> 271.92468 | CV11: =+CT11-CU11 -> 2610.6202 | CW11: =+CV11*AK11 -> 246.27268 | CX11: =+CV11-CW11 -> 2364.3475 | CY11: =+CX11*AK11 -> 223.04056 | CZ11: =+CX11-CY11 -> 2141.307 | DA11: =+CZ11*AK11 -> 202.00005 | DB11: =+CZ11-DA11 -> 1939.3069 | DC11: =+DB11-E11*5% -> 69.306938 | DD11: =+DB11-DC11 -> 1870 | DE11: 0 | DF11: =+DD11-DE11 -> 1870 | DG11: 0 | DH11: =+DF11-DG11 -> 1870 | DJ11: =+DH11-DI11 -> 1870 | DL11: =+DJ11-DK11 -> 1870 | DN11: =+DL11-DM11 -> 1870 | DP11: =+DN11-DO11 -> 1870 | DR11: =+DP11-DQ11 -> 1870 | DT11: =+DR11-DS11 -> 1870 | DW11: =+E11*5% -> 1870 | DX11: =+DW11-DR11 -> 0
A12: =A11+1 -> 5 | B12: Factory Building Construction | C12: Building | D12: 0.1 | E12: 50000 | F12: opening | G12: 40052 | P12: =IF(($P$6-G12+1)>365,365,($P$6-G12+1))+1 -> 218 | Q12: =ROUND(E12*P12/365*D12,0) -> 2986 | R12: =E12-Q12 -> 47014 | S12: =IF(($S$6-G12+1)>365,365,($Y$6-G12+1)) -> 365 | T12: =ROUND(R12*13.91%/365*S12,0) -> 6540 | U12: =R12-T12 -> 40474 | V12: =IF(($V$6-G12+1)>365,365,($V$6-G12+1)) -> 365 | W12: =186694/(U59+825639)*U12 -> 2216.4722 | X12: =IF((U12-W12)>0,U12-W12,E12-W12) -> 38257.528 | Y12: =IF(($Y$6-G12+1)>365,365,($Y$6-G12+1)) -> 365 | Z12: =ROUND(IF(X12>0,X12*$D12/365*Y12,($E12*$D12*Y12/365)),0) -> 3826 | AA12: =IF((X12-Z12)>0,X12-Z12,$E12-Z12) -> 34431.528 | AB12: =IF(($AB$6-G12+1)>365,365,($AB$6-G12+1)) -> 365 | AC12: =ROUND(IF(AA12>0,AA12*$D12/365*AB12,($E12*$D12*AB12/365)),0) -> 3443 | AD12: =IF((AA12-AC12)>0,AA12-AC12,$E12-AC12) -> 30988.528 | AE12: =T12+W12+Z12+AC12+Q12+N12 -> 19011.472 | AF12: =E12-AE12 -> 30988.528 | AG12: =AD12-AF12 -> 0 | AH12: =($AH$6-G12+1)/365 -> 4.5972603 | AI12: 30 | AJ12: =AI12-AH12 -> 25.40274 | AK12: =IF(AJ12>0,1-(((E12*$AJ$4)/AF12)^(1/AJ12)),0) -> 0.094344825 | AL12: =IF(AJ12<0,AF12-(E12*5%),0) -> 0 | AM12: =IF(($AM$6-$G12+1)>365,365,($AM$6-$G12+1)) -> 365 | AN12: =ROUND(IF(AF12>0,AF12*$D12/365*AM12,($E12*$D12*AM12/365)),0) -> 3099 | AO12: =MIN(ROUND(IF(AL12>0,0,(AK12*AF12)*AM12/365),0),AF12-(E12*5%)) -> 2924 | AP12: =ROUND(+IF(AJ12<1,(E12*5%),IF(AF12>0,AF12-AO12,E12-AO12)),0) -> 28065 | AQ12: =AF12-AO12-AL12 -> 28064.528 | AR12: =$AF12-($AL12+$AO12+$AP12) -> -0.47220072 | AS12: =AO12-AN12 -> -175 | AT12: =AF12-AN12 -> 27889.528 | AU12: =AT12-AS12-AL12 -> 28064.528 | AV12: =AU12-AQ12 -> 0 | AW12: =IF(($AW$6-$G12+1)>365,365,($AW$6-$G12+1)) -> 365 | AX12: =AU12*AK12 -> 2647.743 | AY12: =AU12-AX12 -> 25416.785 | AZ12: =IF(($AZ$6-$G12+1)>365,365,($AZ$6-$G12+1)) -> 365 | BA12: =AY12*AK12 -> 2397.9421 | BB12: =AY12-BA12 -> 23018.843 | BC12: =60*365 -> 21900 | BD12: =+$BD$6-G12 -> 2773 | BE12: =+BC12-BD12 -> 19127 | BF12: =IF(($BF$6-$G12+1)>365,365,($BF$6-$G12+1)) -> 365 | BG12: =IF(BE12>365,IF(BF12=365,BB12*AK12,BB12*AK12*BF12/365),0) -> 2171.7087 | BH12: =+BB12-BG12 -> 20847.134 | BI12: =+BH12*AK12 -> 1966.8192 | BJ12: =+BH12-BI12 -> 18880.315 | BK12: =+ROUND(BJ12*AK12,2) -> 1781.26 | BL12: =+BJ12-BK12 -> 17099.055 | BN12: =BL12-BM12 -> 17099.055 | BO12: =+BL12*AK12 -> 1613.2073 | BP12: =+BL12-BO12 -> 15485.847 | BR12: =BP12-BQ12 -> 15485.847 | BS12: =+BR12*AK12 -> 1461.0096 | BT12: =+BP12-BS12 -> 14024.838 | BU12: =+BT12*AK12 -> 1323.1709 | BV12: =+BT12-BU12 -> 12701.667 | BW12: =+BV12*AK12 -> 1198.3366 | BX12: =+BV12-BW12 -> 11503.33 | BY12: =+BX12*AK12 -> 1085.2797 | BZ12: =+BX12-BY12 -> 10418.051 | CA12: =+BZ12*AK12 -> 982.88918 | CB12: =+BZ12-CA12 -> 9435.1616 | CC12: =+CB12*AK12 -> 890.15867 | CD12: =+CB12-CC12 -> 8545.0029 | CE12: =+CD12*AK12 -> 806.17681 | CF12: =+CD12-CE12 -> 7738.8261 | CG12: =+CF12*AK12 -> 730.1182 | CH12: =+CF12-CG12 -> 7008.7079 | CI12: =+CH12*AK12 -> 661.23532 | CJ12: =+CH12-CI12 -> 6347.4726 | CK12: =+CJ12*AK12 -> 598.85119 | CL12: =+CJ12-CK12 -> 5748.6214 | CM12: =+CL12*AK12 -> 542.35268 | CN12: =+CL12-CM12 -> 5206.2687 | CO12: =+CN12*AK12 -> 491.18451 | CP12: =+CN12-CO12 -> 4715.0842 | CQ12: =+CP12*AK12 -> 444.8438 | CR12: =+CP12-CQ12 -> 4270.2404 | CS12: =+CR12*AK12 -> 402.87509 | CT12: =+CR12-CS12 -> 3867.3653 | CU12: =+CT12*AK12 -> 364.86591 | CV12: =+CT12-CU12 -> 3502.4994 | CW12: =+CV12*AK12 -> 330.4427 | CX12: =+CV12-CW12 -> 3172.0567 | CY12: =+CX12*AK12 -> 299.26714 | CZ12: =+CX12-CY12 -> 2872.7896 | DA12: =+CZ12*AK12 -> 271.03283 | DB12: =+CZ12-DA12 -> 2601.7568 | DC12: =+DB12-E12*5% -> 101.75676 | DD12: =+DB12-DC12 -> 2500 | DE12: 0 | DF12: =+DD12-DE12 -> 2500 | DG12: 0 | DH12: =+DF12-DG12 -> 2500 | DJ12: =+DH12-DI12 -> 2500 | DL12: =+DJ12-DK12 -> 2500 | DN12: =+DL12-DM12 -> 2500 | DP12: =+DN12-DO12 -> 2500 | DR12: =+DP12-DQ12 -> 2500 | DT12: =+DR12-DS12 -> 2500 | DW12: =+E12*5% -> 2500 | DX12: =+DW12-DR12 -> 0
A13: =A12+1 -> 6 | B13: Factory Building Construction | C13: Building | D13: 0.1 | E13: 40000 | F13: opening | G13: 40080 | P13: =IF(($P$6-G13+1)>365,365,($P$6-G13+1))+3-1 -> 191 | Q13: =ROUND(E13*P13/365*D13,0) -> 2093 | R13: =E13-Q13 -> 37907 | S13: =IF(($S$6-G13+1)>365,365,($Y$6-G13+1)) -> 365 | T13: =ROUND(R13*13.91%/365*S13,0) -> 5273 | U13: =R13-T13 -> 32634 | V13: =IF(($V$6-G13+1)>365,365,($V$6-G13+1)) -> 365 | W13: =186694/(U59+825639)*U13 -> 1787.1313 | X13: =IF((U13-W13)>0,U13-W13,E13-W13) -> 30846.869 | Y13: =IF(($Y$6-G13+1)>365,365,($Y$6-G13+1)) -> 365 | Z13: =ROUND(IF(X13>0,X13*$D13/365*Y13,($E13*$D13*Y13/365)),0) -> 3085 | AA13: =IF((X13-Z13)>0,X13-Z13,$E13-Z13) -> 27761.869 | AB13: =IF(($AB$6-G13+1)>365,365,($AB$6-G13+1)) -> 365 | AC13: =ROUND(IF(AA13>0,AA13*$D13/365*AB13,($E13*$D13*AB13/365)),0) -> 2776 | AD13: =IF((AA13-AC13)>0,AA13-AC13,$E13-AC13) -> 24985.869 | AE13: =T13+W13+Z13+AC13+Q13+N13 -> 15014.131 | AF13: =E13-AE13 -> 24985.869 | AG13: =AD13-AF13 -> 0 | AH13: =($AH$6-G13+1)/365 -> 4.5205479 | AI13: 30 | AJ13: =AI13-AH13 -> 25.479452 | AK13: =IF(AJ13>0,1-(((E13*$AJ$4)/AF13)^(1/AJ13)),0) -> 0.094353177 | AL13: =IF(AJ13<0,AF13-(E13*5%),0) -> 0 | AM13: =IF(($AM$6-$G13+1)>365,365,($AM$6-$G13+1)) -> 365 | AN13: =ROUND(IF(AF13>0,AF13*$D13/365*AM13,($E13*$D13*AM13/365)),0) -> 2499 | AO13: =MIN(ROUND(IF(AL13>0,0,(AK13*AF13)*AM13/365),0),AF13-(E13*5%)) -> 2357 | AP13: =ROUND(+IF(AJ13<1,(E13*5%),IF(AF13>0,AF13-AO13,E13-AO13)),0) -> 22629 | AQ13: =AF13-AO13-AL13 -> 22628.869 | AR13: =$AF13-($AL13+$AO13+$AP13) -> -0.13133859 | AS13: =AO13-AN13 -> -142 | AT13: =AF13-AN13 -> 22486.869 | AU13: =AT13-AS13-AL13 -> 22628.869 | AV13: =AU13-AQ13 -> 0 | AW13: =IF(($AW$6-$G13+1)>365,365,($AW$6-$G13+1)) -> 365 | AX13: =AU13*AK13 -> 2135.1056 | AY13: =AU13-AX13 -> 20493.763 | AZ13: =IF(($AZ$6-$G13+1)>365,365,($AZ$6-$G13+1)) -> 365 | BA13: =AY13*AK13 -> 1933.6516 | BB13: =AY13-BA13 -> 18560.111 | BC13: =60*365 -> 21900 | BD13: =+$BD$6-G13 -> 2745 | BE13: =+BC13-BD13 -> 19155 | BF13: =IF(($BF$6-$G13+1)>365,365,($BF$6-$G13+1)) -> 365 | BG13: =IF(BE13>365,IF(BF13=365,BB13*AK13,BB13*AK13*BF13/365),0) -> 1751.2055 | BH13: =+BB13-BG13 -> 16808.906 | BI13: =+BH13*AK13 -> 1585.9737 | BJ13: =+BH13-BI13 -> 15222.932 | BK13: =+ROUND(BJ13*AK13,2) -> 1436.33 | BL13: =+BJ13-BK13 -> 13786.602 | BN13: =BL13-BM13 -> 13786.602 | BO13: =+BL13*AK13 -> 1300.8097 | BP13: =+BL13-BO13 -> 12485.793 | BR13: =BP13-BQ13 -> 12485.793 | BS13: =+BR13*AK13 -> 1178.0742 | BT13: =+BP13-BS13 -> 11307.718 | BU13: =+BT13*AK13 -> 1066.9191 | BV13: =+BT13-BU13 -> 10240.799 | BW13: =+BV13*AK13 -> 966.25194 | BX13: =+BV13-BW13 -> 9274.5472 | BY13: =+BX13*AK13 -> 875.083 | BZ13: =+BX13-BY13 -> 8399.4643 | CA13: =+BZ13*AK13 -> 792.51614 | CB13: =+BZ13-CA13 -> 7606.9481 | CC13: =+CB13*AK13 -> 717.73972 | CD13: =+CB13-CC13 -> 6889.2084 | CE13: =+CD13*AK13 -> 650.0187 | CF13: =+CD13-CE13 -> 6239.1897 | CG13: =+CF13*AK13 -> 588.68737 | CH13: =+CF13-CG13 -> 5650.5023 | CI13: =+CH13*AK13 -> 533.14285 | CJ13: =+CH13-CI13 -> 5117.3595 | CK13: =+CJ13*AK13 -> 482.83912 | CL13: =+CJ13-CK13 -> 4634.5204 | CM13: =+CL13*AK13 -> 437.28172 | CN13: =+CL13-CM13 -> 4197.2386 | CO13: =+CN13*AK13 -> 396.0228 | CP13: =+CN13-CO13 -> 3801.2158 | CQ13: =+CP13*AK13 -> 358.65679 | CR13: =+CP13-CQ13 -> 3442.5591 | CS13: =+CR13*AK13 -> 324.81638 | CT13: =+CR13-CS13 -> 3117.7427 | CU13: =+CT13*AK13 -> 294.16893 | CV13: =+CT13-CU13 -> 2823.5737 | CW13: =+CV13*AK13 -> 266.41315 | CX13: =+CV13-CW13 -> 2557.1606 | CY13: =+CX13*AK13 -> 241.27623 | CZ13: =+CX13-CY13 -> 2315.8844 | DA13: =+CZ13*AK13 -> 218.51105 | DB13: =+CZ13-DA13 -> 2097.3733 | DC13: =+DB13-E13*5% -> 97.37332 | DD13: =+DB13-DC13 -> 2000 | DE13: 0 | DF13: =+DD13-DE13 -> 2000 | DG13: 0 | DH13: =+DF13-DG13 -> 2000 | DJ13: =+DH13-DI13 -> 2000 | DL13: =+DJ13-DK13 -> 2000 | DN13: =+DL13-DM13 -> 2000 | DP13: =+DN13-DO13 -> 2000 | DR13: =+DP13-DQ13 -> 2000 | DT13: =+DR13-DS13 -> 2000 | DW13: =+E13*5% -> 2000 | DX13: =+DW13-DR13 -> 0
A14: =A13+1 -> 7 | B14: Factory Building Construction | C14: Building | D14: 0.1 | E14: 20000 | F14: opening | G14: 40182 | P14: =IF(($P$6-G14+1)>365,365,($P$6-G14+1))+3+1 -> 91 | Q14: =ROUND(E14*P14/365*D14,0) -> 499 | R14: =E14-Q14 -> 19501 | S14: =IF(($S$6-G14+1)>365,365,($Y$6-G14+1)) -> 365 | T14: =ROUND(R14*13.91%/365*S14,0) -> 2713 | U14: =R14-T14 -> 16788 | V14: =IF(($V$6-G14+1)>365,365,($V$6-G14+1)) -> 365 | W14: =186694/(U59+825639)*U14 -> 919.35898 | X14: =IF((U14-W14)>0,U14-W14,E14-W14) -> 15868.641 | Y14: =IF(($Y$6-G14+1)>365,365,($Y$6-G14+1)) -> 365 | Z14: =ROUND(IF(X14>0,X14*$D14/365*Y14,($E14*$D14*Y14/365)),0) -> 1587 | AA14: =IF((X14-Z14)>0,X14-Z14,$E14-Z14) -> 14281.641 | AB14: =IF(($AB$6-G14+1)>365,365,($AB$6-G14+1)) -> 365 | AC14: =ROUND(IF(AA14>0,AA14*$D14/365*AB14,($E14*$D14*AB14/365)),0) -> 1428 | AD14: =IF((AA14-AC14)>0,AA14-AC14,$E14-AC14) -> 12853.641 | AE14: =T14+W14+Z14+AC14+Q14+N14 -> 7146.359 | AF14: =E14-AE14 -> 12853.641 | AG14: =AD14-AF14 -> 0 | AH14: =($AH$6-G14+1)/365 -> 4.2410959 | AI14: 30 | AJ14: =AI14-AH14 -> 25.758904 | AK14: =IF(AJ14>0,1-(((E14*$AJ$4)/AF14)^(1/AJ14)),0) -> 0.094380197 | AL14: =IF(AJ14<0,AF14-(E14*5%),0) -> 0 | AM14: =IF(($AM$6-$G14+1)>365,365,($AM$6-$G14+1)) -> 365 | AN14: =ROUND(IF(AF14>0,AF14*$D14/365*AM14,($E14*$D14*AM14/365)),0) -> 1285 | AO14: =MIN(ROUND(IF(AL14>0,0,(AK14*AF14)*AM14/365),0),AF14-(E14*5%)) -> 1213 | AP14: =ROUND(+IF(AJ14<1,(E14*5%),IF(AF14>0,AF14-AO14,E14-AO14)),0) -> 11641 | AQ14: =AF14-AO14-AL14 -> 11640.641 | AR14: =$AF14-($AL14+$AO14+$AP14) -> -0.35897874 | AS14: =AO14-AN14 -> -72 | AT14: =AF14-AN14 -> 11568.641 | AU14: =AT14-AS14-AL14 -> 11640.641 | AV14: =AU14-AQ14 -> 0 | AW14: =IF(($AW$6-$G14+1)>365,365,($AW$6-$G14+1)) -> 365 | AX14: =AU14*AK14 -> 1098.646 | AY14: =AU14-AX14 -> 10541.995 | AZ14: =IF(($AZ$6-$G14+1)>365,365,($AZ$6-$G14+1)) -> 365 | BA14: =AY14*AK14 -> 994.95557 | BB14: =AY14-BA14 -> 9547.0395 | BC14: =60*365 -> 21900 | BD14: =+$BD$6-G14 -> 2643 | BE14: =+BC14-BD14 -> 19257 | BF14: =IF(($BF$6-$G14+1)>365,365,($BF$6-$G14+1)) -> 365 | BG14: =IF(BE14>365,IF(BF14=365,BB14*AK14,BB14*AK14*BF14/365),0) -> 901.05147 | BH14: =+BB14-BG14 -> 8645.988 | BI14: =+BH14*AK14 -> 816.01005 | BJ14: =+BH14-BI14 -> 7829.9779 | BK14: =+ROUND(BJ14*AK14,2) -> 738.99 | BL14: =+BJ14-BK14 -> 7090.9879 | BN14: =BL14-BM14 -> 7090.9879 | BO14: =+BL14*AK14 -> 669.24884 | BP14: =+BL14-BO14 -> 6421.7391 | BR14: =BP14-BQ14 -> 6421.7391 | BS14: =+BR14*AK14 -> 606.085 | BT14: =+BP14-BS14 -> 5815.6541 | BU14: =+BT14*AK14 -> 548.88258 | BV14: =+BT14-BU14 -> 5266.7715 | BW14: =+BV14*AK14 -> 497.07893 | BX14: =+BV14-BW14 -> 4769.6926 | BY14: =+BX14*AK14 -> 450.16453 | BZ14: =+BX14-BY14 -> 4319.528 | CA14: =+BZ14*AK14 -> 407.67791 | CB14: =+BZ14-CA14 -> 3911.8501 | CC14: =+CB14*AK14 -> 369.20119 | CD14: =+CB14-CC14 -> 3542.6489 | CE14: =+CD14*AK14 -> 334.35591 | CF14: =+CD14-CE14 -> 3208.293 | CG14: =+CF14*AK14 -> 302.79933 | CH14: =+CF14-CG14 -> 2905.4937 | CI14: =+CH14*AK14 -> 274.22107 | CJ14: =+CH14-CI14 -> 2631.2726 | CK14: =+CJ14*AK14 -> 248.34003 | CL14: =+CJ14-CK14 -> 2382.9326 | CM14: =+CL14*AK14 -> 224.90165 | CN14: =+CL14-CM14 -> 2158.031 | CO14: =+CN14*AK14 -> 203.67539 | CP14: =+CN14-CO14 -> 1954.3556 | CQ14: =+CP14*AK14 -> 184.45246 | CR14: =+CP14-CQ14 -> 1769.9031 | CS14: =+CR14*AK14 -> 167.0438 | CT14: =+CR14-CS14 -> 1602.8593 | CU14: =+CT14*AK14 -> 151.27818 | CV14: =+CT14-CU14 -> 1451.5811 | CW14: =+CV14*AK14 -> 137.00051 | CX14: =+CV14-CW14 -> 1314.5806 | CY14: =+CX14*AK14 -> 124.07038 | CZ14: =+CX14-CY14 -> 1190.5102 | DA14: =+CZ14*AK14 -> 112.36059 | DB14: =+CZ14-DA14 -> 1078.1496 | DC14: =+DB14-E14*5% -> 78.149642 | DD14: =+DB14-DC14 -> 1000 | DE14: 0 | DF14: =+DD14-DE14 -> 1000 | DG14: 0 | DH14: =+DF14-DG14 -> 1000 | DJ14: =+DH14-DI14 -> 1000 | DL14: =+DJ14-DK14 -> 1000 | DN14: =+DL14-DM14 -> 1000 | DP14: =+DN14-DO14 -> 1000 | DR14: =+DP14-DQ14 -> 1000 | DT14: =+DR14-DS14 -> 1000 | DW14: =+E14*5% -> 1000 | DX14: =+DW14-DR14 -> 0
A15: =A14+1 -> 8 | B15: Factory Building Construction | C15: Building | D15: 0.1 | E15: 20000 | F15: opening | G15: 40183 | P15: =IF(($P$6-G15+1)>365,365,($P$6-G15+1))+3+1 -> 90 | Q15: =ROUND(E15*P15/365*D15,0) -> 493 | R15: =E15-Q15 -> 19507 | S15: =IF(($S$6-G15+1)>365,365,($Y$6-G15+1)) -> 365 | T15: =ROUND(R15*13.91%/365*S15,0) -> 2713 | U15: =R15-T15 -> 16794 | V15: =IF(($V$6-G15+1)>365,365,($V$6-G15+1)) -> 365 | W15: =186694/(U59+825639)*U15 -> 919.68756 | X15: =IF((U15-W15)>0,U15-W15,E15-W15) -> 15874.312 | Y15: =IF(($Y$6-G15+1)>365,365,($Y$6-G15+1)) -> 365 | Z15: =ROUND(IF(X15>0,X15*$D15/365*Y15,($E15*$D15*Y15/365)),0) -> 1587 | AA15: =IF((X15-Z15)>0,X15-Z15,$E15-Z15) -> 14287.312 | AB15: =IF(($AB$6-G15+1)>365,365,($AB$6-G15+1)) -> 365 | AC15: =ROUND(IF(AA15>0,AA15*$D15/365*AB15,($E15*$D15*AB15/365)),0) -> 1429 | AD15: =IF((AA15-AC15)>0,AA15-AC15,$E15-AC15) -> 12858.312 | AE15: =T15+W15+Z15+AC15+Q15+N15 -> 7141.6876 | AF15: =E15-AE15 -> 12858.312 | AG15: =AD15-AF15 -> 0 | AH15: =($AH$6-G15+1)/365 -> 4.2383562 | AI15: 30 | AJ15: =AI15-AH15 -> 25.761644 | AK15: =IF(AJ15>0,1-(((E15*$AJ$4)/AF15)^(1/AJ15)),0) -> 0.094383423 | AL15: =IF(AJ15<0,AF15-(E15*5%),0) -> 0 | AM15: =IF(($AM$6-$G15+1)>365,365,($AM$6-$G15+1)) -> 365 | AN15: =ROUND(IF(AF15>0,AF15*$D15/365*AM15,($E15*$D15*AM15/365)),0) -> 1286 | AO15: =MIN(ROUND(IF(AL15>0,0,(AK15*AF15)*AM15/365),0),AF15-(E15*5%)) -> 1214 | AP15: =ROUND(+IF(AJ15<1,(E15*5%),IF(AF15>0,AF15-AO15,E15-AO15)),0) -> 11644 | AQ15: =AF15-AO15-AL15 -> 11644.312 | AR15: =$AF15-($AL15+$AO15+$AP15) -> 0.31244407 | AS15: =AO15-AN15 -> -72 | AT15: =AF15-AN15 -> 11572.312 | AU15: =AT15-AS15-AL15 -> 11644.312 | AV15: =AU15-AQ15 -> 0 | AW15: =IF(($AW$6-$G15+1)>365,365,($AW$6-$G15+1)) -> 365 | AX15: =AU15*AK15 -> 1099.0301 | AY15: =AU15-AX15 -> 10545.282 | AZ15: =IF(($AZ$6-$G15+1)>365,365,($AZ$6-$G15+1)) -> 365 | BA15: =AY15*AK15 -> 995.29985 | BB15: =AY15-BA15 -> 9549.9825 | BC15: =60*365 -> 21900 | BD15: =+$BD$6-G15 -> 2642 | BE15: =+BC15-BD15 -> 19258 | BF15: =IF(($BF$6-$G15+1)>365,365,($BF$6-$G15+1)) -> 365 | BG15: =IF(BE15>365,IF(BF15=365,BB15*AK15,BB15*AK15*BF15/365),0) -> 901.36004 | BH15: =+BB15-BG15 -> 8648.6225 | BI15: =+BH15*AK15 -> 816.2866 | BJ15: =+BH15-BI15 -> 7832.3359 | BK15: =+ROUND(BJ15*AK15,2) -> 739.24 | BL15: =+BJ15-BK15 -> 7093.0959 | BN15: =BL15-BM15 -> 7093.0959 | BO15: =+BL15*AK15 -> 669.47067 | BP15: =+BL15-BO15 -> 6423.6252 | BR15: =BP15-BQ15 -> 6423.6252 | BS15: =+BR15*AK15 -> 606.28374 | BT15: =+BP15-BS15 -> 5817.3415 | BU15: =+BT15*AK15 -> 549.0606 | BV15: =+BT15-BU15 -> 5268.2809 | BW15: =+BV15*AK15 -> 497.23838 | BX15: =+BV15-BW15 -> 4771.0425 | BY15: =+BX15*AK15 -> 450.30732 | BZ15: =+BX15-BY15 -> 4320.7352 | CA15: =+BZ15*AK15 -> 407.80578 | CB15: =+BZ15-CA15 -> 3912.9294 | CC15: =+CB15*AK15 -> 369.31567 | CD15: =+CB15-CC15 -> 3543.6137 | CE15: =+CD15*AK15 -> 334.45839 | CF15: =+CD15-CE15 -> 3209.1553 | CG15: =+CF15*AK15 -> 302.89107 | CH15: =+CF15-CG15 -> 2906.2643 | CI15: =+CH15*AK15 -> 274.30317 | CJ15: =+CH15-CI15 -> 2631.9611 | CK15: =+CJ15*AK15 -> 248.4135 | CL15: =+CJ15-CK15 -> 2383.5476 | CM15: =+CL15*AK15 -> 224.96738 | CN15: =+CL15-CM15 -> 2158.5802 | CO15: =+CN15*AK15 -> 203.73419 | CP15: =+CN15-CO15 -> 1954.846 | CQ15: =+CP15*AK15 -> 184.50506 | CR15: =+CP15-CQ15 -> 1770.341 | CS15: =+CR15*AK15 -> 167.09084 | CT15: =+CR15-CS15 -> 1603.2501 | CU15: =+CT15*AK15 -> 151.32023 | CV15: =+CT15-CU15 -> 1451.9299 | CW15: =+CV15*AK15 -> 137.03811 | CX15: =+CV15-CW15 -> 1314.8918 | CY15: =+CX15*AK15 -> 124.10399 | CZ15: =+CX15-CY15 -> 1190.7878 | DA15: =+CZ15*AK15 -> 112.39063 | DB15: =+CZ15-DA15 -> 1078.3972 | DC15: =+DB15-E15*5% -> 78.397161 | DD15: =+DB15-DC15 -> 1000 | DE15: 0 | DF15: =+DD15-DE15 -> 1000 | DG15: 0 | DH15: =+DF15-DG15 -> 1000 | DJ15: =+DH15-DI15 -> 1000 | DL15: =+DJ15-DK15 -> 1000 | DN15: =+DL15-DM15 -> 1000 | DP15: =+DN15-DO15 -> 1000 | DR15: =+DP15-DQ15 -> 1000 | DT15: =+DR15-DS15 -> 1000 | DW15: =+E15*5% -> 1000 | DX15: =+DW15-DR15 -> 0
A16: =A15+1 -> 9 | B16: Factory Building Construction | C16: Building | D16: 0.1 | E16: 30000 | F16: opening | G16: 40231 | P16: =IF(($P$6-G16+1)>365,365,($P$6-G16+1))+3+2 -> 43 | Q16: =ROUND(E16*P16/365*D16,0) -> 353 | R16: =E16-Q16 -> 29647 | S16: =IF(($S$6-G16+1)>365,365,($Y$6-G16+1)) -> 365 | T16: =ROUND(R16*13.91%/365*S16,0) -> 4124 | U16: =R16-T16 -> 25523 | V16: =IF(($V$6-G16+1)>365,365,($V$6-G16+1)) -> 365 | W16: =186694/(U59+825639)*U16 -> 1397.7126 | X16: =IF((U16-W16)>0,U16-W16,E16-W16) -> 24125.287 | Y16: =IF(($Y$6-G16+1)>365,365,($Y$6-G16+1)) -> 365 | Z16: =ROUND(IF(X16>0,X16*$D16/365*Y16,($E16*$D16*Y16/365)),0) -> 2413 | AA16: =IF((X16-Z16)>0,X16-Z16,$E16-Z16) -> 21712.287 | AB16: =IF(($AB$6-G16+1)>365,365,($AB$6-G16+1)) -> 365 | AC16: =ROUND(IF(AA16>0,AA16*$D16/365*AB16,($E16*$D16*AB16/365)),0) -> 2171 | AD16: =IF((AA16-AC16)>0,AA16-AC16,$E16-AC16) -> 19541.287 | AE16: =T16+W16+Z16+AC16+Q16+N16 -> 10458.713 | AF16: =E16-AE16 -> 19541.287 | AG16: =AD16-AF16 -> 0 | AH16: =($AH$6-G16+1)/365 -> 4.1068493 | AI16: 30 | AJ16: =AI16-AH16 -> 25.893151 | AK16: =IF(AJ16>0,1-(((E16*$AJ$4)/AF16)^(1/AJ16)),0) -> 0.094384698 | AL16: =IF(AJ16<0,AF16-(E16*5%),0) -> 0 | AM16: =IF(($AM$6-$G16+1)>365,365,($AM$6-$G16+1)) -> 365 | AN16: =ROUND(IF(AF16>0,AF16*$D16/365*AM16,($E16*$D16*AM16/365)),0) -> 1954 | AO16: =MIN(ROUND(IF(AL16>0,0,(AK16*AF16)*AM16/365),0),AF16-(E16*5%)) -> 1844 | AP16: =ROUND(+IF(AJ16<1,(E16*5%),IF(AF16>0,AF16-AO16,E16-AO16)),0) -> 17697 | AQ16: =AF16-AO16-AL16 -> 17697.287 | AR16: =$AF16-($AL16+$AO16+$AP16) -> 0.2873949 | AS16: =AO16-AN16 -> -110 | AT16: =AF16-AN16 -> 17587.287 | AU16: =AT16-AS16-AL16 -> 17697.287 | AV16: =AU16-AQ16 -> 0 | AW16: =IF(($AW$6-$G16+1)>365,365,($AW$6-$G16+1)) -> 365 | AX16: =AU16*AK16 -> 1670.3531 | AY16: =AU16-AX16 -> 16026.934 | AZ16: =IF(($AZ$6-$G16+1)>365,365,($AZ$6-$G16+1)) -> 365 | BA16: =AY16*AK16 -> 1512.6973 | BB16: =AY16-BA16 -> 14514.237 | BC16: =60*365 -> 21900 | BD16: =+$BD$6-G16 -> 2594 | BE16: =+BC16-BD16 -> 19306 | BF16: =IF(($BF$6-$G16+1)>365,365,($BF$6-$G16+1)) -> 365 | BG16: =IF(BE16>365,IF(BF16=365,BB16*AK16,BB16*AK16*BF16/365),0) -> 1369.9219 | BH16: =+BB16-BG16 -> 13144.315 | BI16: =+BH16*AK16 -> 1240.6222 | BJ16: =+BH16-BI16 -> 11903.693 | BK16: =+ROUND(BJ16*AK16,2) -> 1123.53 | BL16: =+BJ16-BK16 -> 10780.163 | BN16: =BL16-BM16 -> 10780.163 | BO16: =+BL16*AK16 -> 1017.4824 | BP16: =+BL16-BO16 -> 9762.6804 | BR16: =BP16-BQ16 -> 9762.6804 | BS16: =+BR16*AK16 -> 921.44764 | BT16: =+BP16-BS16 -> 8841.2328 | BU16: =+BT16*AK16 -> 834.47709 | BV16: =+BT16-BU16 -> 8006.7557 | BW16: =+BV16*AK16 -> 755.71522 | BX16: =+BV16-BW16 -> 7251.0405 | BY16: =+BX16*AK16 -> 684.38727 | BZ16: =+BX16-BY16 -> 6566.6532 | CA16: =+BZ16*AK16 -> 619.79158 | CB16: =+BZ16-CA16 -> 5946.8616 | CC16: =+CB16*AK16 -> 561.29274 | CD16: =+CB16-CC16 -> 5385.5689 | CE16: =+CD16*AK16 -> 508.31529 | CF16: =+CD16-CE16 -> 4877.2536 | CG16: =+CF16*AK16 -> 460.33811 | CH16: =+CF16-CG16 -> 4416.9155 | CI16: =+CH16*AK16 -> 416.88924 | CJ16: =+CH16-CI16 -> 4000.0263 | CK16: =+CJ16*AK16 -> 377.54127 | CL16: =+CJ16-CK16 -> 3622.485 | CM16: =+CL16*AK16 -> 341.90715 | CN16: =+CL16-CM16 -> 3280.5778 | CO16: =+CN16*AK16 -> 309.63635 | CP16: =+CN16-CO16 -> 2970.9415 | CQ16: =+CP16*AK16 -> 280.41142 | CR16: =+CP16-CQ16 -> 2690.5301 | CS16: =+CR16*AK16 -> 253.94487 | CT16: =+CR16-CS16 -> 2436.5852 | CU16: =+CT16*AK16 -> 229.97636 | CV16: =+CT16-CU16 -> 2206.6089 | CW16: =+CV16*AK16 -> 208.27011 | CX16: =+CV16-CW16 -> 1998.3387 | CY16: =+CX16*AK16 -> 188.6126 | CZ16: =+CX16-CY16 -> 1809.7261 | DA16: =+CZ16*AK16 -> 170.81046 | DB16: =+CZ16-DA16 -> 1638.9157 | DC16: =+DB16-E16*5% -> 138.91569 | DD16: =+DB16-DC16 -> 1500 | DE16: 0 | DF16: =+DD16-DE16 -> 1500 | DG16: 0 | DH16: =+DF16-DG16 -> 1500 | DJ16: =+DH16-DI16 -> 1500 | DL16: =+DJ16-DK16 -> 1500 | DN16: =+DL16-DM16 -> 1500 | DP16: =+DN16-DO16 -> 1500 | DR16: =+DP16-DQ16 -> 1500 | DT16: =+DR16-DS16 -> 1500 | DW16: =+E16*5% -> 1500 | DX16: =+DW16-DR16 -> 0
A17: =A16+1 -> 10 | B17: Factory Building Construction | C17: Building | D17: 0.1 | E17: 150000 | F17: opening | G17: 40254 | P17: =IF(($P$6-G17+1)>365,365,($P$6-G17+1))+3 -> 18 | Q17: =ROUND(E17*P17/365*D17,0) -> 740 | R17: =E17-Q17 -> 149260 | S17: =IF(($S$6-G17+1)>365,365,($Y$6-G17+1)) -> 365 | T17: =ROUND(R17*13.91%/365*S17,0) -> 20762 | U17: =R17-T17 -> 128498 | V17: =IF(($V$6-G17+1)>365,365,($V$6-G17+1)) -> 365 | W17: =186694/(U59+825639)*U17 -> 7036.9186 | X17: =IF((U17-W17)>0,U17-W17,E17-W17) -> 121461.08 | Y17: =IF(($Y$6-G17+1)>365,365,($Y$6-G17+1)) -> 365 | Z17: =ROUND(IF(X17>0,X17*$D17/365*Y17,($E17*$D17*Y17/365)),0) -> 12146 | AA17: =IF((X17-Z17)>0,X17-Z17,$E17-Z17) -> 109315.08 | AB17: =IF(($AB$6-G17+1)>365,365,($AB$6-G17+1)) -> 365 | AC17: =ROUND(IF(AA17>0,AA17*$D17/365*AB17,($E17*$D17*AB17/365)),0) -> 10932 | AD17: =IF((AA17-AC17)>0,AA17-AC17,$E17-AC17) -> 98383.081 | AE17: =T17+W17+Z17+AC17+Q17+N17 -> 51616.919 | AF17: =E17-AE17 -> 98383.081 | AG17: =AD17-AF17 -> 0 | AH17: =($AH$6-G17+1)/365 -> 4.0438356 | AI17: 30 | AJ17: =AI17-AH17 -> 25.956164 | AK17: =IF(AJ17>0,1-(((E17*$AJ$4)/AF17)^(1/AJ17)),0) -> 0.094407522 | AL17: =IF(AJ17<0,AF17-(E17*5%),0) -> 0 | AM17: =IF(($AM$6-$G17+1)>365,365,($AM$6-$G17+1)) -> 365 | AN17: =ROUND(IF(AF17>0,AF17*$D17/365*AM17,($E17*$D17*AM17/365)),0) -> 9838 | AO17: =MIN(ROUND(IF(AL17>0,0,(AK17*AF17)*AM17/365),0),AF17-(E17*5%)) -> 9288 | AP17: =ROUND(+IF(AJ17<1,(E17*5%),IF(AF17>0,AF17-AO17,E17-AO17)),0) -> 89095 | AQ17: =AF17-AO17-AL17 -> 89095.081 | AR17: =$AF17-($AL17+$AO17+$AP17) -> 0.081364628 | AS17: =AO17-AN17 -> -550 | AT17: =AF17-AN17 -> 88545.081 | AU17: =AT17-AS17-AL17 -> 89095.081 | AV17: =AU17-AQ17 -> 0 | AW17: =IF(($AW$6-$G17+1)>365,365,($AW$6-$G17+1)) -> 365 | AX17: =AU17*AK17 -> 8411.2459 | AY17: =AU17-AX17 -> 80683.835 | AZ17: =IF(($AZ$6-$G17+1)>365,365,($AZ$6-$G17+1)) -> 365 | BA17: =AY17*AK17 -> 7617.161 | BB17: =AY17-BA17 -> 73066.674 | BC17: =60*365 -> 21900 | BD17: =+$BD$6-G17 -> 2571 | BE17: =+BC17-BD17 -> 19329 | BF17: =IF(($BF$6-$G17+1)>365,365,($BF$6-$G17+1)) -> 365 | BG17: =IF(BE17>365,IF(BF17=365,BB17*AK17,BB17*AK17*BF17/365),0) -> 6898.0437 | BH17: =+BB17-BG17 -> 66168.631 | BI17: =+BH17*AK17 -> 6246.8165 | BJ17: =+BH17-BI17 -> 59921.814 | BK17: =+ROUND(BJ17*AK17,2) -> 5657.07 | BL17: =+BJ17-BK17 -> 54264.744 | BN17: =BL17-BM17 -> 54264.744 | BO17: =+BL17*AK17 -> 5123.0001 | BP17: =+BL17-BO17 -> 49141.744 | BR17: =BP17-BQ17 -> 49141.744 | BS17: =+BR17*AK17 -> 4639.3503 | BT17: =+BP17-BS17 -> 44502.394 | BU17: =+BT17*AK17 -> 4201.3607 | BV17: =+BT17-BU17 -> 40301.033 | BW17: =+BV17*AK17 -> 3804.7207 | BX17: =+BV17-BW17 -> 36496.312 | BY17: =+BX17*AK17 -> 3445.5264 | BZ17: =+BX17-BY17 -> 33050.786 | CA17: =+BZ17*AK17 -> 3120.2428 | CB17: =+BZ17-CA17 -> 29930.543 | CC17: =+CB17*AK17 -> 2825.6684 | CD17: =+CB17-CC17 -> 27104.875 | CE17: =+CD17*AK17 -> 2558.9041 | CF17: =+CD17-CE17 -> 24545.971 | CG17: =+CF17*AK17 -> 2317.3243 | CH17: =+CF17-CG17 -> 22228.646 | CI17: =+CH17*AK17 -> 2098.5514 | CJ17: =+CH17-CI17 -> 20130.095 | CK17: =+CJ17*AK17 -> 1900.4324 | CL17: =+CJ17-CK17 -> 18229.663 | CM17: =+CL17*AK17 -> 1721.0173 | CN17: =+CL17-CM17 -> 16508.645 | CO17: =+CN17*AK17 -> 1558.5403 | CP17: =+CN17-CO17 -> 14950.105 | CQ17: =+CP17*AK17 -> 1411.4024 | CR17: =+CP17-CQ17 -> 13538.703 | CS17: =+CR17*AK17 -> 1278.1554 | CT17: =+CR17-CS17 -> 12260.547 | CU17: =+CT17*AK17 -> 1157.4879 | CV17: =+CT17-CU17 -> 11103.059 | CW17: =+CV17*AK17 -> 1048.2123 | CX17: =+CV17-CW17 -> 10054.847 | CY17: =+CX17*AK17 -> 949.2532 | CZ17: =+CX17-CY17 -> 9105.5939 | DA17: =+CZ17*AK17 -> 859.63656 | DB17: =+CZ17-DA17 -> 8245.9573 | DC17: =+DB17-E17*5% -> 745.95731 | DD17: =+DB17-DC17 -> 7500 | DE17: 0 | DF17: =+DD17-DE17 -> 7500 | DG17: 0 | DH17: =+DF17-DG17 -> 7500 | DJ17: =+DH17-DI17 -> 7500 | DL17: =+DJ17-DK17 -> 7500 | DN17: =+DL17-DM17 -> 7500 | DP17: =+DN17-DO17 -> 7500 | DR17: =+DP17-DQ17 -> 7500 | DT17: =+DR17-DS17 -> 7500 | DW17: =+E17*5% -> 7500 | DX17: =+DW17-DR17 -> 0
A18: =A17+1 -> 11 | B18: Factory Building Construction | C18: Building | D18: 0.1 | E18: 150000 | F18: opening | G18: 40255 | P18: =IF(($P$6-G18+1)>365,365,($P$6-G18+1))+3 -> 17 | Q18: =ROUND(E18*P18/365*D18,0) -> 699 | R18: =E18-Q18 -> 149301 | S18: =IF(($S$6-G18+1)>365,365,($Y$6-G18+1)) -> 365 | T18: =ROUND(R18*13.91%/365*S18,0) -> 20768 | U18: =R18-T18 -> 128533 | V18: =IF(($V$6-G18+1)>365,365,($V$6-G18+1)) -> 365 | W18: =186694/(U59+825639)*U18 -> 7038.8353 | X18: =IF((U18-W18)>0,U18-W18,E18-W18) -> 121494.16 | Y18: =IF(($Y$6-G18+1)>365,365,($Y$6-G18+1)) -> 365 | Z18: =ROUND(IF(X18>0,X18*$D18/365*Y18,($E18*$D18*Y18/365)),0) -> 12149 | AA18: =IF((X18-Z18)>0,X18-Z18,$E18-Z18) -> 109345.16 | AB18: =IF(($AB$6-G18+1)>365,365,($AB$6-G18+1)) -> 365 | AC18: =ROUND(IF(AA18>0,AA18*$D18/365*AB18,($E18*$D18*AB18/365)),0) -> 10935 | AD18: =IF((AA18-AC18)>0,AA18-AC18,$E18-AC18) -> 98410.165 | AE18: =T18+W18+Z18+AC18+Q18+N18 -> 51589.835 | AF18: =E18-AE18 -> 98410.165 | AG18: =AD18-AF18 -> 0 | AH18: =($AH$6-G18+1)/365 -> 4.0410959 | AI18: 30 | AJ18: =AI18-AH18 -> 25.958904 | AK18: =IF(AJ18>0,1-(((E18*$AJ$4)/AF18)^(1/AJ18)),0) -> 0.094407646 | AL18: =IF(AJ18<0,AF18-(E18*5%),0) -> 0 | AM18: =IF(($AM$6-$G18+1)>365,365,($AM$6-$G18+1)) -> 365 | AN18: =ROUND(IF(AF18>0,AF18*$D18/365*AM18,($E18*$D18*AM18/365)),0) -> 9841 | AO18: =MIN(ROUND(IF(AL18>0,0,(AK18*AF18)*AM18/365),0),AF18-(E18*5%)) -> 9291 | AP18: =ROUND(+IF(AJ18<1,(E18*5%),IF(AF18>0,AF18-AO18,E18-AO18)),0) -> 89119 | AQ18: =AF18-AO18-AL18 -> 89119.165 | AR18: =$AF18-($AL18+$AO18+$AP18) -> 0.16466435 | AS18: =AO18-AN18 -> -550 | AT18: =AF18-AN18 -> 88569.165 | AU18: =AT18-AS18-AL18 -> 89119.165 | AV18: =AU18-AQ18 -> 0 | AW18: =IF(($AW$6-$G18+1)>365,365,($AW$6-$G18+1)) -> 365 | AX18: =AU18*AK18 -> 8413.5306 | AY18: =AU18-AX18 -> 80705.634 | AZ18: =IF(($AZ$6-$G18+1)>365,365,($AZ$6-$G18+1)) -> 365 | BA18: =AY18*AK18 -> 7619.229 | BB18: =AY18-BA18 -> 73086.405 | BC18: =60*365 -> 21900 | BD18: =+$BD$6-G18 -> 2570 | BE18: =+BC18-BD18 -> 19330 | BF18: =IF(($BF$6-$G18+1)>365,365,($BF$6-$G18+1)) -> 365 | BG18: =IF(BE18>365,IF(BF18=365,BB18*AK18,BB18*AK18*BF18/365),0) -> 6899.9155 | BH18: =+BB18-BG18 -> 66186.49 | BI18: =+BH18*AK18 -> 6248.5107 | BJ18: =+BH18-BI18 -> 59937.979 | BK18: =+ROUND(BJ18*AK18,2) -> 5658.6 | BL18: =+BJ18-BK18 -> 54279.379 | BN18: =BL18-BM18 -> 54279.379 | BO18: =+BL18*AK18 -> 5124.3884 | BP18: =+BL18-BO18 -> 49154.99 | BR18: =BP18-BQ18 -> 49154.99 | BS18: =+BR18*AK18 -> 4640.607 | BT18: =+BP18-BS18 -> 44514.384 | BU18: =+BT18*AK18 -> 4202.4982 | BV18: =+BT18-BU18 -> 40311.885 | BW18: =+BV18*AK18 -> 3805.7502 | BX18: =+BV18-BW18 -> 36506.135 | BY18: =+BX18*AK18 -> 3446.4583 | BZ18: =+BX18-BY18 -> 33059.677 | CA18: =+BZ18*AK18 -> 3121.0863 | CB18: =+BZ18-CA18 -> 29938.591 | CC18: =+CB18*AK18 -> 2826.4319 | CD18: =+CB18-CC18 -> 27112.159 | CE18: =+CD18*AK18 -> 2559.5951 | CF18: =+CD18-CE18 -> 24552.564 | CG18: =+CF18*AK18 -> 2317.9497 | CH18: =+CF18-CG18 -> 22234.614 | CI18: =+CH18*AK18 -> 2099.1176 | CJ18: =+CH18-CI18 -> 20135.496 | CK18: =+CJ18*AK18 -> 1900.9448 | CL18: =+CJ18-CK18 -> 18234.551 | CM18: =+CL18*AK18 -> 1721.4811 | CN18: =+CL18-CM18 -> 16513.07 | CO18: =+CN18*AK18 -> 1558.9601 | CP18: =+CN18-CO18 -> 14954.11 | CQ18: =+CP18*AK18 -> 1411.7824 | CR18: =+CP18-CQ18 -> 13542.328 | CS18: =+CR18*AK18 -> 1278.4993 | CT18: =+CR18-CS18 -> 12263.829 | CU18: =+CT18*AK18 -> 1157.7992 | CV18: =+CT18-CU18 -> 11106.029 | CW18: =+CV18*AK18 -> 1048.4941 | CX18: =+CV18-CW18 -> 10057.535 | CY18: =+CX18*AK18 -> 949.50824 | CZ18: =+CX18-CY18 -> 9108.0271 | DA18: =+CZ18*AK18 -> 859.8674 | DB18: =+CZ18-DA18 -> 8248.1597 | DC18: =+DB18-E18*5% -> 748.15967 | DD18: =+DB18-DC18 -> 7500 | DE18: 0 | DF18: =+DD18-DE18 -> 7500 | DG18: 0 | DH18: =+DF18-DG18 -> 7500 | DJ18: =+DH18-DI18 -> 7500 | DL18: =+DJ18-DK18 -> 7500 | DN18: =+DL18-DM18 -> 7500 | DP18: =+DN18-DO18 -> 7500 | DR18: =+DP18-DQ18 -> 7500 | DT18: =+DR18-DS18 -> 7500 | DW18: =+E18*5% -> 7500 | DX18: =+DW18-DR18 -> 0
A19: =A18+1 -> 12 | B19: Factory Building Construction | C19: Building | D19: 0.1 | E19: 4450 | F19: opening | G19: 40770 | S19: 0 | T19: 0 | U19: =E19-T19 -> 4450 | V19: =IF(($V$6-G19+1)>365,365,($V$6-G19+1)) -> 230 | W19: =186694/(U59+825639)*U19 -> 243.69475 | X19: =IF((U19-W19)>0,U19-W19,E19-W19) -> 4206.3053 | Y19: =IF(($Y$6-G19+1)>365,365,($Y$6-G19+1)) -> 365 | Z19: =ROUND(IF(X19>0,X19*$D19/365*Y19,($E19*$D19*Y19/365)),0) -> 421 | AA19: =IF((X19-Z19)>0,X19-Z19,$E19-Z19) -> 3785.3053 | AB19: =IF(($AB$6-G19+1)>365,365,($AB$6-G19+1)) -> 365 | AC19: =ROUND(IF(AA19>0,AA19*$D19/365*AB19,($E19*$D19*AB19/365)),0) -> 379 | AD19: =IF((AA19-AC19)>0,AA19-AC19,$E19-AC19) -> 3406.3053 | AE19: =T19+W19+Z19+AC19+Q19+N19 -> 1043.6947 | AF19: =E19-AE19 -> 3406.3053 | AG19: =AD19-AF19 -> 0 | AH19: =($AH$6-G19+1)/365 -> 2.630137 | AI19: 30 | AJ19: =AI19-AH19 -> 27.369863 | AK19: =IF(AJ19>0,1-(((E19*$AJ$4)/AF19)^(1/AJ19)),0) -> 0.094880542 | AL19: =IF(AJ19<0,AF19-(E19*5%),0) -> 0 | AM19: =IF(($AM$6-$G19+1)>365,365,($AM$6-$G19+1)) -> 365 | AN19: =ROUND(IF(AF19>0,AF19*$D19/365*AM19,($E19*$D19*AM19/365)),0) -> 341 | AO19: =MIN(ROUND(IF(AL19>0,0,(AK19*AF19)*AM19/365),0),AF19-(E19*5%)) -> 323 | AP19: =ROUND(+IF(AJ19<1,(E19*5%),IF(AF19>0,AF19-AO19,E19-AO19)),0) -> 3083 | AQ19: =AF19-AO19-AL19 -> 3083.3053 | AR19: =$AF19-($AL19+$AO19+$AP19) -> 0.30525045 | AS19: =AO19-AN19 -> -18 | AT19: =AF19-AN19 -> 3065.3053 | AU19: =AT19-AS19-AL19 -> 3083.3053 | AV19: =AU19-AQ19 -> 0 | AW19: =IF(($AW$6-$G19+1)>365,365,($AW$6-$G19+1)) -> 365 | AX19: =AU19*AK19 -> 292.54567 | AY19: =AU19-AX19 -> 2790.7596 | AZ19: =IF(($AZ$6-$G19+1)>365,365,($AZ$6-$G19+1)) -> 365 | BA19: =AY19*AK19 -> 264.78878 | BB19: =AY19-BA19 -> 2525.9708 | BC19: =60*365 -> 21900 | BD19: =+$BD$6-G19 -> 2055 | BE19: =+BC19-BD19 -> 19845 | BF19: =IF(($BF$6-$G19+1)>365,365,($BF$6-$G19+1)) -> 365 | BG19: =IF(BE19>365,IF(BF19=365,BB19*AK19,BB19*AK19*BF19/365),0) -> 239.66548 | BH19: =+BB19-BG19 -> 2286.3053 | BI19: =+BH19*AK19 -> 216.92589 | BJ19: =+BH19-BI19 -> 2069.3794 | BK19: =+ROUND(BJ19*AK19,2) -> 196.34 | BL19: =+BJ19-BK19 -> 1873.0394 | BN19: =BL19-BM19 -> 1873.0394 | BO19: =+BL19*AK19 -> 177.715 | BP19: =+BL19-BO19 -> 1695.3244 | BR19: =BP19-BQ19 -> 1695.3244 | BS19: =+BR19*AK19 -> 160.8533 | BT19: =+BP19-BS19 -> 1534.4711 | BU19: =+BT19*AK19 -> 145.59145 | BV19: =+BT19-BU19 -> 1388.8797 | BW19: =+BV19*AK19 -> 131.77766 | BX19: =+BV19-BW19 -> 1257.102 | BY19: =+BX19*AK19 -> 119.27452 | BZ19: =+BX19-BY19 -> 1137.8275 | CA19: =+BZ19*AK19 -> 107.95769 | CB19: =+BZ19-CA19 -> 1029.8698 | CC19: =+CB19*AK19 -> 97.714606 | CD19: =+CB19-CC19 -> 932.15521 | CE19: =+CD19*AK19 -> 88.443391 | CF19: =+CD19-CE19 -> 843.71182 | CG19: =+CF19*AK19 -> 80.051834 | CH19: =+CF19-CG19 -> 763.65998 | CI19: =+CH19*AK19 -> 72.456473 | CJ19: =+CH19-CI19 -> 691.20351 | CK19: =+CJ19*AK19 -> 65.581763 | CL19: =+CJ19-CK19 -> 625.62174 | CM19: =+CL19*AK19 -> 59.35933 | CN19: =+CL19-CM19 -> 566.26241 | CO19: =+CN19*AK19 -> 53.727285 | CP19: =+CN19-CO19 -> 512.53513 | CQ19: =+CP19*AK19 -> 48.629611 | CR19: =+CP19-CQ19 -> 463.90552 | CS19: =+CR19*AK19 -> 44.015607 | CT19: =+CR19-CS19 -> 419.88991 | CU19: =+CT19*AK19 -> 39.839382 | CV19: =+CT19-CU19 -> 380.05053 | CW19: =+CV19*AK19 -> 36.0594 | CX19: =+CV19-CW19 -> 343.99113 | CY19: =+CX19*AK19 -> 32.638065 | CZ19: =+CX19-CY19 -> 311.35306 | DA19: =+CZ19*AK19 -> 29.541348 | DB19: =+CZ19-DA19 -> 281.81172 | DC19: =+DB19*AK19 -> 26.738448 | DD19: =+DB19-DC19 -> 255.07327 | DE19: =+DD19*AK19 -> 24.20149 | DF19: =+DD19-DE19 -> 230.87178 | DG19: =+DF19-E19*5% -> 8.3717788 | DH19: =+DF19-DG19 -> 222.5 | DJ19: =+DH19-DI19 -> 222.5 | DL19: =+DJ19-DK19 -> 222.5 | DN19: =+DL19-DM19 -> 222.5 | DP19: =+DN19-DO19 -> 222.5 | DR19: =+DP19-DQ19 -> 222.5 | DT19: =+DR19-DS19 -> 222.5 | DW19: =+E19*5% -> 222.5 | DX19: =+DW19-DR19 -> 0
A20: =A19+1 -> 13 | B20: Factory Building Construction | C20: Building | D20: 0.1 | E20: 10567 | F20: opening | G20: 40770 | S20: 0 | T20: 0 | U20: =E20-T20 -> 10567 | V20: =IF(($V$6-G20+1)>365,365,($V$6-G20+1)) -> 230 | W20: =186694/(U59+825639)*U20 -> 578.6792 | X20: =IF((U20-W20)>0,U20-W20,E20-W20) -> 9988.3208 | Y20: =IF(($Y$6-G20+1)>365,365,($Y$6-G20+1)) -> 365 | Z20: =ROUND(IF(X20>0,X20*$D20/365*Y20,($E20*$D20*Y20/365)),0) -> 999 | AA20: =IF((X20-Z20)>0,X20-Z20,$E20-Z20) -> 8989.3208 | AB20: =IF(($AB$6-G20+1)>365,365,($AB$6-G20+1)) -> 365 | AC20: =ROUND(IF(AA20>0,AA20*$D20/365*AB20,($E20*$D20*AB20/365)),0) -> 899 | AD20: =IF((AA20-AC20)>0,AA20-AC20,$E20-AC20) -> 8090.3208 | AE20: =T20+W20+Z20+AC20+Q20+N20 -> 2476.6792 | AF20: =E20-AE20 -> 8090.3208 | AG20: =AD20-AF20 -> 0 | AH20: =($AH$6-G20+1)/365 -> 2.630137 | AI20: 30 | AJ20: =AI20-AH20 -> 27.369863 | AK20: =IF(AJ20>0,1-(((E20*$AJ$4)/AF20)^(1/AJ20)),0) -> 0.094887432 | AL20: =IF(AJ20<0,AF20-(E20*5%),0) -> 0 | AM20: =IF(($AM$6-$G20+1)>365,365,($AM$6-$G20+1)) -> 365 | AN20: =ROUND(IF(AF20>0,AF20*$D20/365*AM20,($E20*$D20*AM20/365)),0) -> 809 | AO20: =MIN(ROUND(IF(AL20>0,0,(AK20*AF20)*AM20/365),0),AF20-(E20*5%)) -> 768 | AP20: =ROUND(+IF(AJ20<1,(E20*5%),IF(AF20>0,AF20-AO20,E20-AO20)),0) -> 7322 | AQ20: =AF20-AO20-AL20 -> 7322.3208 | AR20: =$AF20-($AL20+$AO20+$AP20) -> 0.32080484 | AS20: =AO20-AN20 -> -41 | AT20: =AF20-AN20 -> 7281.3208 | AU20: =AT20-AS20-AL20 -> 7322.3208 | AV20: =AU20-AQ20 -> 0 | AW20: =IF(($AW$6-$G20+1)>365,365,($AW$6-$G20+1)) -> 365 | AX20: =AU20*AK20 -> 694.79622 | AY20: =AU20-AX20 -> 6627.5246 | AZ20: =IF(($AZ$6-$G20+1)>365,365,($AZ$6-$G20+1)) -> 365 | BA20: =AY20*AK20 -> 628.86879 | BB20: =AY20-BA20 -> 5998.6558 | BC20: =60*365 -> 21900 | BD20: =+$BD$6-G20 -> 2055 | BE20: =+BC20-BD20 -> 19845 | BF20: =IF(($BF$6-$G20+1)>365,365,($BF$6-$G20+1)) -> 365 | BG20: =IF(BE20>365,IF(BF20=365,BB20*AK20,BB20*AK20*BF20/365),0) -> 569.19704 | BH20: =+BB20-BG20 -> 5429.4588 | BI20: =+BH20*AK20 -> 515.1874 | BJ20: =+BH20-BI20 -> 4914.2714 | BK20: =+ROUND(BJ20*AK20,2) -> 466.3 | BL20: =+BJ20-BK20 -> 4447.9714 | BN20: =BL20-BM20 -> 4447.9714 | BO20: =+BL20*AK20 -> 422.05658 | BP20: =+BL20-BO20 -> 4025.9148 | BR20: =BP20-BQ20 -> 4025.9148 | BS20: =+BR20*AK20 -> 382.00871 | BT20: =+BP20-BS20 -> 3643.9061 | BU20: =+BT20*AK20 -> 345.76089 | BV20: =+BT20-BU20 -> 3298.1452 | BW20: =+BV20*AK20 -> 312.95253 | BX20: =+BV20-BW20 -> 2985.1927 | BY20: =+BX20*AK20 -> 283.25726 | BZ20: =+BX20-BY20 -> 2701.9354 | CA20: =+BZ20*AK20 -> 256.37971 | CB20: =+BZ20-CA20 -> 2445.5557 | CC20: =+CB20*AK20 -> 232.0525 | CD20: =+CB20-CC20 -> 2213.5032 | CE20: =+CD20*AK20 -> 210.03363 | CF20: =+CD20-CE20 -> 2003.4695 | CG20: =+CF20*AK20 -> 190.10408 | CH20: =+CF20-CG20 -> 1813.3655 | CI20: =+CH20*AK20 -> 172.06559 | CJ20: =+CH20-CI20 -> 1641.2999 | CK20: =+CJ20*AK20 -> 155.73873 | CL20: =+CJ20-CK20 -> 1485.5611 | CM20: =+CL20*AK20 -> 140.96108 | CN20: =+CL20-CM20 -> 1344.6001 | CO20: =+CN20*AK20 -> 127.58565 | CP20: =+CN20-CO20 -> 1217.0144 | CQ20: =+CP20*AK20 -> 115.47937 | CR20: =+CP20-CQ20 -> 1101.535 | CS20: =+CR20*AK20 -> 104.52183 | CT20: =+CR20-CS20 -> 997.01321 | CU20: =+CT20*AK20 -> 94.604023 | CV20: =+CT20-CU20 -> 902.40919 | CW20: =+CV20*AK20 -> 85.62729 | CX20: =+CV20-CW20 -> 816.7819 | CY20: =+CX20*AK20 -> 77.502337 | CZ20: =+CX20-CY20 -> 739.27956 | DA20: =+CZ20*AK20 -> 70.148339 | DB20: =+CZ20-DA20 -> 669.13122 | DC20: =+DB20*AK20 -> 63.492143 | DD20: =+DB20-DC20 -> 605.63908 | DE20: =+DD20*AK20 -> 57.467537 | DF20: =+DD20-DE20 -> 548.17154 | DG20: =+DF20-E20*5% -> 19.821543 | DH20: =+DF20-DG20 -> 528.35 | DJ20: =+DH20-DI20 -> 528.35 | DL20: =+DJ20-DK20 -> 528.35 | DN20: =+DL20-DM20 -> 528.35 | DP20: =+DN20-DO20 -> 528.35 | DR20: =+DP20-DQ20 -> 528.35 | DT20: =+DR20-DS20 -> 528.35 | DW20: =+E20*5% -> 528.35 | DX20: =+DW20-DR20 -> 0
A21: =A20+1 -> 14 | B21: Factory Building Construction | C21: Building | D21: 0.1 | E21: 100000 | F21: opening | G21: 40770 | S21: 0 | T21: 0 | U21: =E21-T21 -> 100000 | V21: =IF(($V$6-G21+1)>365,365,($V$6-G21+1)) -> 230 | W21: =186694/(U59+825639)*U21 -> 5476.2865 | X21: =IF((U21-W21)>0,U21-W21,E21-W21) -> 94523.713 | Y21: =IF(($Y$6-G21+1)>365,365,($Y$6-G21+1)) -> 365 | Z21: =ROUND(IF(X21>0,X21*$D21/365*Y21,($E21*$D21*Y21/365)),0) -> 9452 | AA21: =IF((X21-Z21)>0,X21-Z21,$E21-Z21) -> 85071.713 | AB21: =IF(($AB$6-G21+1)>365,365,($AB$6-G21+1)) -> 365 | AC21: =ROUND(IF(AA21>0,AA21*$D21/365*AB21,($E21*$D21*AB21/365)),0) -> 8507 | AD21: =IF((AA21-AC21)>0,AA21-AC21,$E21-AC21) -> 76564.713 | AE21: =T21+W21+Z21+AC21+Q21+N21 -> 23435.287 | AF21: =E21-AE21 -> 76564.713 | AG21: =AD21-AF21 -> 0 | AH21: =($AH$6-G21+1)/365 -> 2.630137 | AI21: 30 | AJ21: =AI21-AH21 -> 27.369863 | AK21: =IF(AJ21>0,1-(((E21*$AJ$4)/AF21)^(1/AJ21)),0) -> 0.094888546 | AL21: =IF(AJ21<0,AF21-(E21*5%),0) -> 0 | AM21: =IF(($AM$6-$G21+1)>365,365,($AM$6-$G21+1)) -> 365 | AN21: =ROUND(IF(AF21>0,AF21*$D21/365*AM21,($E21*$D21*AM21/365)),0) -> 7656 | AO21: =MIN(ROUND(IF(AL21>0,0,(AK21*AF21)*AM21/365),0),AF21-(E21*5%)) -> 7265 | AP21: =ROUND(+IF(AJ21<1,(E21*5%),IF(AF21>0,AF21-AO21,E21-AO21)),0) -> 69300 | AQ21: =AF21-AO21-AL21 -> 69299.713 | AR21: =$AF21-($AL21+$AO21+$AP21) -> -0.28650669 | AS21: =AO21-AN21 -> -391 | AT21: =AF21-AN21 -> 68908.713 | AU21: =AT21-AS21-AL21 -> 69299.713 | AV21: =AU21-AQ21 -> 0 | AW21: =IF(($AW$6-$G21+1)>365,365,($AW$6-$G21+1)) -> 365 | AX21: =AU21*AK21 -> 6575.749 | AY21: =AU21-AX21 -> 62723.964 | AZ21: =IF(($AZ$6-$G21+1)>365,365,($AZ$6-$G21+1)) -> 365 | BA21: =AY21*AK21 -> 5951.7858 | BB21: =AY21-BA21 -> 56772.179 | BC21: =60*365 -> 21900 | BD21: =+$BD$6-G21 -> 2055 | BE21: =+BC21-BD21 -> 19845 | BF21: =IF(($BF$6-$G21+1)>365,365,($BF$6-$G21+1)) -> 365 | BG21: =IF(BE21>365,IF(BF21=365,BB21*AK21,BB21*AK21*BF21/365),0) -> 5387.0295 | BH21: =+BB21-BG21 -> 51385.149 | BI21: =+BH21*AK21 -> 4875.8621 | BJ21: =+BH21-BI21 -> 46509.287 | BK21: =+ROUND(BJ21*AK21,2) -> 4413.2 | BL21: =+BJ21-BK21 -> 42096.087 | BN21: =BL21-BM21 -> 42096.087 | BO21: =+BL21*AK21 -> 3994.4365 | BP21: =+BL21-BO21 -> 38101.651 | BR21: =BP21-BQ21 -> 38101.651 | BS21: =+BR21*AK21 -> 3615.4102 | BT21: =+BP21-BS21 -> 34486.24 | BU21: =+BT21*AK21 -> 3272.3492 | BV21: =+BT21-BU21 -> 31213.891 | BW21: =+BV21*AK21 -> 2961.8407 | BX21: =+BV21-BW21 -> 28252.051 | BY21: =+BX21*AK21 -> 2680.796 | BZ21: =+BX21-BY21 -> 25571.255 | CA21: =+BZ21*AK21 -> 2426.4192 | CB21: =+BZ21-CA21 -> 23144.835 | CC21: =+CB21*AK21 -> 2196.1798 | CD21: =+CB21-CC21 -> 20948.656 | CE21: =+CD21*AK21 -> 1987.7875 | CF21: =+CD21-CE21 -> 18960.868 | CG21: =+CF21*AK21 -> 1799.1692 | CH21: =+CF21-CG21 -> 17161.699 | CI21: =+CH21*AK21 -> 1628.4487 | CJ21: =+CH21-CI21 -> 15533.25 | CK21: =+CJ21*AK21 -> 1473.9275 | CL21: =+CJ21-CK21 -> 14059.323 | CM21: =+CL21*AK21 -> 1334.0687 | CN21: =+CL21-CM21 -> 12725.254 | CO21: =+CN21*AK21 -> 1207.4809 | CP21: =+CN21-CO21 -> 11517.773 | CQ21: =+CP21*AK21 -> 1092.9048 | CR21: =+CP21-CQ21 -> 10424.868 | CS21: =+CR21*AK21 -> 989.20061 | CT21: =+CR21-CS21 -> 9435.6679 | CU21: =+CT21*AK21 -> 895.3368 | CV21: =+CT21-CU21 -> 8540.3311 | CW21: =+CV21*AK21 -> 810.37959 | CX21: =+CV21-CW21 -> 7729.9515 | CY21: =+CX21*AK21 -> 733.48385 | CZ21: =+CX21-CY21 -> 6996.4676 | DA21: =+CZ21*AK21 -> 663.88464 | DB21: =+CZ21-DA21 -> 6332.583 | DC21: =+DB21*AK21 -> 600.88959 | DD21: =+DB21-DC21 -> 5731.6934 | DE21: =+DD21*AK21 -> 543.87205 | DF21: =+DD21-DE21 -> 5187.8214 | DG21: =+DF21-E21*5% -> 187.82135 | DH21: =+DF21-DG21 -> 5000 | DJ21: =+DH21-DI21 -> 5000 | DL21: =+DJ21-DK21 -> 5000 | DN21: =+DL21-DM21 -> 5000 | DP21: =+DN21-DO21 -> 5000 | DR21: =+DP21-DQ21 -> 5000 | DT21: =+DR21-DS21 -> 5000 | DW21: =+E21*5% -> 5000 | DX21: =+DW21-DR21 -> 0
A22: =A21+1 -> 15 | B22: Factory Building Construction | C22: Building | D22: 0.1 | E22: 32889 | F22: opening | G22: 40770 | S22: 0 | T22: 0 | U22: =E22-T22 -> 32889 | V22: =IF(($V$6-G22+1)>365,365,($V$6-G22+1)) -> 230 | W22: =186694/(U59+825639)*U22 -> 1801.0959 | X22: =IF((U22-W22)>0,U22-W22,E22-W22) -> 31087.904 | Y22: =IF(($Y$6-G22+1)>365,365,($Y$6-G22+1)) -> 365 | Z22: =ROUND(IF(X22>0,X22*$D22/365*Y22,($E22*$D22*Y22/365)),0) -> 3109 | AA22: =IF((X22-Z22)>0,X22-Z22,$E22-Z22) -> 27978.904 | AB22: =IF(($AB$6-G22+1)>365,365,($AB$6-G22+1)) -> 365 | AC22: =ROUND(IF(AA22>0,AA22*$D22/365*AB22,($E22*$D22*AB22/365)),0) -> 2798 | AD22: =IF((AA22-AC22)>0,AA22-AC22,$E22-AC22) -> 25180.904 | AE22: =T22+W22+Z22+AC22+Q22+N22 -> 7708.0959 | AF22: =E22-AE22 -> 25180.904 | AG22: =AD22-AF22 -> 0 | AH22: =($AH$6-G22+1)/365 -> 2.630137 | AI22: 30 | AJ22: =AI22-AH22 -> 27.369863 | AK22: =IF(AJ22>0,1-(((E22*$AJ$4)/AF22)^(1/AJ22)),0) -> 0.094887936 | AL22: =IF(AJ22<0,AF22-(E22*5%),0) -> 0 | AM22: =IF(($AM$6-$G22+1)>365,365,($AM$6-$G22+1)) -> 365 | AN22: =ROUND(IF(AF22>0,AF22*$D22/365*AM22,($E22*$D22*AM22/365)),0) -> 2518 | AO22: =MIN(ROUND(IF(AL22>0,0,(AK22*AF22)*AM22/365),0),AF22-(E22*5%)) -> 2389 | AP22: =ROUND(+IF(AJ22<1,(E22*5%),IF(AF22>0,AF22-AO22,E22-AO22)),0) -> 22792 | AQ22: =AF22-AO22-AL22 -> 22791.904 | AR22: =$AF22-($AL22+$AO22+$AP22) -> -0.095869187 | AS22: =AO22-AN22 -> -129 | AT22: =AF22-AN22 -> 22662.904 | AU22: =AT22-AS22-AL22 -> 22791.904 | AV22: =AU22-AQ22 -> 0 | AW22: =IF(($AW$6-$G22+1)>365,365,($AW$6-$G22+1)) -> 365 | AX22: =AU22*AK22 -> 2162.6767 | AY22: =AU22-AX22 -> 20629.227 | AZ22: =IF(($AZ$6-$G22+1)>365,365,($AZ$6-$G22+1)) -> 365 | BA22: =AY22*AK22 -> 1957.4648 | BB22: =AY22-BA22 -> 18671.763 | BC22: =60*365 -> 21900 | BD22: =+$BD$6-G22 -> 2055 | BE22: =+BC22-BD22 -> 19845 | BF22: =IF(($BF$6-$G22+1)>365,365,($BF$6-$G22+1)) -> 365 | BG22: =IF(BE22>365,IF(BF22=365,BB22*AK22,BB22*AK22*BF22/365),0) -> 1771.725 | BH22: =+BB22-BG22 -> 16900.038 | BI22: =+BH22*AK22 -> 1603.6097 | BJ22: =+BH22-BI22 -> 15296.428 | BK22: =+ROUND(BJ22*AK22,2) -> 1451.45 | BL22: =+BJ22-BK22 -> 13844.978 | BN22: =BL22-BM22 -> 13844.978 | BO22: =+BL22*AK22 -> 1313.7214 | BP22: =+BL22-BO22 -> 12531.257 | BR22: =BP22-BQ22 -> 12531.257 | BS22: =+BR22*AK22 -> 1189.0651 | BT22: =+BP22-BS22 -> 11342.191 | BU22: =+BT22*AK22 -> 1076.2371 | BV22: =+BT22-BU22 -> 10265.954 | BW22: =+BV22*AK22 -> 974.11521 | BX22: =+BV22-BW22 -> 9291.8391 | BY22: =+BX22*AK22 -> 881.68343 | BZ22: =+BX22-BY22 -> 8410.1557 | CA22: =+BZ22*AK22 -> 798.02231 | CB22: =+BZ22-CA22 -> 7612.1334 | CC22: =+CB22*AK22 -> 722.29962 | CD22: =+CB22-CC22 -> 6889.8338 | CE22: =+CD22*AK22 -> 653.7621 | CF22: =+CD22-CE22 -> 6236.0717 | CG22: =+CF22*AK22 -> 591.72797 | CH22: =+CF22-CG22 -> 5644.3437 | CI22: =+CH22*AK22 -> 535.58012 | CJ22: =+CH22-CI22 -> 5108.7636 | CK22: =+CJ22*AK22 -> 484.76003 | CL22: =+CJ22-CK22 -> 4624.0035 | CM22: =+CL22*AK22 -> 438.76215 | CN22: =+CL22-CM22 -> 4185.2414 | CO22: =+CN22*AK22 -> 397.12892 | CP22: =+CN22-CO22 -> 3788.1125 | CQ22: =+CP22*AK22 -> 359.44617 | CR22: =+CP22-CQ22 -> 3428.6663 | CS22: =+CR22*AK22 -> 325.33907 | CT22: =+CR22-CS22 -> 3103.3272 | CU22: =+CT22*AK22 -> 294.46832 | CV22: =+CT22-CU22 -> 2808.8589 | CW22: =+CV22*AK22 -> 266.52682 | CX22: =+CV22-CW22 -> 2542.3321 | CY22: =+CX22*AK22 -> 241.23664 | CZ22: =+CX22-CY22 -> 2301.0955 | DA22: =+CZ22*AK22 -> 218.3462 | DB22: =+CZ22-DA22 -> 2082.7493 | DC22: =+DB22*AK22 -> 197.62778 | DD22: =+DB22-DC22 -> 1885.1215 | DE22: =+DD22*AK22 -> 178.87529 | DF22: =+DD22-DE22 -> 1706.2462 | DG22: =+DF22-E22*5% -> 61.796197 | DH22: =+DF22-DG22 -> 1644.45 | DJ22: =+DH22-DI22 -> 1644.45 | DL22: =+DJ22-DK22 -> 1644.45 | DN22: =+DL22-DM22 -> 1644.45 | DP22: =+DN22-DO22 -> 1644.45 | DR22: =+DP22-DQ22 -> 1644.45 | DT22: =+DR22-DS22 -> 1644.45 | DW22: =+E22*5% -> 1644.45 | DX22: =+DW22-DR22 -> 0
A23: =A22+1 -> 16 | B23: Factory Building Construction | C23: Building | D23: 0.1 | E23: 28000 | F23: opening | G23: 40770 | S23: 0 | T23: 0 | U23: =E23-T23 -> 28000 | V23: =IF(($V$6-G23+1)>365,365,($V$6-G23+1)) -> 230 | W23: =186694/(U59+825639)*U23 -> 1533.3602 | X23: =IF((U23-W23)>0,U23-W23,E23-W23) -> 26466.64 | Y23: =IF(($Y$6-G23+1)>365,365,($Y$6-G23+1)) -> 365 | Z23: =ROUND(IF(X23>0,X23*$D23/365*Y23,($E23*$D23*Y23/365)),0) -> 2647 | AA23: =IF((X23-Z23)>0,X23-Z23,$E23-Z23) -> 23819.64 | AB23: =IF(($AB$6-G23+1)>365,365,($AB$6-G23+1)) -> 365 | AC23: =ROUND(IF(AA23>0,AA23*$D23/365*AB23,($E23*$D23*AB23/365)),0) -> 2382 | AD23: =IF((AA23-AC23)>0,AA23-AC23,$E23-AC23) -> 21437.64 | AE23: =T23+W23+Z23+AC23+Q23+N23 -> 6562.3602 | AF23: =E23-AE23 -> 21437.64 | AG23: =AD23-AF23 -> 0 | AH23: =($AH$6-G23+1)/365 -> 2.630137 | AI23: 30 | AJ23: =AI23-AH23 -> 27.369863 | AK23: =IF(AJ23>0,1-(((E23*$AJ$4)/AF23)^(1/AJ23)),0) -> 0.094887805 | AL23: =IF(AJ23<0,AF23-(E23*5%),0) -> 0 | AM23: =IF(($AM$6-$G23+1)>365,365,($AM$6-$G23+1)) -> 365 | AN23: =ROUND(IF(AF23>0,AF23*$D23/365*AM23,($E23*$D23*AM23/365)),0) -> 2144 | AO23: =MIN(ROUND(IF(AL23>0,0,(AK23*AF23)*AM23/365),0),AF23-(E23*5%)) -> 2034 | AP23: =ROUND(+IF(AJ23<1,(E23*5%),IF(AF23>0,AF23-AO23,E23-AO23)),0) -> 19404 | AQ23: =AF23-AO23-AL23 -> 19403.64 | AR23: =$AF23-($AL23+$AO23+$AP23) -> -0.36022187 | AS23: =AO23-AN23 -> -110 | AT23: =AF23-AN23 -> 19293.64 | AU23: =AT23-AS23-AL23 -> 19403.64 | AV23: =AU23-AQ23 -> 0 | AW23: =IF(($AW$6-$G23+1)>365,365,($AW$6-$G23+1)) -> 365 | AX23: =AU23*AK23 -> 1841.1688 | AY23: =AU23-AX23 -> 17562.471 | AZ23: =IF(($AZ$6-$G23+1)>365,365,($AZ$6-$G23+1)) -> 365 | BA23: =AY23*AK23 -> 1666.4643 | BB23: =AY23-BA23 -> 15896.007 | BC23: =60*365 -> 21900 | BD23: =+$BD$6-G23 -> 2055 | BE23: =+BC23-BD23 -> 19845 | BF23: =IF(($BF$6-$G23+1)>365,365,($BF$6-$G23+1)) -> 365 | BG23: =IF(BE23>365,IF(BF23=365,BB23*AK23,BB23*AK23*BF23/365),0) -> 1508.3372 | BH23: =+BB23-BG23 -> 14387.669 | BI23: =+BH23*AK23 -> 1365.2144 | BJ23: =+BH23-BI23 -> 13022.455 | BK23: =+ROUND(BJ23*AK23,2) -> 1235.67 | BL23: =+BJ23-BK23 -> 11786.785 | BN23: =BL23-BM23 -> 11786.785 | BO23: =+BL23*AK23 -> 1118.4222 | BP23: =+BL23-BO23 -> 10668.363 | BR23: =BP23-BQ23 -> 10668.363 | BS23: =+BR23*AK23 -> 1012.2975 | BT23: =+BP23-BS23 -> 9656.0654 | BU23: =+BT23*AK23 -> 916.24285 | BV23: =+BT23-BU23 -> 8739.8225 | BW23: =+BV23*AK23 -> 829.30258 | BX23: =+BV23-BW23 -> 7910.52 | BY23: =+BX23*AK23 -> 750.61188 | BZ23: =+BX23-BY23 -> 7159.9081 | CA23: =+BZ23*AK23 -> 679.38796 | CB23: =+BZ23-CA23 -> 6480.5201 | CC23: =+CB23*AK23 -> 614.92233 | CD23: =+CB23-CC23 -> 5865.5978 | CE23: =+CD23*AK23 -> 556.5737 | CF23: =+CD23-CE23 -> 5309.0241 | CG23: =+CF23*AK23 -> 503.76164 | CH23: =+CF23-CG23 -> 4805.2625 | CI23: =+CH23*AK23 -> 455.96081 | CJ23: =+CH23-CI23 -> 4349.3016 | CK23: =+CJ23*AK23 -> 412.69569 | CL23: =+CJ23-CK23 -> 3936.606 | CM23: =+CL23*AK23 -> 373.5359 | CN23: =+CL23-CM23 -> 3563.0701 | CO23: =+CN23*AK23 -> 338.0919 | CP23: =+CN23-CO23 -> 3224.9782 | CQ23: =+CP23*AK23 -> 306.0111 | CR23: =+CP23-CQ23 -> 2918.9671 | CS23: =+CR23*AK23 -> 276.97438 | CT23: =+CR23-CS23 -> 2641.9927 | CU23: =+CT23*AK23 -> 250.69289 | CV23: =+CT23-CU23 -> 2391.2998 | CW23: =+CV23*AK23 -> 226.90519 | CX23: =+CV23-CW23 -> 2164.3946 | CY23: =+CX23*AK23 -> 205.37465 | CZ23: =+CX23-CY23 -> 1959.02 | DA23: =+CZ23*AK23 -> 185.8871 | DB23: =+CZ23-DA23 -> 1773.1329 | DC23: =+DB23*AK23 -> 168.24868 | DD23: =+DB23-DC23 -> 1604.8842 | DE23: =+DD23*AK23 -> 152.28394 | DF23: =+DD23-DE23 -> 1452.6002 | DG23: =+DF23-E23*5% -> 52.600231 | DH23: =+DF23-DG23 -> 1400 | DJ23: =+DH23-DI23 -> 1400 | DL23: =+DJ23-DK23 -> 1400 | DN23: =+DL23-DM23 -> 1400 | DP23: =+DN23-DO23 -> 1400 | DR23: =+DP23-DQ23 -> 1400 | DT23: =+DR23-DS23 -> 1400 | DW23: =+E23*5% -> 1400 | DX23: =+DW23-DR23 -> 0
A24: =A23+1 -> 17 | B24: Factory Building Construction | C24: Building | D24: 0.1 | E24: 39800 | F24: opening | G24: 40770 | S24: 0 | T24: 0 | U24: =E24-T24 -> 39800 | V24: =IF(($V$6-G24+1)>365,365,($V$6-G24+1)) -> 230 | W24: =186694/(U59+825639)*U24 -> 2179.562 | X24: =IF((U24-W24)>0,U24-W24,E24-W24) -> 37620.438 | Y24: =IF(($Y$6-G24+1)>365,365,($Y$6-G24+1)) -> 365 | Z24: =ROUND(IF(X24>0,X24*$D24/365*Y24,($E24*$D24*Y24/365)),0) -> 3762 | AA24: =IF((X24-Z24)>0,X24-Z24,$E24-Z24) -> 33858.438 | AB24: =IF(($AB$6-G24+1)>365,365,($AB$6-G24+1)) -> 365 | AC24: =ROUND(IF(AA24>0,AA24*$D24/365*AB24,($E24*$D24*AB24/365)),0) -> 3386 | AD24: =IF((AA24-AC24)>0,AA24-AC24,$E24-AC24) -> 30472.438 | AE24: =T24+W24+Z24+AC24+Q24+N24 -> 9327.562 | AF24: =E24-AE24 -> 30472.438 | AG24: =AD24-AF24 -> 0 | AH24: =($AH$6-G24+1)/365 -> 2.630137 | AI24: 30 | AJ24: =AI24-AH24 -> 27.369863 | AK24: =IF(AJ24>0,1-(((E24*$AJ$4)/AF24)^(1/AJ24)),0) -> 0.0948882 | AL24: =IF(AJ24<0,AF24-(E24*5%),0) -> 0 | AM24: =IF(($AM$6-$G24+1)>365,365,($AM$6-$G24+1)) -> 365 | AN24: =ROUND(IF(AF24>0,AF24*$D24/365*AM24,($E24*$D24*AM24/365)),0) -> 3047 | AO24: =MIN(ROUND(IF(AL24>0,0,(AK24*AF24)*AM24/365),0),AF24-(E24*5%)) -> 2891 | AP24: =ROUND(+IF(AJ24<1,(E24*5%),IF(AF24>0,AF24-AO24,E24-AO24)),0) -> 27581 | AQ24: =AF24-AO24-AL24 -> 27581.438 | AR24: =$AF24-($AL24+$AO24+$AP24) -> 0.43797034 | AS24: =AO24-AN24 -> -156 | AT24: =AF24-AN24 -> 27425.438 | AU24: =AT24-AS24-AL24 -> 27581.438 | AV24: =AU24-AQ24 -> 0 | AW24: =IF(($AW$6-$G24+1)>365,365,($AW$6-$G24+1)) -> 365 | AX24: =AU24*AK24 -> 2617.153 | AY24: =AU24-AX24 -> 24964.285 | AZ24: =IF(($AZ$6-$G24+1)>365,365,($AZ$6-$G24+1)) -> 365 | BA24: =AY24*AK24 -> 2368.8161 | BB24: =AY24-BA24 -> 22595.469 | BC24: =60*365 -> 21900 | BD24: =+$BD$6-G24 -> 2055 | BE24: =+BC24-BD24 -> 19845 | BF24: =IF(($BF$6-$G24+1)>365,365,($BF$6-$G24+1)) -> 365 | BG24: =IF(BE24>365,IF(BF24=365,BB24*AK24,BB24*AK24*BF24/365),0) -> 2144.0434 | BH24: =+BB24-BG24 -> 20451.426 | BI24: =+BH24*AK24 -> 1940.599 | BJ24: =+BH24-BI24 -> 18510.827 | BK24: =+ROUND(BJ24*AK24,2) -> 1756.46 | BL24: =+BJ24-BK24 -> 16754.367 | BN24: =BL24-BM24 -> 16754.367 | BO24: =+BL24*AK24 -> 1589.7917 | BP24: =+BL24-BO24 -> 15164.575 | BR24: =BP24-BQ24 -> 15164.575 | BS24: =+BR24*AK24 -> 1438.9392 | BT24: =+BP24-BS24 -> 13725.636 | BU24: =+BT24*AK24 -> 1302.4009 | BV24: =+BT24-BU24 -> 12423.235 | BW24: =+BV24*AK24 -> 1178.8184 | BX24: =+BV24-BW24 -> 11244.416 | BY24: =+BX24*AK24 -> 1066.9624 | BZ24: =+BX24-BY24 -> 10177.454 | CA24: =+BZ24*AK24 -> 965.72029 | CB24: =+BZ24-CA24 -> 9211.7337 | CC24: =+CB24*AK24 -> 874.08483 | CD24: =+CB24-CC24 -> 8337.6488 | CE24: =+CD24*AK24 -> 791.14449 | CF24: =+CD24-CE24 -> 7546.5043 | CG24: =+CF24*AK24 -> 716.07422 | CH24: =+CF24-CG24 -> 6830.4301 | CI24: =+CH24*AK24 -> 648.12722 | CJ24: =+CH24-CI24 -> 6182.3029 | CK24: =+CJ24*AK24 -> 586.6276 | CL24: =+CJ24-CK24 -> 5595.6753 | CM24: =+CL24*AK24 -> 530.96356 | CN24: =+CL24-CM24 -> 5064.7117 | CO24: =+CN24*AK24 -> 480.58138 | CP24: =+CN24-CO24 -> 4584.1304 | CQ24: =+CP24*AK24 -> 434.97988 | CR24: =+CP24-CQ24 -> 4149.1505 | CS24: =+CR24*AK24 -> 393.70542 | CT24: =+CR24-CS24 -> 3755.4451 | CU24: =+CT24*AK24 -> 356.34742 | CV24: =+CT24-CU24 -> 3399.0976 | CW24: =+CV24*AK24 -> 322.53426 | CX24: =+CV24-CW24 -> 3076.5634 | CY24: =+CX24*AK24 -> 291.92956 | CZ24: =+CX24-CY24 -> 2784.6338 | DA24: =+CZ24*AK24 -> 264.22889 | DB24: =+CZ24-DA24 -> 2520.4049 | DC24: =+DB24*AK24 -> 239.15669 | DD24: =+DB24-DC24 -> 2281.2482 | DE24: =+DD24*AK24 -> 216.46354 | DF24: =+DD24-DE24 -> 2064.7847 | DG24: =+DF24-E24*5% -> 74.784694 | DH24: =+DF24-DG24 -> 1990 | DJ24: =+DH24-DI24 -> 1990 | DL24: =+DJ24-DK24 -> 1990 | DN24: =+DL24-DM24 -> 1990 | DP24: =+DN24-DO24 -> 1990 | DR24: =+DP24-DQ24 -> 1990 | DT24: =+DR24-DS24 -> 1990 | DW24: =+E24*5% -> 1990 | DX24: =+DW24-DR24 -> 0
A25: =A24+1 -> 18 | B25: Factory Building Construction | C25: Building | D25: 0.1 | E25: 5650 | F25: opening | G25: 40770 | S25: 0 | T25: 0 | U25: =E25-T25 -> 5650 | V25: =IF(($V$6-G25+1)>365,365,($V$6-G25+1)) -> 230 | W25: =186694/(U59+825639)*U25 -> 309.41019 | X25: =IF((U25-W25)>0,U25-W25,E25-W25) -> 5340.5898 | Y25: =IF(($Y$6-G25+1)>365,365,($Y$6-G25+1)) -> 365 | Z25: =ROUND(IF(X25>0,X25*$D25/365*Y25,($E25*$D25*Y25/365)),0) -> 534 | AA25: =IF((X25-Z25)>0,X25-Z25,$E25-Z25) -> 4806.5898 | AB25: =IF(($AB$6-G25+1)>365,365,($AB$6-G25+1)) -> 365 | AC25: =ROUND(IF(AA25>0,AA25*$D25/365*AB25,($E25*$D25*AB25/365)),0) -> 481 | AD25: =IF((AA25-AC25)>0,AA25-AC25,$E25-AC25) -> 4325.5898 | AE25: =T25+W25+Z25+AC25+Q25+N25 -> 1324.4102 | AF25: =E25-AE25 -> 4325.5898 | AG25: =AD25-AF25 -> 0 | AH25: =($AH$6-G25+1)/365 -> 2.630137 | AI25: 30 | AJ25: =AI25-AH25 -> 27.369863 | AK25: =IF(AJ25>0,1-(((E25*$AJ$4)/AF25)^(1/AJ25)),0) -> 0.094886126 | AL25: =IF(AJ25<0,AF25-(E25*5%),0) -> 0 | AM25: =IF(($AM$6-$G25+1)>365,365,($AM$6-$G25+1)) -> 365 | AN25: =ROUND(IF(AF25>0,AF25*$D25/365*AM25,($E25*$D25*AM25/365)),0) -> 433 | AO25: =MIN(ROUND(IF(AL25>0,0,(AK25*AF25)*AM25/365),0),AF25-(E25*5%)) -> 410 | AP25: =ROUND(+IF(AJ25<1,(E25*5%),IF(AF25>0,AF25-AO25,E25-AO25)),0) -> 3916 | AQ25: =AF25-AO25-AL25 -> 3915.5898 | AR25: =$AF25-($AL25+$AO25+$AP25) -> -0.41018763 | AS25: =AO25-AN25 -> -23 | AT25: =AF25-AN25 -> 3892.5898 | AU25: =AT25-AS25-AL25 -> 3915.5898 | AV25: =AU25-AQ25 -> 0 | AW25: =IF(($AW$6-$G25+1)>365,365,($AW$6-$G25+1)) -> 365 | AX25: =AU25*AK25 -> 371.53515 | AY25: =AU25-AX25 -> 3544.0547 | AZ25: =IF(($AZ$6-$G25+1)>365,365,($AZ$6-$G25+1)) -> 365 | BA25: =AY25*AK25 -> 336.28162 | BB25: =AY25-BA25 -> 3207.773 | BC25: =60*365 -> 21900 | BD25: =+$BD$6-G25 -> 2055 | BE25: =+BC25-BD25 -> 19845 | BF25: =IF(($BF$6-$G25+1)>365,365,($BF$6-$G25+1)) -> 365 | BG25: =IF(BE25>365,IF(BF25=365,BB25*AK25,BB25*AK25*BF25/365),0) -> 304.37316 | BH25: =+BB25-BG25 -> 2903.3999 | BI25: =+BH25*AK25 -> 275.49237 | BJ25: =+BH25-BI25 -> 2627.9075 | BK25: =+ROUND(BJ25*AK25,2) -> 249.35 | BL25: =+BJ25-BK25 -> 2378.5575 | BN25: =BL25-BM25 -> 2378.5575 | BO25: =+BL25*AK25 -> 225.69211 | BP25: =+BL25-BO25 -> 2152.8654 | BR25: =BP25-BQ25 -> 2152.8654 | BS25: =+BR25*AK25 -> 204.27706 | BT25: =+BP25-BS25 -> 1948.5884 | BU25: =+BT25*AK25 -> 184.894 | BV25: =+BT25-BU25 -> 1763.6944 | BW25: =+BV25*AK25 -> 167.35012 | BX25: =+BV25-BW25 -> 1596.3442 | BY25: =+BX25*AK25 -> 151.47092 | BZ25: =+BX25-BY25 -> 1444.8733 | CA25: =+BZ25*AK25 -> 137.09843 | CB25: =+BZ25-CA25 -> 1307.7749 | CC25: =+CB25*AK25 -> 124.08969 | CD25: =+CB25-CC25 -> 1183.6852 | CE25: =+CD25*AK25 -> 112.3153 | CF25: =+CD25-CE25 -> 1071.3699 | CG25: =+CF25*AK25 -> 101.65814 | CH25: =+CF25-CG25 -> 969.71175 | CI25: =+CH25*AK25 -> 92.012191 | CJ25: =+CH25-CI25 -> 877.69956 | CK25: =+CJ25*AK25 -> 83.281511 | CL25: =+CJ25-CK25 -> 794.41805 | CM25: =+CL25*AK25 -> 75.379251 | CN25: =+CL25-CM25 -> 719.0388 | CO25: =+CN25*AK25 -> 68.226806 | CP25: =+CN25-CO25 -> 650.81199 | CQ25: =+CP25*AK25 -> 61.753028 | CR25: =+CP25-CQ25 -> 589.05896 | CS25: =+CR25*AK25 -> 55.893523 | CT25: =+CR25-CS25 -> 533.16544 | CU25: =+CT25*AK25 -> 50.590003 | CV25: =+CT25-CU25 -> 482.57544 | CW25: =+CV25*AK25 -> 45.789714 | CX25: =+CV25-CW25 -> 436.78572 | CY25: =+CX25*AK25 -> 41.444905 | CZ25: =+CX25-CY25 -> 395.34082 | DA25: =+CZ25*AK25 -> 37.512359 | DB25: =+CZ25-DA25 -> 357.82846 | DC25: =+DB25*AK25 -> 33.952956 | DD25: =+DB25-DC25 -> 323.8755 | DE25: =+DD25*AK25 -> 30.731292 | DF25: =+DD25-DE25 -> 293.14421 | DG25: =+DF25-E25*5% -> 10.644211 | DH25: =+DF25-DG25 -> 282.5 | DJ25: =+DH25-DI25 -> 282.5 | DL25: =+DJ25-DK25 -> 282.5 | DN25: =+DL25-DM25 -> 282.5 | DP25: =+DN25-DO25 -> 282.5 | DR25: =+DP25-DQ25 -> 282.5 | DT25: =+DR25-DS25 -> 282.5 | DW25: =+E25*5% -> 282.5 | DX25: =+DW25-DR25 -> 0
A26: =A25+1 -> 19 | B26: Factory Building Construction | C26: Building | D26: 0.1 | E26: 100000 | F26: opening | G26: 40770 | S26: 0 | T26: 0 | U26: =E26-T26 -> 100000 | V26: =IF(($V$6-G26+1)>365,365,($V$6-G26+1)) -> 230 | W26: =186694/(U59+825639)*U26 -> 5476.2865 | X26: =IF((U26-W26)>0,U26-W26,E26-W26) -> 94523.713 | Y26: =IF(($Y$6-G26+1)>365,365,($Y$6-G26+1)) -> 365 | Z26: =ROUND(IF(X26>0,X26*$D26/365*Y26,($E26*$D26*Y26/365)),0) -> 9452 | AA26: =IF((X26-Z26)>0,X26-Z26,$E26-Z26) -> 85071.713 | AB26: =IF(($AB$6-G26+1)>365,365,($AB$6-G26+1)) -> 365 | AC26: =ROUND(IF(AA26>0,AA26*$D26/365*AB26,($E26*$D26*AB26/365)),0) -> 8507 | AD26: =IF((AA26-AC26)>0,AA26-AC26,$E26-AC26) -> 76564.713 | AE26: =T26+W26+Z26+AC26+Q26+N26 -> 23435.287 | AF26: =E26-AE26 -> 76564.713 | AG26: =AD26-AF26 -> 0 | AH26: =($AH$6-G26+1)/365 -> 2.630137 | AI26: 30 | AJ26: =AI26-AH26 -> 27.369863 | AK26: =IF(AJ26>0,1-(((E26*$AJ$4)/AF26)^(1/AJ26)),0) -> 0.094888546 | AL26: =IF(AJ26<0,AF26-(E26*5%),0) -> 0 | AM26: =IF(($AM$6-$G26+1)>365,365,($AM$6-$G26+1)) -> 365 | AN26: =ROUND(IF(AF26>0,AF26*$D26/365*AM26,($E26*$D26*AM26/365)),0) -> 7656 | AO26: =MIN(ROUND(IF(AL26>0,0,(AK26*AF26)*AM26/365),0),AF26-(E26*5%)) -> 7265 | AP26: =ROUND(+IF(AJ26<1,(E26*5%),IF(AF26>0,AF26-AO26,E26-AO26)),0) -> 69300 | AQ26: =AF26-AO26-AL26 -> 69299.713 | AR26: =$AF26-($AL26+$AO26+$AP26) -> -0.28650669 | AS26: =AO26-AN26 -> -391 | AT26: =AF26-AN26 -> 68908.713 | AU26: =AT26-AS26-AL26 -> 69299.713 | AV26: =AU26-AQ26 -> 0 | AW26: =IF(($AW$6-$G26+1)>365,365,($AW$6-$G26+1)) -> 365 | AX26: =AU26*AK26 -> 6575.749 | AY26: =AU26-AX26 -> 62723.964 | AZ26: =IF(($AZ$6-$G26+1)>365,365,($AZ$6-$G26+1)) -> 365 | BA26: =AY26*AK26 -> 5951.7858 | BB26: =AY26-BA26 -> 56772.179 | BC26: =60*365 -> 21900 | BD26: =+$BD$6-G26 -> 2055 | BE26: =+BC26-BD26 -> 19845 | BF26: =IF(($BF$6-$G26+1)>365,365,($BF$6-$G26+1)) -> 365 | BG26: =IF(BE26>365,IF(BF26=365,BB26*AK26,BB26*AK26*BF26/365),0) -> 5387.0295 | BH26: =+BB26-BG26 -> 51385.149 | BI26: =+BH26*AK26 -> 4875.8621 | BJ26: =+BH26-BI26 -> 46509.287 | BK26: =+ROUND(BJ26*AK26,2) -> 4413.2 | BL26: =+BJ26-BK26 -> 42096.087 | BN26: =BL26-BM26 -> 42096.087 | BO26: =+BL26*AK26 -> 3994.4365 | BP26: =+BL26-BO26 -> 38101.651 | BR26: =BP26-BQ26 -> 38101.651 | BS26: =+BR26*AK26 -> 3615.4102 | BT26: =+BP26-BS26 -> 34486.24 | BU26: =+BT26*AK26 -> 3272.3492 | BV26: =+BT26-BU26 -> 31213.891 | BW26: =+BV26*AK26 -> 2961.8407 | BX26: =+BV26-BW26 -> 28252.051 | BY26: =+BX26*AK26 -> 2680.796 | BZ26: =+BX26-BY26 -> 25571.255 | CA26: =+BZ26*AK26 -> 2426.4192 | CB26: =+BZ26-CA26 -> 23144.835 | CC26: =+CB26*AK26 -> 2196.1798 | CD26: =+CB26-CC26 -> 20948.656 | CE26: =+CD26*AK26 -> 1987.7875 | CF26: =+CD26-CE26 -> 18960.868 | CG26: =+CF26*AK26 -> 1799.1692 | CH26: =+CF26-CG26 -> 17161.699 | CI26: =+CH26*AK26 -> 1628.4487 | CJ26: =+CH26-CI26 -> 15533.25 | CK26: =+CJ26*AK26 -> 1473.9275 | CL26: =+CJ26-CK26 -> 14059.323 | CM26: =+CL26*AK26 -> 1334.0687 | CN26: =+CL26-CM26 -> 12725.254 | CO26: =+CN26*AK26 -> 1207.4809 | CP26: =+CN26-CO26 -> 11517.773 | CQ26: =+CP26*AK26 -> 1092.9048 | CR26: =+CP26-CQ26 -> 10424.868 | CS26: =+CR26*AK26 -> 989.20061 | CT26: =+CR26-CS26 -> 9435.6679 | CU26: =+CT26*AK26 -> 895.3368 | CV26: =+CT26-CU26 -> 8540.3311 | CW26: =+CV26*AK26 -> 810.37959 | CX26: =+CV26-CW26 -> 7729.9515 | CY26: =+CX26*AK26 -> 733.48385 | CZ26: =+CX26-CY26 -> 6996.4676 | DA26: =+CZ26*AK26 -> 663.88464 | DB26: =+CZ26-DA26 -> 6332.583 | DC26: =+DB26*AK26 -> 600.88959 | DD26: =+DB26-DC26 -> 5731.6934 | DE26: =+DD26*AK26 -> 543.87205 | DF26: =+DD26-DE26 -> 5187.8214 | DG26: =+DF26-E26*5% -> 187.82135 | DH26: =+DF26-DG26 -> 5000 | DJ26: =+DH26-DI26 -> 5000 | DL26: =+DJ26-DK26 -> 5000 | DN26: =+DL26-DM26 -> 5000 | DP26: =+DN26-DO26 -> 5000 | DR26: =+DP26-DQ26 -> 5000 | DT26: =+DR26-DS26 -> 5000 | DW26: =+E26*5% -> 5000 | DX26: =+DW26-DR26 -> 0
A27: =A26+1 -> 20 | B27: Factory Building Construction | C27: Building | D27: 0.1 | E27: 14054 | F27: opening | G27: 40770 | S27: 0 | T27: 0 | U27: =E27-T27 -> 14054 | V27: =IF(($V$6-G27+1)>365,365,($V$6-G27+1)) -> 230 | W27: =186694/(U59+825639)*U27 -> 769.63731 | X27: =IF((U27-W27)>0,U27-W27,E27-W27) -> 13284.363 | Y27: =IF(($Y$6-G27+1)>365,365,($Y$6-G27+1)) -> 365 | Z27: =ROUND(IF(X27>0,X27*$D27/365*Y27,($E27*$D27*Y27/365)),0) -> 1328 | AA27: =IF((X27-Z27)>0,X27-Z27,$E27-Z27) -> 11956.363 | AB27: =IF(($AB$6-G27+1)>365,365,($AB$6-G27+1)) -> 365 | AC27: =ROUND(IF(AA27>0,AA27*$D27/365*AB27,($E27*$D27*AB27/365)),0) -> 1196 | AD27: =IF((AA27-AC27)>0,AA27-AC27,$E27-AC27) -> 10760.363 | AE27: =T27+W27+Z27+AC27+Q27+N27 -> 3293.6373 | AF27: =E27-AE27 -> 10760.363 | AG27: =AD27-AF27 -> 0 | AH27: =($AH$6-G27+1)/365 -> 2.630137 | AI27: 30 | AJ27: =AI27-AH27 -> 27.369863 | AK27: =IF(AJ27>0,1-(((E27*$AJ$4)/AF27)^(1/AJ27)),0) -> 0.094888416 | AL27: =IF(AJ27<0,AF27-(E27*5%),0) -> 0 | AM27: =IF(($AM$6-$G27+1)>365,365,($AM$6-$G27+1)) -> 365 | AN27: =ROUND(IF(AF27>0,AF27*$D27/365*AM27,($E27*$D27*AM27/365)),0) -> 1076 | AO27: =MIN(ROUND(IF(AL27>0,0,(AK27*AF27)*AM27/365),0),AF27-(E27*5%)) -> 1021 | AP27: =ROUND(+IF(AJ27<1,(E27*5%),IF(AF27>0,AF27-AO27,E27-AO27)),0) -> 9739 | AQ27: =AF27-AO27-AL27 -> 9739.3627 | AR27: =$AF27-($AL27+$AO27+$AP27) -> 0.36269435 | AS27: =AO27-AN27 -> -55 | AT27: =AF27-AN27 -> 9684.3627 | AU27: =AT27-AS27-AL27 -> 9739.3627 | AV27: =AU27-AQ27 -> 0 | AW27: =IF(($AW$6-$G27+1)>365,365,($AW$6-$G27+1)) -> 365 | AX27: =AU27*AK27 -> 924.1527 | AY27: =AU27-AX27 -> 8815.21 | AZ27: =IF(($AZ$6-$G27+1)>365,365,($AZ$6-$G27+1)) -> 365 | BA27: =AY27*AK27 -> 836.46131 | BB27: =AY27-BA27 -> 7978.7487 | BC27: =60*365 -> 21900 | BD27: =+$BD$6-G27 -> 2055 | BE27: =+BC27-BD27 -> 19845 | BF27: =IF(($BF$6-$G27+1)>365,365,($BF$6-$G27+1)) -> 365 | BG27: =IF(BE27>365,IF(BF27=365,BB27*AK27,BB27*AK27*BF27/365),0) -> 757.09082 | BH27: =+BB27-BG27 -> 7221.6579 | BI27: =+BH27*AK27 -> 685.25168 | BJ27: =+BH27-BI27 -> 6536.4062 | BK27: =+ROUND(BJ27*AK27,2) -> 620.23 | BL27: =+BJ27-BK27 -> 5916.1762 | BN27: =BL27-BM27 -> 5916.1762 | BO27: =+BL27*AK27 -> 561.37659 | BP27: =+BL27-BO27 -> 5354.7996 | BR27: =BP27-BQ27 -> 5354.7996 | BS27: =+BR27*AK27 -> 508.10845 | BT27: =+BP27-BS27 -> 4846.6911 | BU27: =+BT27*AK27 -> 459.89485 | BV27: =+BT27-BU27 -> 4386.7963 | BW27: =+BV27*AK27 -> 416.25615 | BX27: =+BV27-BW27 -> 3970.5401 | BY27: =+BX27*AK27 -> 376.75827 | BZ27: =+BX27-BY27 -> 3593.7819 | CA27: =+BZ27*AK27 -> 341.00827 | CB27: =+BZ27-CA27 -> 3252.7736 | CC27: =+CB27*AK27 -> 308.65054 | CD27: =+CB27-CC27 -> 2944.1231 | CE27: =+CD27*AK27 -> 279.36318 | CF27: =+CD27-CE27 -> 2664.7599 | CG27: =+CF27*AK27 -> 252.85485 | CH27: =+CF27-CG27 -> 2411.9051 | CI27: =+CH27*AK27 -> 228.86185 | CJ27: =+CH27-CI27 -> 2183.0432 | CK27: =+CJ27*AK27 -> 207.14551 | CL27: =+CJ27-CK27 -> 1975.8977 | CM27: =+CL27*AK27 -> 187.4898 | CN27: =+CL27-CM27 -> 1788.4079 | CO27: =+CN27*AK27 -> 169.69919 | CP27: =+CN27-CO27 -> 1618.7087 | CQ27: =+CP27*AK27 -> 153.5967 | CR27: =+CP27-CQ27 -> 1465.112 | CS27: =+CR27*AK27 -> 139.02216 | CT27: =+CR27-CS27 -> 1326.0898 | CU27: =+CT27*AK27 -> 125.83056 | CV27: =+CT27-CU27 -> 1200.2593 | CW27: =+CV27*AK27 -> 113.8907 | CX27: =+CV27-CW27 -> 1086.3686 | CY27: =+CX27*AK27 -> 103.08379 | CZ27: =+CX27-CY27 -> 983.28478 | DA27: =+CZ27*AK27 -> 93.302335 | DB27: =+CZ27-DA27 -> 889.98244 | DC27: =+DB27*AK27 -> 84.449024 | DD27: =+DB27-DC27 -> 805.53342 | DE27: =+DD27*AK27 -> 76.43579 | DF27: =+DD27-DE27 -> 729.09763 | DG27: =+DF27-E27*5% -> 26.397629 | DH27: =+DF27-DG27 -> 702.7 | DJ27: =+DH27-DI27 -> 702.7 | DL27: =+DJ27-DK27 -> 702.7 | DN27: =+DL27-DM27 -> 702.7 | DP27: =+DN27-DO27 -> 702.7 | DR27: =+DP27-DQ27 -> 702.7 | DT27: =+DR27-DS27 -> 702.7 | DW27: =+E27*5% -> 702.7 | DX27: =+DW27-DR27 -> 0
A28: =A27+1 -> 21 | B28: Factory Building Construction | C28: Building | D28: 0.1 | E28: 7900 | F28: opening | G28: 40770 | S28: 0 | T28: 0 | U28: =E28-T28 -> 7900 | V28: =IF(($V$6-G28+1)>365,365,($V$6-G28+1)) -> 230 | W28: =186694/(U59+825639)*U28 -> 432.62663 | X28: =IF((U28-W28)>0,U28-W28,E28-W28) -> 7467.3734 | Y28: =IF(($Y$6-G28+1)>365,365,($Y$6-G28+1)) -> 365 | Z28: =ROUND(IF(X28>0,X28*$D28/365*Y28,($E28*$D28*Y28/365)),0) -> 747 | AA28: =IF((X28-Z28)>0,X28-Z28,$E28-Z28) -> 6720.3734 | AB28: =IF(($AB$6-G28+1)>365,365,($AB$6-G28+1)) -> 365 | AC28: =ROUND(IF(AA28>0,AA28*$D28/365*AB28,($E28*$D28*AB28/365)),0) -> 672 | AD28: =IF((AA28-AC28)>0,AA28-AC28,$E28-AC28) -> 6048.3734 | AE28: =T28+W28+Z28+AC28+Q28+N28 -> 1851.6266 | AF28: =E28-AE28 -> 6048.3734 | AG28: =AD28-AF28 -> 0 | AH28: =($AH$6-G28+1)/365 -> 2.630137 | AI28: 30 | AJ28: =AI28-AH28 -> 27.369863 | AK28: =IF(AJ28>0,1-(((E28*$AJ$4)/AF28)^(1/AJ28)),0) -> 0.094887239 | AL28: =IF(AJ28<0,AF28-(E28*5%),0) -> 0 | AM28: =IF(($AM$6-$G28+1)>365,365,($AM$6-$G28+1)) -> 365 | AN28: =ROUND(IF(AF28>0,AF28*$D28/365*AM28,($E28*$D28*AM28/365)),0) -> 605 | AO28: =MIN(ROUND(IF(AL28>0,0,(AK28*AF28)*AM28/365),0),AF28-(E28*5%)) -> 574 | AP28: =ROUND(+IF(AJ28<1,(E28*5%),IF(AF28>0,AF28-AO28,E28-AO28)),0) -> 5474 | AQ28: =AF28-AO28-AL28 -> 5474.3734 | AR28: =$AF28-($AL28+$AO28+$AP28) -> 0.37336597 | AS28: =AO28-AN28 -> -31 | AT28: =AF28-AN28 -> 5443.3734 | AU28: =AT28-AS28-AL28 -> 5474.3734 | AV28: =AU28-AQ28 -> 0 | AW28: =IF(($AW$6-$G28+1)>365,365,($AW$6-$G28+1)) -> 365 | AX28: =AU28*AK28 -> 519.44817 | AY28: =AU28-AX28 -> 4954.9252 | AZ28: =IF(($AZ$6-$G28+1)>365,365,($AZ$6-$G28+1)) -> 365 | BA28: =AY28*AK28 -> 470.15917 | BB28: =AY28-BA28 -> 4484.766 | BC28: =60*365 -> 21900 | BD28: =+$BD$6-G28 -> 2055 | BE28: =+BC28-BD28 -> 19845 | BF28: =IF(($BF$6-$G28+1)>365,365,($BF$6-$G28+1)) -> 365 | BG28: =IF(BE28>365,IF(BF28=365,BB28*AK28,BB28*AK28*BF28/365),0) -> 425.54706 | BH28: =+BB28-BG28 -> 4059.219 | BI28: =+BH28*AK28 -> 385.16808 | BJ28: =+BH28-BI28 -> 3674.0509 | BK28: =+ROUND(BJ28*AK28,2) -> 348.62 | BL28: =+BJ28-BK28 -> 3325.4309 | BN28: =BL28-BM28 -> 3325.4309 | BO28: =+BL28*AK28 -> 315.54095 | BP28: =+BL28-BO28 -> 3009.8899 | BR28: =BP28-BQ28 -> 3009.8899 | BS28: =+BR28*AK28 -> 285.60014 | BT28: =+BP28-BS28 -> 2724.2898 | BU28: =+BT28*AK28 -> 258.50034 | BV28: =+BT28-BU28 -> 2465.7894 | BW28: =+BV28*AK28 -> 233.97195 | BX28: =+BV28-BW28 -> 2231.8175 | BY28: =+BX28*AK28 -> 211.771 | BZ28: =+BX28-BY28 -> 2020.0465 | CA28: =+BZ28*AK28 -> 191.67663 | CB28: =+BZ28-CA28 -> 1828.3699 | CC28: =+CB28*AK28 -> 173.48897 | CD28: =+CB28-CC28 -> 1654.8809 | CE28: =+CD28*AK28 -> 157.02708 | CF28: =+CD28-CE28 -> 1497.8538 | CG28: =+CF28*AK28 -> 142.12721 | CH28: =+CF28-CG28 -> 1355.7266 | CI28: =+CH28*AK28 -> 128.64115 | CJ28: =+CH28-CI28 -> 1227.0854 | CK28: =+CJ28*AK28 -> 116.43475 | CL28: =+CJ28-CK28 -> 1110.6507 | CM28: =+CL28*AK28 -> 105.38658 | CN28: =+CL28-CM28 -> 1005.2641 | CO28: =+CN28*AK28 -> 95.386737 | CP28: =+CN28-CO28 -> 909.87738 | CQ28: =+CP28*AK28 -> 86.335753 | CR28: =+CP28-CQ28 -> 823.54163 | CS28: =+CR28*AK28 -> 78.143591 | CT28: =+CR28-CS28 -> 745.39804 | CU28: =+CT28*AK28 -> 70.728762 | CV28: =+CT28-CU28 -> 674.66928 | CW28: =+CV28*AK28 -> 64.017505 | CX28: =+CV28-CW28 -> 610.65177 | CY28: =+CX28*AK28 -> 57.943061 | CZ28: =+CX28-CY28 -> 552.70871 | DA28: =+CZ28*AK28 -> 52.445004 | DB28: =+CZ28-DA28 -> 500.26371 | DC28: =+DB28*AK28 -> 47.468642 | DD28: =+DB28-DC28 -> 452.79507 | DE28: =+DD28*AK28 -> 42.964474 | DF28: =+DD28-DE28 -> 409.83059 | DG28: =+DF28-E28*5% -> 14.830593 | DH28: =+DF28-DG28 -> 395 | DJ28: =+DH28-DI28 -> 395 | DL28: =+DJ28-DK28 -> 395 | DN28: =+DL28-DM28 -> 395 | DP28: =+DN28-DO28 -> 395 | DR28: =+DP28-DQ28 -> 395 | DT28: =+DR28-DS28 -> 395 | DW28: =+E28*5% -> 395 | DX28: =+DW28-DR28 -> 0
A29: =A28+1 -> 22 | B29: Factory Building Construction | C29: Building | D29: 0.1 | E29: 48084 | F29: opening | G29: 40770 | S29: 0 | T29: 0 | U29: =E29-T29 -> 48084 | V29: =IF(($V$6-G29+1)>365,365,($V$6-G29+1)) -> 230 | W29: =186694/(U59+825639)*U29 -> 2633.2176 | X29: =IF((U29-W29)>0,U29-W29,E29-W29) -> 45450.782 | Y29: =IF(($Y$6-G29+1)>365,365,($Y$6-G29+1)) -> 365 | Z29: =ROUND(IF(X29>0,X29*$D29/365*Y29,($E29*$D29*Y29/365)),0) -> 4545 | AA29: =IF((X29-Z29)>0,X29-Z29,$E29-Z29) -> 40905.782 | AB29: =IF(($AB$6-G29+1)>365,365,($AB$6-G29+1)) -> 365 | AC29: =ROUND(IF(AA29>0,AA29*$D29/365*AB29,($E29*$D29*AB29/365)),0) -> 4091 | AD29: =IF((AA29-AC29)>0,AA29-AC29,$E29-AC29) -> 36814.782 | AE29: =T29+W29+Z29+AC29+Q29+N29 -> 11269.218 | AF29: =E29-AE29 -> 36814.782 | AG29: =AD29-AF29 -> 0 | AH29: =($AH$6-G29+1)/365 -> 2.630137 | AI29: 30 | AJ29: =AI29-AH29 -> 27.369863 | AK29: =IF(AJ29>0,1-(((E29*$AJ$4)/AF29)^(1/AJ29)),0) -> 0.094888012 | AL29: =IF(AJ29<0,AF29-(E29*5%),0) -> 0 | AM29: =IF(($AM$6-$G29+1)>365,365,($AM$6-$G29+1)) -> 365 | AN29: =ROUND(IF(AF29>0,AF29*$D29/365*AM29,($E29*$D29*AM29/365)),0) -> 3681 | AO29: =MIN(ROUND(IF(AL29>0,0,(AK29*AF29)*AM29/365),0),AF29-(E29*5%)) -> 3493 | AP29: =ROUND(+IF(AJ29<1,(E29*5%),IF(AF29>0,AF29-AO29,E29-AO29)),0) -> 33322 | AQ29: =AF29-AO29-AL29 -> 33321.782 | AR29: =$AF29-($AL29+$AO29+$AP29) -> -0.21760388 | AS29: =AO29-AN29 -> -188 | AT29: =AF29-AN29 -> 33133.782 | AU29: =AT29-AS29-AL29 -> 33321.782 | AV29: =AU29-AQ29 -> 0 | AW29: =IF(($AW$6-$G29+1)>365,365,($AW$6-$G29+1)) -> 365 | AX29: =AU29*AK29 -> 3161.8377 | AY29: =AU29-AX29 -> 30159.945 | AZ29: =IF(($AZ$6-$G29+1)>365,365,($AZ$6-$G29+1)) -> 365 | BA29: =AY29*AK29 -> 2861.8172 | BB29: =AY29-BA29 -> 27298.128 | BC29: =60*365 -> 21900 | BD29: =+$BD$6-G29 -> 2055 | BE29: =+BC29-BD29 -> 19845 | BF29: =IF(($BF$6-$G29+1)>365,365,($BF$6-$G29+1)) -> 365 | BG29: =IF(BE29>365,IF(BF29=365,BB29*AK29,BB29*AK29*BF29/365),0) -> 2590.265 | BH29: =+BB29-BG29 -> 24707.862 | BI29: =+BH29*AK29 -> 2344.4799 | BJ29: =+BH29-BI29 -> 22363.383 | BK29: =+ROUND(BJ29*AK29,2) -> 2122.02 | BL29: =+BJ29-BK29 -> 20241.363 | BN29: =BL29-BM29 -> 20241.363 | BO29: =+BL29*AK29 -> 1920.6626 | BP29: =+BL29-BO29 -> 18320.7 | BR29: =BP29-BQ29 -> 18320.7 | BS29: =+BR29*AK29 -> 1738.4148 | BT29: =+BP29-BS29 -> 16582.285 | BU29: =+BT29*AK29 -> 1573.4601 | BV29: =+BT29-BU29 -> 15008.825 | BW29: =+BV29*AK29 -> 1424.1576 | BX29: =+BV29-BW29 -> 13584.667 | BY29: =+BX29*AK29 -> 1289.0221 | BZ29: =+BX29-BY29 -> 12295.645 | CA29: =+BZ29*AK29 -> 1166.7093 | CB29: =+BZ29-CA29 -> 11128.936 | CC29: =+CB29*AK29 -> 1056.0026 | CD29: =+CB29-CC29 -> 10072.933 | CE29: =+CD29*AK29 -> 955.80063 | CF29: =+CD29-CE29 -> 9117.1328 | CG29: =+CF29*AK29 -> 865.10661 | CH29: =+CF29-CG29 -> 8252.0262 | CI29: =+CH29*AK29 -> 783.01836 | CJ29: =+CH29-CI29 -> 7469.0079 | CK29: =+CJ29*AK29 -> 708.7193 | CL29: =+CJ29-CK29 -> 6760.2886 | CM29: =+CL29*AK29 -> 641.47034 | CN29: =+CL29-CM29 -> 6118.8182 | CO29: =+CN29*AK29 -> 580.60249 | CP29: =+CN29-CO29 -> 5538.2157 | CQ29: =+CP29*AK29 -> 525.51028 | CR29: =+CP29-CQ29 -> 5012.7054 | CS29: =+CR29*AK29 -> 475.64565 | CT29: =+CR29-CS29 -> 4537.0598 | CU29: =+CT29*AK29 -> 430.51258 | CV29: =+CT29-CU29 -> 4106.5472 | CW29: =+CV29*AK29 -> 389.6621 | CX29: =+CV29-CW29 -> 3716.8851 | CY29: =+CX29*AK29 -> 352.68784 | CZ29: =+CX29-CY29 -> 3364.1973 | DA29: =+CZ29*AK29 -> 319.22199 | DB29: =+CZ29-DA29 -> 3044.9753 | DC29: =+DB29*AK29 -> 288.93165 | DD29: =+DB29-DC29 -> 2756.0436 | DE29: =+DD29*AK29 -> 261.5155 | DF29: =+DD29-DE29 -> 2494.5281 | DG29: =+DF29-E29*5% -> 90.328135 | DH29: =+DF29-DG29 -> 2404.2 | DJ29: =+DH29-DI29 -> 2404.2 | DL29: =+DJ29-DK29 -> 2404.2 | DN29: =+DL29-DM29 -> 2404.2 | DP29: =+DN29-DO29 -> 2404.2 | DR29: =+DP29-DQ29 -> 2404.2 | DT29: =+DR29-DS29 -> 2404.2 | DW29: =+E29*5% -> 2404.2 | DX29: =+DW29-DR29 -> 0
A30: =A29+1 -> 23 | B30: Factory Building Construction | C30: Building | D30: 0.1 | E30: 81643 | F30: opening | G30: 40770 | S30: 0 | T30: 0 | U30: =E30-T30 -> 81643 | V30: =IF(($V$6-G30+1)>365,365,($V$6-G30+1)) -> 230 | W30: =186694/(U59+825639)*U30 -> 4471.0046 | X30: =IF((U30-W30)>0,U30-W30,E30-W30) -> 77171.995 | Y30: =IF(($Y$6-G30+1)>365,365,($Y$6-G30+1)) -> 365 | Z30: =ROUND(IF(X30>0,X30*$D30/365*Y30,($E30*$D30*Y30/365)),0) -> 7717 | AA30: =IF((X30-Z30)>0,X30-Z30,$E30-Z30) -> 69454.995 | AB30: =IF(($AB$6-G30+1)>365,365,($AB$6-G30+1)) -> 365 | AC30: =ROUND(IF(AA30>0,AA30*$D30/365*AB30,($E30*$D30*AB30/365)),0) -> 6945 | AD30: =IF((AA30-AC30)>0,AA30-AC30,$E30-AC30) -> 62509.995 | AE30: =T30+W30+Z30+AC30+Q30+N30 -> 19133.005 | AF30: =E30-AE30 -> 62509.995 | AG30: =AD30-AF30 -> 0 | AH30: =($AH$6-G30+1)/365 -> 2.630137 | AI30: 30 | AJ30: =AI30-AH30 -> 27.369863 | AK30: =IF(AJ30>0,1-(((E30*$AJ$4)/AF30)^(1/AJ30)),0) -> 0.094888686 | AL30: =IF(AJ30<0,AF30-(E30*5%),0) -> 0 | AM30: =IF(($AM$6-$G30+1)>365,365,($AM$6-$G30+1)) -> 365 | AN30: =ROUND(IF(AF30>0,AF30*$D30/365*AM30,($E30*$D30*AM30/365)),0) -> 6251 | AO30: =MIN(ROUND(IF(AL30>0,0,(AK30*AF30)*AM30/365),0),AF30-(E30*5%)) -> 5931 | AP30: =ROUND(+IF(AJ30<1,(E30*5%),IF(AF30>0,AF30-AO30,E30-AO30)),0) -> 56579 | AQ30: =AF30-AO30-AL30 -> 56578.995 | AR30: =$AF30-($AL30+$AO30+$AP30) -> -0.0045926606 | AS30: =AO30-AN30 -> -320 | AT30: =AF30-AN30 -> 56258.995 | AU30: =AT30-AS30-AL30 -> 56578.995 | AV30: =AU30-AQ30 -> 0 | AW30: =IF(($AW$6-$G30+1)>365,365,($AW$6-$G30+1)) -> 365 | AX30: =AU30*AK30 -> 5368.7066 | AY30: =AU30-AX30 -> 51210.289 | AZ30: =IF(($AZ$6-$G30+1)>365,365,($AZ$6-$G30+1)) -> 365 | BA30: =AY30*AK30 -> 4859.277 | BB30: =AY30-BA30 -> 46351.012 | BC30: =60*365 -> 21900 | BD30: =+$BD$6-G30 -> 2055 | BE30: =+BC30-BD30 -> 19845 | BF30: =IF(($BF$6-$G30+1)>365,365,($BF$6-$G30+1)) -> 365 | BG30: =IF(BE30>365,IF(BF30=365,BB30*AK30,BB30*AK30*BF30/365),0) -> 4398.1866 | BH30: =+BB30-BG30 -> 41952.825 | BI30: =+BH30*AK30 -> 3980.8485 | BJ30: =+BH30-BI30 -> 37971.977 | BK30: =+ROUND(BJ30*AK30,2) -> 3603.11 | BL30: =+BJ30-BK30 -> 34368.867 | BN30: =BL30-BM30 -> 34368.867 | BO30: =+BL30*AK30 -> 3261.2166 | BP30: =+BL30-BO30 -> 31107.65 | BR30: =BP30-BQ30 -> 31107.65 | BS30: =+BR30*AK30 -> 2951.7641 | BT30: =+BP30-BS30 -> 28155.886 | BU30: =+BT30*AK30 -> 2671.675 | BV30: =+BT30-BU30 -> 25484.211 | BW30: =+BV30*AK30 -> 2418.1633 | BX30: =+BV30-BW30 -> 23066.048 | BY30: =+BX30*AK30 -> 2188.707 | BZ30: =+BX30-BY30 -> 20877.341 | CA30: =+BZ30*AK30 -> 1981.0234 | CB30: =+BZ30-CA30 -> 18896.317 | CC30: =+CB30*AK30 -> 1793.0467 | CD30: =+CB30-CC30 -> 17103.271 | CE30: =+CD30*AK30 -> 1622.9069 | CF30: =+CD30-CE30 -> 15480.364 | CG30: =+CF30*AK30 -> 1468.9114 | CH30: =+CF30-CG30 -> 14011.452 | CI30: =+CH30*AK30 -> 1329.5283 | CJ30: =+CH30-CI30 -> 12681.924 | CK30: =+CJ30*AK30 -> 1203.3711 | CL30: =+CJ30-CK30 -> 11478.553 | CM30: =+CL30*AK30 -> 1089.1848 | CN30: =+CL30-CM30 -> 10389.368 | CO30: =+CN30*AK30 -> 985.83349 | CP30: =+CN30-CO30 -> 9403.5346 | CQ30: =+CP30*AK30 -> 892.28905 | CR30: =+CP30-CQ30 -> 8511.2456 | CS30: =+CR30*AK30 -> 807.62091 | CT30: =+CR30-CS30 -> 7703.6246 | CU30: =+CT30*AK30 -> 730.98682 | CV30: =+CT30-CU30 -> 6972.6378 | CW30: =+CV30*AK30 -> 661.62444 | CX30: =+CV30-CW30 -> 6311.0134 | CY30: =+CX30*AK30 -> 598.84377 | CZ30: =+CX30-CY30 -> 5712.1696 | DA30: =+CZ30*AK30 -> 542.02027 | DB30: =+CZ30-DA30 -> 5170.1493 | DC30: =+DB30*AK30 -> 490.58868 | DD30: =+DB30-DC30 -> 4679.5607 | DE30: =+DD30*AK30 -> 444.03736 | DF30: =+DD30-DE30 -> 4235.5233 | DG30: =+DF30-E30*5% -> 153.37329 | DH30: =+DF30-DG30 -> 4082.15 | DJ30: =+DH30-DI30 -> 4082.15 | DL30: =+DJ30-DK30 -> 4082.15 | DN30: =+DL30-DM30 -> 4082.15 | DP30: =+DN30-DO30 -> 4082.15 | DR30: =+DP30-DQ30 -> 4082.15 | DT30: =+DR30-DS30 -> 4082.15 | DW30: =+E30*5% -> 4082.15 | DX30: =+DW30-DR30 -> 0
A31: =A30+1 -> 24 | B31: Factory Building Construction | C31: Building | D31: 0.1 | E31: 265561 | F31: opening | G31: 40770 | S31: 0 | T31: 0 | U31: =E31-T31 -> 265561 | V31: =IF(($V$6-G31+1)>365,365,($V$6-G31+1)) -> 230 | W31: =186694/(U59+825639)*U31 -> 14542.881 | X31: =IF((U31-W31)>0,U31-W31,E31-W31) -> 251018.12 | Y31: =IF(($Y$6-G31+1)>365,365,($Y$6-G31+1)) -> 365 | Z31: =ROUND(IF(X31>0,X31*$D31/365*Y31,($E31*$D31*Y31/365)),0) -> 25102 | AA31: =IF((X31-Z31)>0,X31-Z31,$E31-Z31) -> 225916.12 | AB31: =IF(($AB$6-G31+1)>365,365,($AB$6-G31+1)) -> 365 | AC31: =ROUND(IF(AA31>0,AA31*$D31/365*AB31,($E31*$D31*AB31/365)),0) -> 22592 | AD31: =IF((AA31-AC31)>0,AA31-AC31,$E31-AC31) -> 203324.12 | AE31: =T31+W31+Z31+AC31+Q31+N31 -> 62236.881 | AF31: =E31-AE31 -> 203324.12 | AG31: =AD31-AF31 -> 0 | AH31: =($AH$6-G31+1)/365 -> 2.630137 | AI31: 30 | AJ31: =AI31-AH31 -> 27.369863 | AK31: =IF(AJ31>0,1-(((E31*$AJ$4)/AF31)^(1/AJ31)),0) -> 0.094888236 | AL31: =IF(AJ31<0,AF31-(E31*5%),0) -> 0 | AM31: =IF(($AM$6-$G31+1)>365,365,($AM$6-$G31+1)) -> 365 | AN31: =ROUND(IF(AF31>0,AF31*$D31/365*AM31,($E31*$D31*AM31/365)),0) -> 20332 | AO31: =MIN(ROUND(IF(AL31>0,0,(AK31*AF31)*AM31/365),0),AF31-(E31*5%)) -> 19293 | AP31: =ROUND(+IF(AJ31<1,(E31*5%),IF(AF31>0,AF31-AO31,E31-AO31)),0) -> 184031 | AQ31: =AF31-AO31-AL31 -> 184031.12 | AR31: =$AF31-($AL31+$AO31+$AP31) -> 0.11878996 | AS31: =AO31-AN31 -> -1039 | AT31: =AF31-AN31 -> 182992.12 | AU31: =AT31-AS31-AL31 -> 184031.12 | AV31: =AU31-AQ31 -> 0 | AW31: =IF(($AW$6-$G31+1)>365,365,($AW$6-$G31+1)) -> 365 | AX31: =AU31*AK31 -> 17462.388 | AY31: =AU31-AX31 -> 166568.73 | AZ31: =IF(($AZ$6-$G31+1)>365,365,($AZ$6-$G31+1)) -> 365 | BA31: =AY31*AK31 -> 15805.413 | BB31: =AY31-BA31 -> 150763.32 | BC31: =60*365 -> 21900 | BD31: =+$BD$6-G31 -> 2055 | BE31: =+BC31-BD31 -> 19845 | BF31: =IF(($BF$6-$G31+1)>365,365,($BF$6-$G31+1)) -> 365 | BG31: =IF(BE31>365,IF(BF31=365,BB31*AK31,BB31*AK31*BF31/365),0) -> 14305.665 | BH31: =+BB31-BG31 -> 136457.65 | BI31: =+BH31*AK31 -> 12948.226 | BJ31: =+BH31-BI31 -> 123509.43 | BK31: =+ROUND(BJ31*AK31,2) -> 11719.59 | BL31: =+BJ31-BK31 -> 111789.84 | BN31: =BL31-BM31 -> 111789.84 | BO31: =+BL31*AK31 -> 10607.54 | BP31: =+BL31-BO31 -> 101182.3 | BR31: =BP31-BQ31 -> 101182.3 | BS31: =+BR31*AK31 -> 9601.0096 | BT31: =+BP31-BS31 -> 91581.286 | BU31: =+BT31*AK31 -> 8689.9867 | BV31: =+BT31-BU31 -> 82891.299 | BW31: =+BV31*AK31 -> 7865.4092 | BX31: =+BV31-BW31 -> 75025.89 | BY31: =+BX31*AK31 -> 7119.0744 | BZ31: =+BX31-BY31 -> 67906.816 | CA31: =+BZ31*AK31 -> 6443.558 | CB31: =+BZ31-CA31 -> 61463.258 | CC31: =+CB31*AK31 -> 5832.1401 | CD31: =+CB31-CC31 -> 55631.118 | CE31: =+CD31*AK31 -> 5278.7386 | CF31: =+CD31-CE31 -> 50352.379 | CG31: =+CF31*AK31 -> 4777.8484 | CH31: =+CF31-CG31 -> 45574.531 | CI31: =+CH31*AK31 -> 4324.4868 | CJ31: =+CH31-CI31 -> 41250.044 | CK31: =+CJ31*AK31 -> 3914.1439 | CL31: =+CJ31-CK31 -> 37335.9 | CM31: =+CL31*AK31 -> 3542.7377 | CN31: =+CL31-CM31 -> 33793.162 | CO31: =+CN31*AK31 -> 3206.5736 | CP31: =+CN31-CO31 -> 30586.589 | CQ31: =+CP31*AK31 -> 2902.3074 | CR31: =+CP31-CQ31 -> 27684.281 | CS31: =+CR31*AK31 -> 2626.9126 | CT31: =+CR31-CS31 -> 25057.368 | CU31: =+CT31*AK31 -> 2377.6495 | CV31: =+CT31-CU31 -> 22679.719 | CW31: =+CV31*AK31 -> 2152.0385 | CX31: =+CV31-CW31 -> 20527.68 | CY31: =+CX31*AK31 -> 1947.8354 | CZ31: =+CX31-CY31 -> 18579.845 | DA31: =+CZ31*AK31 -> 1763.0087 | DB31: =+CZ31-DA31 -> 16816.836 | DC31: =+DB31*AK31 -> 1595.7199 | DD31: =+DB31-DC31 -> 15221.116 | DE31: =+DD31*AK31 -> 1444.3049 | DF31: =+DD31-DE31 -> 13776.811 | DG31: =+DF31-E31*5% -> 498.76148 | DH31: =+DF31-DG31 -> 13278.05 | DI31: 0 | DJ31: =+DH31-DI31 -> 13278.05 | DK31: 0 | DL31: =+DJ31-DK31 -> 13278.05 | DM31: 0 | DN31: =+DL31-DM31 -> 13278.05 | DO31: 0 | DP31: =+DN31-DO31 -> 13278.05 | DQ31: 0 | DR31: =+DP31-DQ31 -> 13278.05 | DT31: =+DR31-DS31 -> 13278.05 | DW31: =+E31*5% -> 13278.05 | DX31: =+DW31-DR31 -> 0
A32: =A31+1 -> 25 | B32: Factory Building Construction | C32: Building | D32: 0.1 | E32: 9641 | F32: opening | G32: 40770 | S32: 0 | T32: 0 | U32: =E32-T32 -> 9641 | V32: =IF(($V$6-G32+1)>365,365,($V$6-G32+1)) -> 230 | W32: =186694/(U59+825639)*U32 -> 527.96878 | X32: =IF((U32-W32)>0,U32-W32,E32-W32) -> 9113.0312 | Y32: =IF(($Y$6-G32+1)>365,365,($Y$6-G32+1)) -> 365 | Z32: =ROUND(IF(X32>0,X32*$D32/365*Y32,($E32*$D32*Y32/365)),0) -> 911 | AA32: =IF((X32-Z32)>0,X32-Z32,$E32-Z32) -> 8202.0312 | AB32: =IF(($AB$6-G32+1)>365,365,($AB$6-G32+1)) -> 365 | AC32: =ROUND(IF(AA32>0,AA32*$D32/365*AB32,($E32*$D32*AB32/365)),0) -> 820 | AD32: =IF((AA32-AC32)>0,AA32-AC32,$E32-AC32) -> 7382.0312 | AE32: =T32+W32+Z32+AC32+Q32+N32 -> 2258.9688 | AF32: =E32-AE32 -> 7382.0312 | AG32: =AD32-AF32 -> 0 | AH32: =($AH$6-G32+1)/365 -> 2.630137 | AI32: 30 | AJ32: =AI32-AH32 -> 27.369863 | AK32: =IF(AJ32>0,1-(((E32*$AJ$4)/AF32)^(1/AJ32)),0) -> 0.094890459 | AL32: =IF(AJ32<0,AF32-(E32*5%),0) -> 0 | AM32: =IF(($AM$6-$G32+1)>365,365,($AM$6-$G32+1)) -> 365 | AN32: =ROUND(IF(AF32>0,AF32*$D32/365*AM32,($E32*$D32*AM32/365)),0) -> 738 | AO32: =MIN(ROUND(IF(AL32>0,0,(AK32*AF32)*AM32/365),0),AF32-(E32*5%)) -> 700 | AP32: =ROUND(+IF(AJ32<1,(E32*5%),IF(AF32>0,AF32-AO32,E32-AO32)),0) -> 6682 | AQ32: =AF32-AO32-AL32 -> 6682.0312 | AR32: =$AF32-($AL32+$AO32+$AP32) -> 0.03121789 | AS32: =AO32-AN32 -> -38 | AT32: =AF32-AN32 -> 6644.0312 | AU32: =AT32-AS32-AL32 -> 6682.0312 | AV32: =AU32-AQ32 -> 0 | AW32: =IF(($AW$6-$G32+1)>365,365,($AW$6-$G32+1)) -> 365 | AX32: =AU32*AK32 -> 634.06101 | AY32: =AU32-AX32 -> 6047.9702 | AZ32: =IF(($AZ$6-$G32+1)>365,365,($AZ$6-$G32+1)) -> 365 | BA32: =AY32*AK32 -> 573.89467 | BB32: =AY32-BA32 -> 5474.0755 | BC32: =60*365 -> 21900 | BD32: =+$BD$6-G32 -> 2055 | BE32: =+BC32-BD32 -> 19845 | BF32: =IF(($BF$6-$G32+1)>365,365,($BF$6-$G32+1)) -> 365 | BG32: =IF(BE32>365,IF(BF32=365,BB32*AK32,BB32*AK32*BF32/365),0) -> 519.43754 | BH32: =+BB32-BG32 -> 4954.638 | BI32: =+BH32*AK32 -> 470.14787 | BJ32: =+BH32-BI32 -> 4484.4901 | BK32: =+ROUND(BJ32*AK32,2) -> 425.54 | BL32: =+BJ32-BK32 -> 4058.9501 | BN32: =BL32-BM32 -> 4058.9501 | BO32: =+BL32*AK32 -> 385.15564 | BP32: =+BL32-BO32 -> 3673.7945 | BR32: =BP32-BQ32 -> 3673.7945 | BS32: =+BR32*AK32 -> 348.60805 | BT32: =+BP32-BS32 -> 3325.1864 | BU32: =+BT32*AK32 -> 315.52847 | BV32: =+BT32-BU32 -> 3009.658 | BW32: =+BV32*AK32 -> 285.58783 | BX32: =+BV32-BW32 -> 2724.0701 | BY32: =+BX32*AK32 -> 258.48827 | BZ32: =+BX32-BY32 -> 2465.5819 | CA32: =+BZ32*AK32 -> 233.9602 | CB32: =+BZ32-CA32 -> 2231.6217 | CC32: =+CB32*AK32 -> 211.75961 | CD32: =+CB32-CC32 -> 2019.8621 | CE32: =+CD32*AK32 -> 191.66564 | CF32: =+CD32-CE32 -> 1828.1964 | CG32: =+CF32*AK32 -> 173.4784 | CH32: =+CF32-CG32 -> 1654.718 | CI32: =+CH32*AK32 -> 157.01695 | CJ32: =+CH32-CI32 -> 1497.7011 | CK32: =+CJ32*AK32 -> 142.11754 | CL32: =+CJ32-CK32 -> 1355.5835 | CM32: =+CL32*AK32 -> 128.63194 | CN32: =+CL32-CM32 -> 1226.9516 | CO32: =+CN32*AK32 -> 116.426 | CP32: =+CN32-CO32 -> 1110.5256 | CQ32: =+CP32*AK32 -> 105.37828 | CR32: =+CP32-CQ32 -> 1005.1473 | CS32: =+CR32*AK32 -> 95.37889 | CT32: =+CR32-CS32 -> 909.76842 | CU32: =+CT32*AK32 -> 86.328343 | CV32: =+CT32-CU32 -> 823.44007 | CW32: =+CV32*AK32 -> 78.136607 | CX32: =+CV32-CW32 -> 745.30347 | CY32: =+CX32*AK32 -> 70.722188 | CZ32: =+CX32-CY32 -> 674.58128 | DA32: =+CZ32*AK32 -> 64.011327 | DB32: =+CZ32-DA32 -> 610.56995 | DC32: =+DB32*AK32 -> 57.937263 | DD32: =+DB32-DC32 -> 552.63269 | DE32: =+DD32*AK32 -> 52.43957 | DF32: =+DD32-DE32 -> 500.19312 | DG32: =IF((DF32-(DF32*$AK$32))>$E$32*5%,DF32*$AK$32,DF32-($E$32*5%)) -> 18.143119 | DH32: =+DF32-DG32 -> 482.05 | DI32: =IF((DH32-(DH32*$AK$32))>$E$32*5%,DH32*$AK$32,DH32-($E$32*5%)) -> 0 | DJ32: =+DH32-DI32 -> 482.05 | DK32: =IF((DJ32-(DJ32*$AK$32))>$E$32*5%,DJ32*$AK$32,DJ32-($E$32*5%)) -> 0 | DL32: =+DJ32-DK32 -> 482.05 | DM32: =IF((DL32-(DL32*$AK$32))>$E$32*5%,DL32*$AK$32,DL32-($E$32*5%)) -> 0 | DN32: =+DL32-DM32 -> 482.05 | DO32: =IF((DN32-(DN32*$AK$32))>$E$32*5%,DN32*$AK$32,DN32-($E$32*5%)) -> 0 | DP32: =+DN32-DO32 -> 482.05 | DR32: =+DP32-DQ32 -> 482.05 | DT32: =+DR32-DS32 -> 482.05 | DW32: =+E32*5% -> 482.05 | DX32: =+DW32-DR32 -> 0
A33: =A32+1 -> 26 | B33: Factory Building Construction | C33: Building | D33: 0.1 | E33: 100400 | F33: opening | G33: 40770 | S33: 0 | T33: 0 | U33: =E33-T33 -> 100400 | V33: =IF(($V$6-G33+1)>365,365,($V$6-G33+1)) -> 230 | W33: =186694/(U59+825639)*U33 -> 5498.1917 | X33: =IF((U33-W33)>0,U33-W33,E33-W33) -> 94901.808 | Y33: =IF(($Y$6-G33+1)>365,365,($Y$6-G33+1)) -> 365 | Z33: =ROUND(IF(X33>0,X33*$D33/365*Y33,($E33*$D33*Y33/365)),0) -> 9490 | AA33: =IF((X33-Z33)>0,X33-Z33,$E33-Z33) -> 85411.808 | AB33: =IF(($AB$6-G33+1)>365,365,($AB$6-G33+1)) -> 365 | AC33: =ROUND(IF(AA33>0,AA33*$D33/365*AB33,($E33*$D33*AB33/365)),0) -> 8541 | AD33: =IF((AA33-AC33)>0,AA33-AC33,$E33-AC33) -> 76870.808 | AE33: =T33+W33+Z33+AC33+Q33+N33 -> 23529.192 | AF33: =E33-AE33 -> 76870.808 | AG33: =AD33-AF33 -> 0 | AH33: =($AH$6-G33+1)/365 -> 2.630137 | AI33: 30 | AJ33: =AI33-AH33 -> 27.369863 | AK33: =IF(AJ33>0,1-(((E33*$AJ$4)/AF33)^(1/AJ33)),0) -> 0.094888475 | AL33: =IF(AJ33<0,AF33-(E33*5%),0) -> 0 | AM33: =IF(($AM$6-$G33+1)>365,365,($AM$6-$G33+1)) -> 365 | AN33: =ROUND(IF(AF33>0,AF33*$D33/365*AM33,($E33*$D33*AM33/365)),0) -> 7687 | AO33: =MIN(ROUND(IF(AL33>0,0,(AK33*AF33)*AM33/365),0),AF33-(E33*5%)) -> 7294 | AP33: =ROUND(+IF(AJ33<1,(E33*5%),IF(AF33>0,AF33-AO33,E33-AO33)),0) -> 69577 | AQ33: =AF33-AO33-AL33 -> 69576.808 | AR33: =$AF33-($AL33+$AO33+$AP33) -> -0.19165272 | AS33: =AO33-AN33 -> -393 | AT33: =AF33-AN33 -> 69183.808 | AU33: =AT33-AS33-AL33 -> 69576.808 | AV33: =AU33-AQ33 -> 0 | AW33: =IF(($AW$6-$G33+1)>365,365,($AW$6-$G33+1)) -> 365 | AX33: =AU33*AK33 -> 6602.0372 | AY33: =AU33-AX33 -> 62974.771 | AZ33: =IF(($AZ$6-$G33+1)>365,365,($AZ$6-$G33+1)) -> 365 | BA33: =AY33*AK33 -> 5975.58 | BB33: =AY33-BA33 -> 56999.191 | BC33: =60*365 -> 21900 | BD33: =+$BD$6-G33 -> 2055 | BE33: =+BC33-BD33 -> 19845 | BF33: =IF(($BF$6-$G33+1)>365,365,($BF$6-$G33+1)) -> 365 | BG33: =IF(BE33>365,IF(BF33=365,BB33*AK33,BB33*AK33*BF33/365),0) -> 5408.5663 | BH33: =+BB33-BG33 -> 51590.625 | BI33: =+BH33*AK33 -> 4895.3557 | BJ33: =+BH33-BI33 -> 46695.269 | BK33: =+ROUND(BJ33*AK33,2) -> 4430.84 | BL33: =+BJ33-BK33 -> 42264.429 | BN33: =BL33-BM33 -> 42264.429 | BO33: =+BL33*AK33 -> 4010.4072 | BP33: =+BL33-BO33 -> 38254.022 | BR33: =BP33-BQ33 -> 38254.022 | BS33: =+BR33*AK33 -> 3629.8658 | BT33: =+BP33-BS33 -> 34624.156 | BU33: =+BT33*AK33 -> 3285.4334 | BV33: =+BT33-BU33 -> 31338.723 | BW33: =+BV33*AK33 -> 2973.6836 | BX33: =+BV33-BW33 -> 28365.039 | BY33: =+BX33*AK33 -> 2691.5153 | BZ33: =+BX33-BY33 -> 25673.524 | CA33: =+BZ33*AK33 -> 2436.1215 | CB33: =+BZ33-CA33 -> 23237.402 | CC33: =+CB33*AK33 -> 2204.9617 | CD33: =+CB33-CC33 -> 21032.441 | CE33: =+CD33*AK33 -> 1995.7362 | CF33: =+CD33-CE33 -> 19036.704 | CG33: =+CF33*AK33 -> 1806.3638 | CH33: =+CF33-CG33 -> 17230.341 | CI33: =+CH33*AK33 -> 1634.9607 | CJ33: =+CH33-CI33 -> 15595.38 | CK33: =+CJ33*AK33 -> 1479.8218 | CL33: =+CJ33-CK33 -> 14115.558 | CM33: =+CL33*AK33 -> 1339.4038 | CN33: =+CL33-CM33 -> 12776.154 | CO33: =+CN33*AK33 -> 1212.3098 | CP33: =+CN33-CO33 -> 11563.844 | CQ33: =+CP33*AK33 -> 1097.2756 | CR33: =+CP33-CQ33 -> 10466.569 | CS33: =+CR33*AK33 -> 993.15676 | CT33: =+CR33-CS33 -> 9473.4121 | CU33: =+CT33*AK33 -> 898.91763 | CV33: =+CT33-CU33 -> 8574.4945 | CW33: =+CV33*AK33 -> 813.62071 | CX33: =+CV33-CW33 -> 7760.8738 | CY33: =+CX33*AK33 -> 736.41748 | CZ33: =+CX33-CY33 -> 7024.4563 | DA33: =+CZ33*AK33 -> 666.53995 | DB33: =+CZ33-DA33 -> 6357.9164 | DC33: =IF((DB33-(DB33*$AK$32))>$E$32*5%,DB33*$AK$32,DB33-($E$32*5%)) -> 603.3056 | DD33: =+DB33-DC33 -> 5754.6108 | DE33: =IF((DD33-(DD33*$AK$32))>$E33*5%,DD33*$AK$32,DD33-($E33*5%)) -> 546.05766 | DF33: =+DD33-DE33 -> 5208.5531 | DG33: =IF((DF33-(DF33*$AK$32))>$E33*5%,DF33*$AK$32,DF33-($E33*5%)) -> 188.5531 | DH33: =+DF33-DG33 -> 5020 | DI33: =IF((DH33-(DH33*$AK$32))>$E33*5%,DH33*$AK$32,DH33-($E33*5%)) -> 0 | DJ33: =+DH33-DI33 -> 5020 | DK33: =IF((DJ33-(DJ33*$AK$32))>$E33*5%,DJ33*$AK$32,DJ33-($E33*5%)) -> 0 | DL33: =+DJ33-DK33 -> 5020 | DM33: =IF((DL33-(DL33*$AK$32))>$E33*5%,DL33*$AK$32,DL33-($E33*5%)) -> 0 | DN33: =+DL33-DM33 -> 5020 | DP33: =+DN33-DO33 -> 5020 | DR33: =+DP33-DQ33 -> 5020 | DT33: =+DR33-DS33 -> 5020 | DW33: =+E33*5% -> 5020 | DX33: =+DW33-DR33 -> 0
A34: =A33+1 -> 27 | B34: Factory Building Construction | C34: Building | D34: 0.1 | E34: 24900 | F34: opening | G34: 40770 | S34: 0 | T34: 0 | U34: =E34-T34 -> 24900 | V34: =IF(($V$6-G34+1)>365,365,($V$6-G34+1)) -> 230 | W34: =186694/(U59+825639)*U34 -> 1363.5953 | X34: =IF((U34-W34)>0,U34-W34,E34-W34) -> 23536.405 | Y34: =IF(($Y$6-G34+1)>365,365,($Y$6-G34+1)) -> 365 | Z34: =ROUND(IF(X34>0,X34*$D34/365*Y34,($E34*$D34*Y34/365)),0) -> 2354 | AA34: =IF((X34-Z34)>0,X34-Z34,$E34-Z34) -> 21182.405 | AB34: =IF(($AB$6-G34+1)>365,365,($AB$6-G34+1)) -> 365 | AC34: =ROUND(IF(AA34>0,AA34*$D34/365*AB34,($E34*$D34*AB34/365)),0) -> 2118 | AD34: =IF((AA34-AC34)>0,AA34-AC34,$E34-AC34) -> 19064.405 | AE34: =T34+W34+Z34+AC34+Q34+N34 -> 5835.5953 | AF34: =E34-AE34 -> 19064.405 | AG34: =AD34-AF34 -> 0 | AH34: =($AH$6-G34+1)/365 -> 2.630137 | AI34: 30 | AJ34: =AI34-AH34 -> 27.369863 | AK34: =IF(AJ34>0,1-(((E34*$AJ$4)/AF34)^(1/AJ34)),0) -> 0.094888183 | AL34: =IF(AJ34<0,AF34-(E34*5%),0) -> 0 | AM34: =IF(($AM$6-$G34+1)>365,365,($AM$6-$G34+1)) -> 365 | AN34: =ROUND(IF(AF34>0,AF34*$D34/365*AM34,($E34*$D34*AM34/365)),0) -> 1906 | AO34: =MIN(ROUND(IF(AL34>0,0,(AK34*AF34)*AM34/365),0),AF34-(E34*5%)) -> 1809 | AP34: =ROUND(+IF(AJ34<1,(E34*5%),IF(AF34>0,AF34-AO34,E34-AO34)),0) -> 17255 | AQ34: =AF34-AO34-AL34 -> 17255.405 | AR34: =$AF34-($AL34+$AO34+$AP34) -> 0.40465983 | AS34: =AO34-AN34 -> -97 | AT34: =AF34-AN34 -> 17158.405 | AU34: =AT34-AS34-AL34 -> 17255.405 | AV34: =AU34-AQ34 -> 0 | AW34: =IF(($AW$6-$G34+1)>365,365,($AW$6-$G34+1)) -> 365 | AX34: =AU34*AK34 -> 1637.334 | AY34: =AU34-AX34 -> 15618.071 | AZ34: =IF(($AZ$6-$G34+1)>365,365,($AZ$6-$G34+1)) -> 365 | BA34: =AY34*AK34 -> 1481.9703 | BB34: =AY34-BA34 -> 14136.1 | BC34: =60*365 -> 21900 | BD34: =+$BD$6-G34 -> 2055 | BE34: =+BC34-BD34 -> 19845 | BF34: =IF(($BF$6-$G34+1)>365,365,($BF$6-$G34+1)) -> 365 | BG34: =IF(BE34>365,IF(BF34=365,BB34*AK34,BB34*AK34*BF34/365),0) -> 1341.3489 | BH34: =+BB34-BG34 -> 12794.751 | BI34: =+BH34*AK34 -> 1214.0707 | BJ34: =+BH34-BI34 -> 11580.681 | BK34: =+ROUND(BJ34*AK34,2) -> 1098.87 | BL34: =+BJ34-BK34 -> 10481.811 | BN34: =BL34-BM34 -> 10481.811 | BO34: =+BL34*AK34 -> 994.59997 | BP34: =+BL34-BO34 -> 9487.2108 | BR34: =BP34-BQ34 -> 9487.2108 | BS34: =+BR34*AK34 -> 900.22419 | BT34: =+BP34-BS34 -> 8586.9866 | BU34: =+BT34*AK34 -> 814.80355 | BV34: =+BT34-BU34 -> 7772.183 | BW34: =+BV34*AK34 -> 737.48832 | BX34: =+BV34-BW34 -> 7034.6947 | BY34: =+BX34*AK34 -> 667.5094 | BZ34: =+BX34-BY34 -> 6367.1853 | CA34: =+BZ34*AK34 -> 604.17064 | CB34: =+BZ34-CA34 -> 5763.0146 | CC34: =+CB34*AK34 -> 546.84199 | CD34: =+CB34-CC34 -> 5216.1727 | CE34: =+CD34*AK34 -> 494.95315 | CF34: =+CD34-CE34 -> 4721.2195 | CG34: =+CF34*AK34 -> 447.98794 | CH34: =+CF34-CG34 -> 4273.2316 | CI34: =+CH34*AK34 -> 405.47918 | CJ34: =+CH34-CI34 -> 3867.7524 | CK34: =+CJ34*AK34 -> 367.004 | CL34: =+CJ34-CK34 -> 3500.7484 | CM34: =+CL34*AK34 -> 332.17965 | CN34: =+CL34-CM34 -> 3168.5687 | CO34: =+CN34*AK34 -> 300.65973 | CP34: =+CN34-CO34 -> 2867.909 | CQ34: =+CP34*AK34 -> 272.13068 | CR34: =+CP34-CQ34 -> 2595.7783 | CS34: =+CR34*AK34 -> 246.30869 | CT34: =+CR34-CS34 -> 2349.4696 | CU34: =+CT34*AK34 -> 222.93691 | CV34: =+CT34-CU34 -> 2126.5327 | CW34: =+CV34*AK34 -> 201.78283 | CX34: =+CV34-CW34 -> 1924.7499 | CY34: =+CX34*AK34 -> 182.63602 | CZ34: =+CX34-CY34 -> 1742.1139 | DA34: =+CZ34*AK34 -> 165.30602 | DB34: =+CZ34-DA34 -> 1576.8079 | DC34: =+DB34*AK34 -> 149.62043 | DD34: =+DB34-DC34 -> 1427.1874 | DE34: =IF((DD34-(DD34*$AK$32))>$E34*5%,DD34*$AK$32,DD34-($E34*5%)) -> 135.42647 | DF34: =+DD34-DE34 -> 1291.761 | DG34: =IF((DF34-(DF34*$AK$32))>$E34*5%,DF34*$AK$32,DF34-($E34*5%)) -> 46.760964 | DH34: =+DF34-DG34 -> 1245 | DI34: =IF((DH34-(DH34*$AK$32))>$E34*5%,DH34*$AK$32,DH34-($E34*5%)) -> 0 | DJ34: =+DH34-DI34 -> 1245 | DK34: =IF((DJ34-(DJ34*$AK$32))>$E34*5%,DJ34*$AK$32,DJ34-($E34*5%)) -> 0 | DL34: =+DJ34-DK34 -> 1245 | DM34: =IF((DL34-(DL34*$AK$32))>$E34*5%,DL34*$AK$32,DL34-($E34*5%)) -> 0 | DN34: =+DL34-DM34 -> 1245 | DP34: =+DN34-DO34 -> 1245 | DR34: =+DP34-DQ34 -> 1245 | DT34: =+DR34-DS34 -> 1245 | DW34: =+E34*5% -> 1245 | DX34: =+DW34-DR34 -> 0
A35: =A34+1 -> 28 | B35: Factory Building Construction | C35: Building | D35: 0.1 | E35: 12550 | F35: opening | G35: 40770 | S35: 0 | T35: 0 | U35: =E35-T35 -> 12550 | V35: =IF(($V$6-G35+1)>365,365,($V$6-G35+1)) -> 230 | W35: =186694/(U59+825639)*U35 -> 687.27396 | X35: =IF((U35-W35)>0,U35-W35,E35-W35) -> 11862.726 | Y35: =IF(($Y$6-G35+1)>365,365,($Y$6-G35+1)) -> 365 | Z35: =ROUND(IF(X35>0,X35*$D35/365*Y35,($E35*$D35*Y35/365)),0) -> 1186 | AA35: =IF((X35-Z35)>0,X35-Z35,$E35-Z35) -> 10676.726 | AB35: =IF(($AB$6-G35+1)>365,365,($AB$6-G35+1)) -> 365 | AC35: =ROUND(IF(AA35>0,AA35*$D35/365*AB35,($E35*$D35*AB35/365)),0) -> 1068 | AD35: =IF((AA35-AC35)>0,AA35-AC35,$E35-AC35) -> 9608.726 | AE35: =T35+W35+Z35+AC35+Q35+N35 -> 2941.274 | AF35: =E35-AE35 -> 9608.726 | AG35: =AD35-AF35 -> 0 | AH35: =($AH$6-G35+1)/365 -> 2.630137 | AI35: 30 | AJ35: =AI35-AH35 -> 27.369863 | AK35: =IF(AJ35>0,1-(((E35*$AJ$4)/AF35)^(1/AJ35)),0) -> 0.094888045 | AL35: =IF(AJ35<0,AF35-(E35*5%),0) -> 0 | AM35: =IF(($AM$6-$G35+1)>365,365,($AM$6-$G35+1)) -> 365 | AN35: =ROUND(IF(AF35>0,AF35*$D35/365*AM35,($E35*$D35*AM35/365)),0) -> 961 | AO35: =MIN(ROUND(IF(AL35>0,0,(AK35*AF35)*AM35/365),0),AF35-(E35*5%)) -> 912 | AP35: =ROUND(+IF(AJ35<1,(E35*5%),IF(AF35>0,AF35-AO35,E35-AO35)),0) -> 8697 | AQ35: =AF35-AO35-AL35 -> 8696.726 | AR35: =$AF35-($AL35+$AO35+$AP35) -> -0.27395659 | AS35: =AO35-AN35 -> -49 | AT35: =AF35-AN35 -> 8647.726 | AU35: =AT35-AS35-AL35 -> 8696.726 | AV35: =AU35-AQ35 -> 0 | AW35: =IF(($AW$6-$G35+1)>365,365,($AW$6-$G35+1)) -> 365 | AX35: =AU35*AK35 -> 825.21533 | AY35: =AU35-AX35 -> 7871.5107 | AZ35: =IF(($AZ$6-$G35+1)>365,365,($AZ$6-$G35+1)) -> 365 | BA35: =AY35*AK35 -> 746.91226 | BB35: =AY35-BA35 -> 7124.5985 | BC35: =60*365 -> 21900 | BD35: =+$BD$6-G35 -> 2055 | BE35: =+BC35-BD35 -> 19845 | BF35: =IF(($BF$6-$G35+1)>365,365,($BF$6-$G35+1)) -> 365 | BG35: =IF(BE35>365,IF(BF35=365,BB35*AK35,BB35*AK35*BF35/365),0) -> 676.03922 | BH35: =+BB35-BG35 -> 6448.5592 | BI35: =+BH35*AK35 -> 611.89118 | BJ35: =+BH35-BI35 -> 5836.6681 | BK35: =+ROUND(BJ35*AK35,2) -> 553.83 | BL35: =+BJ35-BK35 -> 5282.8381 | BN35: =BL35-BM35 -> 5282.8381 | BO35: =+BL35*AK35 -> 501.27817 | BP35: =+BL35-BO35 -> 4781.5599 | BR35: =BP35-BQ35 -> 4781.5599 | BS35: =+BR35*AK35 -> 453.71287 | BT35: =+BP35-BS35 -> 4327.847 | BU35: =+BT35*AK35 -> 410.66094 | BV35: =+BT35-BU35 -> 3917.1861 | BW35: =+BV35*AK35 -> 371.69413 | BX35: =+BV35-BW35 -> 3545.4919 | BY35: =+BX35*AK35 -> 336.4248 | BZ35: =+BX35-BY35 -> 3209.0671 | CA35: =+BZ35*AK35 -> 304.50211 | CB35: =+BZ35-CA35 -> 2904.565 | CC35: =+CB35*AK35 -> 275.6085 | CD35: =+CB35-CC35 -> 2628.9565 | CE35: =+CD35*AK35 -> 249.45655 | CF35: =+CD35-CE35 -> 2379.5 | CG35: =+CF35*AK35 -> 225.7861 | CH35: =+CF35-CG35 -> 2153.7139 | CI35: =+CH35*AK35 -> 204.3617 | CJ35: =+CH35-CI35 -> 1949.3522 | CK35: =+CJ35*AK35 -> 184.97022 | CL35: =+CJ35-CK35 -> 1764.382 | CM35: =+CL35*AK35 -> 167.41876 | CN35: =+CL35-CM35 -> 1596.9632 | CO35: =+CN35*AK35 -> 151.53272 | CP35: =+CN35-CO35 -> 1445.4305 | CQ35: =+CP35*AK35 -> 137.15407 | CR35: =+CP35-CQ35 -> 1308.2764 | CS35: =+CR35*AK35 -> 124.13979 | CT35: =+CR35-CS35 -> 1184.1366 | CU35: =+CT35*AK35 -> 112.36041 | CV35: =+CT35-CU35 -> 1071.7762 | CW35: =+CV35*AK35 -> 101.69875 | CX35: =+CV35-CW35 -> 970.07748 | CY35: =+CX35*AK35 -> 92.048755 | CZ35: =+CX35-CY35 -> 878.02872 | DA35: =+CZ35*AK35 -> 83.314429 | DB35: =+CZ35-DA35 -> 794.71429 | DC35: =+DB35*AK35 -> 75.408885 | DD35: =+DB35-DC35 -> 719.30541 | DE35: =IF((DD35-(DD35*$AK$32))>$E35*5%,DD35*$AK$32,DD35-($E35*5%)) -> 68.25522 | DF35: =+DD35-DE35 -> 651.05019 | DG35: =IF((DF35-(DF35*$AK$32))>$E35*5%,DF35*$AK$32,DF35-($E35*5%)) -> 23.550186 | DH35: =+DF35-DG35 -> 627.5 | DI35: =IF((DH35-(DH35*$AK$32))>$E35*5%,DH35*$AK$32,DH35-($E35*5%)) -> 0 | DJ35: =+DH35-DI35 -> 627.5 | DK35: =IF((DJ35-(DJ35*$AK$32))>$E35*5%,DJ35*$AK$32,DJ35-($E35*5%)) -> 0 | DL35: =+DJ35-DK35 -> 627.5 | DM35: =IF((DL35-(DL35*$AK$32))>$E35*5%,DL35*$AK$32,DL35-($E35*5%)) -> 0 | DN35: =+DL35-DM35 -> 627.5 | DP35: =+DN35-DO35 -> 627.5 | DR35: =+DP35-DQ35 -> 627.5 | DT35: =+DR35-DS35 -> 627.5 | DW35: =+E35*5% -> 627.5 | DX35: =+DW35-DR35 -> 0
